Workbook

Sheet README
B2: REAL ESTATE FEASIBILITY ENGINE
B3: What it is | C3: An adaptive feasibility model: describe the project with rules (quarters, curves, payment plans) and the engine builds every quarter itself.
B4: Sheets | C4: DASHBOARD (one-page summary) → STRESS (live what-if tables) → INPUTS (everything you type) → TIMELINE (calendar, Gantt & on/off flags) → CURVES (quarterly % for sales, construction & every cost head) → COLLECTIONS (bookings → CLP cash received) → CASHFLOW (outflows, net cash, IRR, NPV) → OUTPUT (revenue, cost, P&L, JV split, key metrics) → LISTS (dropdown sources & conversions).
B6: HOW TO USE
B7: 1. Type only in inputs | C7: Blue-on-yellow cells. Black cells are formulas – never overwrite them.
B8: 2. Quarters | C8: All timing is a quarter number from the project start (Q1). Type 3 → shows Q3.
B9: 3. Products | C9: One row per product with zone and category. Category decides which construction cost head it lands in. Project type (Villa / Apartments / Plotted / Mixed) automatically switches off products of other zones.
B10: 4. Product timing | C10: Section 5B: each product's launch and construction start can be a fixed quarter, or linked to another product's launch / sales end / construction start / 50% / end.
B11: 5. Cost heads | C11: All 21 standard heads + 3 spare rows. Each has an Applicable switch, its own calculation and a phasing curve.
B12: 6. Payment plans | C12: Milestones tied to booking or construction %, so they move automatically with the schedule.
B13: 7. Scenarios | C13: One dropdown switches Best / Base / Worst case.
B14: 8. Checks | C14: INPUTS must show ✔ ALL CHECKS PASSED before results are used.
B15: 9. Stress tests | C15: STRESS sheet tables re-run the whole model automatically. If Excel is slow: Formulas → Calculation Options → Automatic except for Data Tables, then F9.
B17: COLOUR CODE
B18: Blue on yellow | C18: Input
B19: Black | C19: Formula
B20: Green | C20: Link from another sheet
B22: ROADMAP
B23: Step 1 ✔ | C23: Inputs, cost heads, calculators, output statements
B24: Step 2 ✔ | C24: Timeline engine (TIMELINE sheet: 40 self-switching quarter columns + Gantt)
B25: Step 3 ✔ | C25: Curve engine (CURVES sheet: curve names → quarterly %, always 100%)
B26: Step 4 ✔ | C26: COLLECTIONS sheet: bookings, CLP milestone triggers, catch-up, collections, LO/developer split
B27: Step 5 ✔ | C27: CASHFLOW sheet: outflows, landowner payments, project & developer cash flow, IRR, NPV, peak investment, break-even, FY summary
B28: Step 6 ✔ | C28: DASHBOARD sheet: KPI tiles with benchmark colours, auto-written takeaways, 6 charts incl. Gantt
B29: Step 7 ✔ | C29: STRESS sheet: scenario comparison, price / cost / speed / delay sensitivities, 2-way grids, headroom
B31: Disclaimer | C31: Illustrative sample figures. Tax, stamp duty, BAR and regulatory rates must be verified before real use.

Sheet DASHBOARD
B2: =INPUTS!$C$17&" — FEASIBILITY DASHBOARD" -> Project Aurora (Sample) — FEASIBILITY DASHBOARD
B3: =INPUTS!$C$18&" | "&INPUTS!$C$19&" | "&INPUTS!$C$21&" deal | Scenario: "&INPUTS!$C$23&" | "&TEXT(INPUTS!$C$39,"0.0")&" acres, "&TEXT(INPUTS!$F$98,"#,##0")&" sq ft saleable | "&TEXT(INPUTS!$C$20,"mmm yyyy")&" – "&TEXT(INPUTS!$C$30,"mmm yyyy") -> Sample City, Rajasthan | Mixed Development | JV deal | Scenario: Base Case | 6.2 acres, 920,000 sq ft saleable | Jun 2027 – Mar 2032
B4: =INPUTS!$C$7 -> ✔ ALL CHECKS PASSED
B6: GDV (total revenue) | F6: Total cost | J6: EBITDA | N6: PAT
B7: =OUTPUT!$D$23 -> 803 | F7: =OUTPUT!$D$51 -> 630.60532 | J7: =OUTPUT!$D$58 -> 172.39468 | N7: =OUTPUT!$D$60 -> 127.57206
B8: ="₹ "&TEXT(INPUTS!$T$98*INPUTS!$C$25/MAX(1,INPUTS!$F$98),"#,##0")&" per sq ft" -> ₹ 8,728 per sq ft | F8: =TEXT(OUTPUT!$F$51,"0.0%")&" of GDV" -> 78.5% of GDV | J8: =TEXT(OUTPUT!$F$58,"0.0%")&" margin · benchmark "&TEXT(INPUTS!$C$434,"0%") -> 21.5% margin · benchmark 20% | N8: =TEXT(OUTPUT!$F$60,"0.0%")&" margin · tax "&TEXT(INPUTS!$C$425,"0.0%") -> 15.9% margin · tax 26.0%
B10: Developer IRR (pre-tax) | F10: Project IRR | J10: Developer NPV | N10: Equity multiple
B11: =CASHFLOW!$C$69 -> 1.1017638 | F11: =CASHFLOW!$C$67 -> 4.490612 | J11: =CASHFLOW!$C$72 -> 90.628114 | N11: =OUTPUT!$D$75 -> 1.4732968
B12: ="Benchmark "&TEXT(INPUTS!$C$429,"0%")&" · post-tax ≈ "&IFERROR(TEXT(CASHFLOW!$C$70,"0%"),"n/a") -> Benchmark 18% · post-tax ≈ 84% | F12: ="Benchmark "&TEXT(INPUTS!$C$428,"0%")&" · before landowner share" -> Benchmark 22% · before landowner share | J12: ="@ "&TEXT(INPUTS!$C$426,"0%")&" cost of equity" -> @ 18% cost of equity | N12: ="Benchmark "&TEXT(INPUTS!$C$430,"0.0")&"x · cash multiple "&TEXT(CASHFLOW!$C$83,"0.0")&"x" -> Benchmark 2.0x · cash multiple 4.4x
B14: Peak investment | F14: Payback (developer) | J14: ROCE (annualised) | N14: CAGR
B15: =CASHFLOW!$C$73 -> 34.287321 | F15: =CASHFLOW!$C$81 -> Q8 | J15: =OUTPUT!$D$78 -> 1.2009637 | N15: =OUTPUT!$D$80 -> 0.40338456
B16: ="Reached in "&CASHFLOW!$C$74&IF(CASHFLOW!$C$73>0," ("&TEXT(CASHFLOW!$C$75,"mmm yy")&")","") -> Reached in Q2 (Sep 27) | F16: =IF(CASHFLOW!$C$81="never","Cash never recovered",TEXT(CASHFLOW!$C$82,"mmm yyyy")&" · first +ve quarter "&CASHFLOW!$C$79) -> Mar 2029 · first +ve quarter Q3 | J16: ="Benchmark "&TEXT(INPUTS!$C$431,"0%")&" · on initial investment" -> Benchmark 30% · on initial investment | N16: ="Benchmark "&TEXT(INPUTS!$C$432,"0%")&" · over "&TEXT(INPUTS!$C$32,"0.0")&" yrs" -> Benchmark 30% · over 5.0 yrs
B17: Green = beats the benchmark set in INPUTS Section 9; amber = review.
B18: KEY TAKEAWAYS (auto-written from the model)
B19: ="1. The project generates ₹"&TEXT(OUTPUT!$D$23,"#,##0")&" Cr of revenue against ₹"&TEXT(OUTPUT!$D$51,"#,##0")&" Cr of cost – EBITDA ₹"&TEXT(OUTPUT!$D$58,"#,##0")&" Cr ("&TEXT(OUTPUT!$F$58,"0.0%")&") and PAT ₹"&TEXT(OUTPUT!$D$60,"#,##0")&" Cr ("&TEXT(OUTPUT!$F$60,"0.0%")&")." -> 1. The project generates ₹803 Cr of revenue against ₹631 Cr of cost – EBITDA ₹172 Cr (21.5%) and PAT ₹128 Cr (15.9%).
B20: ="2. The developer earns a pre-tax IRR of "&IFERROR(TEXT(CASHFLOW!$C$69,"0%"),"n/a")&" against an "&TEXT(INPUTS!$C$429,"0%")&" hurdle, with an NPV of ₹"&TEXT(CASHFLOW!$C$72,"#,##0.0")&" Cr at the "&TEXT(INPUTS!$C$426,"0%")&" cost of equity." -> 2. The developer earns a pre-tax IRR of 110% against an 18% hurdle, with an NPV of ₹90.6 Cr at the 18% cost of equity.
B21: ="3. Maximum funding needed is ₹"&TEXT(CASHFLOW!$C$73,"#,##0.0")&" Cr ("&CASHFLOW!$C$74&"); the developer gets all of it back by "&CASHFLOW!$C$81&IF(CASHFLOW!$C$81="never",""," ("&TEXT(CASHFLOW!$C$82,"mmm yyyy")&")")&IF(INPUTS!$C$21="JV"," – construction is largely funded by customer collections."," – most of this peak is the land payment, made before customer collections build up.") -> 3. Maximum funding needed is ₹34.3 Cr (Q2); the developer gets all of it back by Q8 (Mar 2029) – construction is largely funded by customer collections.
B22: =IF(INPUTS!$C$21="JV","4. The landowner receives ₹"&TEXT(INPUTS!$G$128,"#,##0.0")&" Cr ("&TEXT(INPUTS!$C$45,"0%")&" revenue share) – about ₹"&TEXT(INPUTS!$D$65,"#,##0")&" per sq yd, "&TEXT(INPUTS!$D$66,"0%")&" above today's market rate – paid out of collections after his ₹"&TEXT(INPUTS!$C$189*INPUTS!$C$55,"#,##0.0")&" Cr advance is recovered.","4. Outright deal: land of ₹"&TEXT(INPUTS!$G$128,"#,##0.0")&" Cr is paid as per the land payment schedule, which is why peak funding is high.") -> 4. The landowner receives ₹257.0 Cr (32% revenue share) – about ₹85,653 per sq yd, 43% above today's market rate – paid out of collections after his ₹18.0 Cr advance is recovered.
B88: CHART DATA (linked – do not edit)
B89: Cost group | D89: ₹ Cr
B90: Land / landowner share | D90: =INPUTS!$G$128+INPUTS!$G$129+INPUTS!$G$130 -> 259.98075
B91: Construction | D91: =INPUTS!$G$153 -> 270.4
B92: Marketing & sales | D92: =INPUTS!$G$139 -> 56.21
B93: Corporate overheads | D93: =INPUTS!$G$138 -> 32.12
B94: Approvals, legal & BAR | D94: =INPUTS!$G$140+INPUTS!$G$148 -> 10.054574
B95: Other (EWS, contingency, EDC, GST, AIF…) | D95: =INPUTS!$G$152-SUM(D90:D94) -> 1.84
B97: Revenue by type | D97: ₹ Cr
B98: =SUBSTITUTE(INPUTS!$B$119," saleable area","") -> Residential | D98: =INPUTS!$F$119 -> 725
B99: =SUBSTITUTE(INPUTS!$B$120," saleable area","") -> Commercial | D99: =INPUTS!$F$120 -> 42
B100: =SUBSTITUTE(INPUTS!$B$121," saleable area","") -> Studio | D100: =INPUTS!$F$121 -> 36
B101: =SUBSTITUTE(INPUTS!$B$122," saleable area","") -> Institutional | D101: =INPUTS!$F$122 -> 0
B102: =SUBSTITUTE(INPUTS!$B$123," saleable area","") -> EWS / LIG area | D102: =INPUTS!$F$123 -> 0
B104: Timeline (Gantt) – included products only | D104: Offset | E104: Selling | F104: Building | H104: # included up to row
B105: =IF(COUNTIF(INPUTS!$E$88:$E$97,"Yes")>=1,INDEX(INPUTS!$B$88:$B$97,MATCH(1,$H$105:$H$114,0))&" – selling","") -> Villas – selling | D105: =IF(COUNTIF(INPUTS!$E$88:$E$97,"Yes")>=1,INDEX(INPUTS!$P$88:$P$97,MATCH(1,$H$105:$H$114,0))-1,0) -> 2 | E105: =IF(COUNTIF(INPUTS!$E$88:$E$97,"Yes")>=1,INDEX(INPUTS!$Q$88:$Q$97,MATCH(1,$H$105:$H$114,0))-INDEX(INPUTS!$P$88:$P$97,MATCH(1,$H$105:$H$114,0))+1,0) -> 8 | F105: =0 -> 0 | H105: =COUNTIF(INPUTS!$E$88:$E$88,"Yes") -> 1
B106: =IF(COUNTIF(INPUTS!$E$88:$E$97,"Yes")>=1,INDEX(INPUTS!$B$88:$B$97,MATCH(1,$H$105:$H$114,0))&" – building","") -> Villas – building | D106: =IF(COUNTIF(INPUTS!$E$88:$E$97,"Yes")>=1,INDEX(INPUTS!$R$88:$R$97,MATCH(1,$H$105:$H$114,0))-1,0) -> 3 | E106: =0 -> 0 | F106: =IF(COUNTIF(INPUTS!$E$88:$E$97,"Yes")>=1,INDEX(INPUTS!$S$88:$S$97,MATCH(1,$H$105:$H$114,0))-INDEX(INPUTS!$R$88:$R$97,MATCH(1,$H$105:$H$114,0))+1,0) -> 12 | H106: =COUNTIF(INPUTS!$E$88:$E$89,"Yes") -> 2
B107: =IF(COUNTIF(INPUTS!$E$88:$E$97,"Yes")>=2,INDEX(INPUTS!$B$88:$B$97,MATCH(2,$H$105:$H$114,0))&" – selling","") -> Apartments – Towers A & B – selling | D107: =IF(COUNTIF(INPUTS!$E$88:$E$97,"Yes")>=2,INDEX(INPUTS!$P$88:$P$97,MATCH(2,$H$105:$H$114,0))-1,0) -> 3 | E107: =IF(COUNTIF(INPUTS!$E$88:$E$97,"Yes")>=2,INDEX(INPUTS!$Q$88:$Q$97,MATCH(2,$H$105:$H$114,0))-INDEX(INPUTS!$P$88:$P$97,MATCH(2,$H$105:$H$114,0))+1,0) -> 12 | F107: =0 -> 0 | H107: =COUNTIF(INPUTS!$E$88:$E$90,"Yes") -> 3
B108: =IF(COUNTIF(INPUTS!$E$88:$E$97,"Yes")>=2,INDEX(INPUTS!$B$88:$B$97,MATCH(2,$H$105:$H$114,0))&" – building","") -> Apartments – Towers A & B – building | D108: =IF(COUNTIF(INPUTS!$E$88:$E$97,"Yes")>=2,INDEX(INPUTS!$R$88:$R$97,MATCH(2,$H$105:$H$114,0))-1,0) -> 4 | E108: =0 -> 0 | F108: =IF(COUNTIF(INPUTS!$E$88:$E$97,"Yes")>=2,INDEX(INPUTS!$S$88:$S$97,MATCH(2,$H$105:$H$114,0))-INDEX(INPUTS!$R$88:$R$97,MATCH(2,$H$105:$H$114,0))+1,0) -> 16 | H108: =COUNTIF(INPUTS!$E$88:$E$91,"Yes") -> 4
B109: =IF(COUNTIF(INPUTS!$E$88:$E$97,"Yes")>=3,INDEX(INPUTS!$B$88:$B$97,MATCH(3,$H$105:$H$114,0))&" – selling","") -> Studios – selling | D109: =IF(COUNTIF(INPUTS!$E$88:$E$97,"Yes")>=3,INDEX(INPUTS!$P$88:$P$97,MATCH(3,$H$105:$H$114,0))-1,0) -> 5 | E109: =IF(COUNTIF(INPUTS!$E$88:$E$97,"Yes")>=3,INDEX(INPUTS!$Q$88:$Q$97,MATCH(3,$H$105:$H$114,0))-INDEX(INPUTS!$P$88:$P$97,MATCH(3,$H$105:$H$114,0))+1,0) -> 8 | F109: =0 -> 0 | H109: =COUNTIF(INPUTS!$E$88:$E$92,"Yes") -> 4
B110: =IF(COUNTIF(INPUTS!$E$88:$E$97,"Yes")>=3,INDEX(INPUTS!$B$88:$B$97,MATCH(3,$H$105:$H$114,0))&" – building","") -> Studios – building | D110: =IF(COUNTIF(INPUTS!$E$88:$E$97,"Yes")>=3,INDEX(INPUTS!$R$88:$R$97,MATCH(3,$H$105:$H$114,0))-1,0) -> 5 | E110: =0 -> 0 | F110: =IF(COUNTIF(INPUTS!$E$88:$E$97,"Yes")>=3,INDEX(INPUTS!$S$88:$S$97,MATCH(3,$H$105:$H$114,0))-INDEX(INPUTS!$R$88:$R$97,MATCH(3,$H$105:$H$114,0))+1,0) -> 12 | H110: =COUNTIF(INPUTS!$E$88:$E$93,"Yes") -> 4
B111: =IF(COUNTIF(INPUTS!$E$88:$E$97,"Yes")>=4,INDEX(INPUTS!$B$88:$B$97,MATCH(4,$H$105:$H$114,0))&" – selling","") -> High-street retail – selling | D111: =IF(COUNTIF(INPUTS!$E$88:$E$97,"Yes")>=4,INDEX(INPUTS!$P$88:$P$97,MATCH(4,$H$105:$H$114,0))-1,0) -> 7 | E111: =IF(COUNTIF(INPUTS!$E$88:$E$97,"Yes")>=4,INDEX(INPUTS!$Q$88:$Q$97,MATCH(4,$H$105:$H$114,0))-INDEX(INPUTS!$P$88:$P$97,MATCH(4,$H$105:$H$114,0))+1,0) -> 8 | F111: =0 -> 0 | H111: =COUNTIF(INPUTS!$E$88:$E$94,"Yes") -> 4
B112: =IF(COUNTIF(INPUTS!$E$88:$E$97,"Yes")>=4,INDEX(INPUTS!$B$88:$B$97,MATCH(4,$H$105:$H$114,0))&" – building","") -> High-street retail – building | D112: =IF(COUNTIF(INPUTS!$E$88:$E$97,"Yes")>=4,INDEX(INPUTS!$R$88:$R$97,MATCH(4,$H$105:$H$114,0))-1,0) -> 5 | E112: =0 -> 0 | F112: =IF(COUNTIF(INPUTS!$E$88:$E$97,"Yes")>=4,INDEX(INPUTS!$S$88:$S$97,MATCH(4,$H$105:$H$114,0))-INDEX(INPUTS!$R$88:$R$97,MATCH(4,$H$105:$H$114,0))+1,0) -> 12 | H112: =COUNTIF(INPUTS!$E$88:$E$95,"Yes") -> 4
B113: =IF(COUNTIF(INPUTS!$E$88:$E$97,"Yes")>=5,INDEX(INPUTS!$B$88:$B$97,MATCH(5,$H$105:$H$114,0))&" – selling","") | D113: =IF(COUNTIF(INPUTS!$E$88:$E$97,"Yes")>=5,INDEX(INPUTS!$P$88:$P$97,MATCH(5,$H$105:$H$114,0))-1,0) -> 0 | E113: =IF(COUNTIF(INPUTS!$E$88:$E$97,"Yes")>=5,INDEX(INPUTS!$Q$88:$Q$97,MATCH(5,$H$105:$H$114,0))-INDEX(INPUTS!$P$88:$P$97,MATCH(5,$H$105:$H$114,0))+1,0) -> 0 | F113: =0 -> 0 | H113: =COUNTIF(INPUTS!$E$88:$E$96,"Yes") -> 4
B114: =IF(COUNTIF(INPUTS!$E$88:$E$97,"Yes")>=5,INDEX(INPUTS!$B$88:$B$97,MATCH(5,$H$105:$H$114,0))&" – building","") | D114: =IF(COUNTIF(INPUTS!$E$88:$E$97,"Yes")>=5,INDEX(INPUTS!$R$88:$R$97,MATCH(5,$H$105:$H$114,0))-1,0) -> 0 | E114: =0 -> 0 | F114: =IF(COUNTIF(INPUTS!$E$88:$E$97,"Yes")>=5,INDEX(INPUTS!$S$88:$S$97,MATCH(5,$H$105:$H$114,0))-INDEX(INPUTS!$R$88:$R$97,MATCH(5,$H$105:$H$114,0))+1,0) -> 0 | H114: =COUNTIF(INPUTS!$E$88:$E$97,"Yes") -> 4
B115: =IF(COUNTIF(INPUTS!$E$88:$E$97,"Yes")>=6,INDEX(INPUTS!$B$88:$B$97,MATCH(6,$H$105:$H$114,0))&" – selling","") | D115: =IF(COUNTIF(INPUTS!$E$88:$E$97,"Yes")>=6,INDEX(INPUTS!$P$88:$P$97,MATCH(6,$H$105:$H$114,0))-1,0) -> 0 | E115: =IF(COUNTIF(INPUTS!$E$88:$E$97,"Yes")>=6,INDEX(INPUTS!$Q$88:$Q$97,MATCH(6,$H$105:$H$114,0))-INDEX(INPUTS!$P$88:$P$97,MATCH(6,$H$105:$H$114,0))+1,0) -> 0 | F115: =0 -> 0
B116: =IF(COUNTIF(INPUTS!$E$88:$E$97,"Yes")>=6,INDEX(INPUTS!$B$88:$B$97,MATCH(6,$H$105:$H$114,0))&" – building","") | D116: =IF(COUNTIF(INPUTS!$E$88:$E$97,"Yes")>=6,INDEX(INPUTS!$R$88:$R$97,MATCH(6,$H$105:$H$114,0))-1,0) -> 0 | E116: =0 -> 0 | F116: =IF(COUNTIF(INPUTS!$E$88:$E$97,"Yes")>=6,INDEX(INPUTS!$S$88:$S$97,MATCH(6,$H$105:$H$114,0))-INDEX(INPUTS!$R$88:$R$97,MATCH(6,$H$105:$H$114,0))+1,0) -> 0
B117: =IF(COUNTIF(INPUTS!$E$88:$E$97,"Yes")>=7,INDEX(INPUTS!$B$88:$B$97,MATCH(7,$H$105:$H$114,0))&" – selling","") | D117: =IF(COUNTIF(INPUTS!$E$88:$E$97,"Yes")>=7,INDEX(INPUTS!$P$88:$P$97,MATCH(7,$H$105:$H$114,0))-1,0) -> 0 | E117: =IF(COUNTIF(INPUTS!$E$88:$E$97,"Yes")>=7,INDEX(INPUTS!$Q$88:$Q$97,MATCH(7,$H$105:$H$114,0))-INDEX(INPUTS!$P$88:$P$97,MATCH(7,$H$105:$H$114,0))+1,0) -> 0 | F117: =0 -> 0
B118: =IF(COUNTIF(INPUTS!$E$88:$E$97,"Yes")>=7,INDEX(INPUTS!$B$88:$B$97,MATCH(7,$H$105:$H$114,0))&" – building","") | D118: =IF(COUNTIF(INPUTS!$E$88:$E$97,"Yes")>=7,INDEX(INPUTS!$R$88:$R$97,MATCH(7,$H$105:$H$114,0))-1,0) -> 0 | E118: =0 -> 0 | F118: =IF(COUNTIF(INPUTS!$E$88:$E$97,"Yes")>=7,INDEX(INPUTS!$S$88:$S$97,MATCH(7,$H$105:$H$114,0))-INDEX(INPUTS!$R$88:$R$97,MATCH(7,$H$105:$H$114,0))+1,0) -> 0
B119: =IF(COUNTIF(INPUTS!$E$88:$E$97,"Yes")>=8,INDEX(INPUTS!$B$88:$B$97,MATCH(8,$H$105:$H$114,0))&" – selling","") | D119: =IF(COUNTIF(INPUTS!$E$88:$E$97,"Yes")>=8,INDEX(INPUTS!$P$88:$P$97,MATCH(8,$H$105:$H$114,0))-1,0) -> 0 | E119: =IF(COUNTIF(INPUTS!$E$88:$E$97,"Yes")>=8,INDEX(INPUTS!$Q$88:$Q$97,MATCH(8,$H$105:$H$114,0))-INDEX(INPUTS!$P$88:$P$97,MATCH(8,$H$105:$H$114,0))+1,0) -> 0 | F119: =0 -> 0
B120: =IF(COUNTIF(INPUTS!$E$88:$E$97,"Yes")>=8,INDEX(INPUTS!$B$88:$B$97,MATCH(8,$H$105:$H$114,0))&" – building","") | D120: =IF(COUNTIF(INPUTS!$E$88:$E$97,"Yes")>=8,INDEX(INPUTS!$R$88:$R$97,MATCH(8,$H$105:$H$114,0))-1,0) -> 0 | E120: =0 -> 0 | F120: =IF(COUNTIF(INPUTS!$E$88:$E$97,"Yes")>=8,INDEX(INPUTS!$S$88:$S$97,MATCH(8,$H$105:$H$114,0))-INDEX(INPUTS!$R$88:$R$97,MATCH(8,$H$105:$H$114,0))+1,0) -> 0
B121: =IF(COUNTIF(INPUTS!$E$88:$E$97,"Yes")>=9,INDEX(INPUTS!$B$88:$B$97,MATCH(9,$H$105:$H$114,0))&" – selling","") | D121: =IF(COUNTIF(INPUTS!$E$88:$E$97,"Yes")>=9,INDEX(INPUTS!$P$88:$P$97,MATCH(9,$H$105:$H$114,0))-1,0) -> 0 | E121: =IF(COUNTIF(INPUTS!$E$88:$E$97,"Yes")>=9,INDEX(INPUTS!$Q$88:$Q$97,MATCH(9,$H$105:$H$114,0))-INDEX(INPUTS!$P$88:$P$97,MATCH(9,$H$105:$H$114,0))+1,0) -> 0 | F121: =0 -> 0
B122: =IF(COUNTIF(INPUTS!$E$88:$E$97,"Yes")>=9,INDEX(INPUTS!$B$88:$B$97,MATCH(9,$H$105:$H$114,0))&" – building","") | D122: =IF(COUNTIF(INPUTS!$E$88:$E$97,"Yes")>=9,INDEX(INPUTS!$R$88:$R$97,MATCH(9,$H$105:$H$114,0))-1,0) -> 0 | E122: =0 -> 0 | F122: =IF(COUNTIF(INPUTS!$E$88:$E$97,"Yes")>=9,INDEX(INPUTS!$S$88:$S$97,MATCH(9,$H$105:$H$114,0))-INDEX(INPUTS!$R$88:$R$97,MATCH(9,$H$105:$H$114,0))+1,0) -> 0
B123: =IF(COUNTIF(INPUTS!$E$88:$E$97,"Yes")>=10,INDEX(INPUTS!$B$88:$B$97,MATCH(10,$H$105:$H$114,0))&" – selling","") | D123: =IF(COUNTIF(INPUTS!$E$88:$E$97,"Yes")>=10,INDEX(INPUTS!$P$88:$P$97,MATCH(10,$H$105:$H$114,0))-1,0) -> 0 | E123: =IF(COUNTIF(INPUTS!$E$88:$E$97,"Yes")>=10,INDEX(INPUTS!$Q$88:$Q$97,MATCH(10,$H$105:$H$114,0))-INDEX(INPUTS!$P$88:$P$97,MATCH(10,$H$105:$H$114,0))+1,0) -> 0 | F123: =0 -> 0
B124: =IF(COUNTIF(INPUTS!$E$88:$E$97,"Yes")>=10,INDEX(INPUTS!$B$88:$B$97,MATCH(10,$H$105:$H$114,0))&" – building","") | D124: =IF(COUNTIF(INPUTS!$E$88:$E$97,"Yes")>=10,INDEX(INPUTS!$R$88:$R$97,MATCH(10,$H$105:$H$114,0))-1,0) -> 0 | E124: =0 -> 0 | F124: =IF(COUNTIF(INPUTS!$E$88:$E$97,"Yes")>=10,INDEX(INPUTS!$S$88:$S$97,MATCH(10,$H$105:$H$114,0))-INDEX(INPUTS!$R$88:$R$97,MATCH(10,$H$105:$H$114,0))+1,0) -> 0

Sheet STRESS
B2: STRESS TESTING — how the deal holds up when things go wrong
B3: Tables below are live Excel Data Tables: each cell re-runs the WHOLE model with the lever value shown. Keep the levers at neutral – the tables flex them automatically.
B4: If Excel feels slow: Formulas → Calculation Options → 'Automatic except for Data Tables', then press F9 to refresh the tables.
B6: A. STRESS LEVERS (inputs – keep at neutral: 0%, 0%, 1.00x, 0, 0)
B7: Lever | C7: Value | D7: Neutral | E7: What it does
B8: Sales price shock | C8: 0 | D8: 0% | E8: Changes every product's sales rate (on top of the scenario)
B9: Construction cost shock | C9: 0 | D9: 0% | E9: Changes every product's construction rate
B10: Sales period multiplier | C10: 1 | D10: 1.00x | E10: 1.5x = every product takes 50% longer to sell
B11: Extra delay (quarters) | C11: 0 | D11: 0 | E11: Pushes every fixed launch & construction start later
B12: Scenario override (0 = use INPUTS) | C12: 0 | D12: 0 | E12: 1 = Best, 2 = Base, 3 = Worst – used by the scenario table
B13: Output selector (technical – keep 1) | C13: 1 | D13: 1 | E13: Lets one table show several outputs; does not change the model
B14: Levers status | C14: =IF(AND($C$8=0,$C$9=0,$C$10=1,$C$11=0,$C$12=0),"Neutral","ACTIVE") -> Neutral
B16: B. SCENARIO COMPARISON – Best / Base / Worst side by side (scenario table in INPUTS Section 3)
B17: Current model → | C17: =OUTPUT!$D$23 -> 803 | D17: =OUTPUT!$D$51 -> 630.60532 | E17: =CASHFLOW!$C$69 -> 1.1017638 | F17: =CASHFLOW!$C$72 -> 90.628114 | G17: =OUTPUT!$D$60 -> 127.57206 | H17: =OUTPUT!$F$60 -> 0.15886932 | I17: =OUTPUT!$D$58 -> 172.39468 | J17: =CASHFLOW!$C$73 -> 34.287321 | K17: =CASHFLOW!$C$81 -> Q8 | L17: =OUTPUT!$D$75 -> 1.4732968
B18: Scenario # | C18: GDV (₹ Cr) | D18: Total cost (₹ Cr) | E18: Developer IRR | F18: Developer NPV (₹ Cr) | G18: PAT (₹ Cr) | H18: PAT margin | I18: EBITDA (₹ Cr) | J18: Peak investment (₹ Cr) | K18: Payback | L18: Equity multiple
B19: =CHOOSE($C$13,OUTPUT!$D$23,OUTPUT!$D$51,CASHFLOW!$C$69,CASHFLOW!$C$72,OUTPUT!$D$60,OUTPUT!$F$60,OUTPUT!$D$58,CASHFLOW!$C$73,CASHFLOW!$C$81,OUTPUT!$D$75) -> 803 | C19: 1 | D19: 2 | E19: 3 | F19: 4 | G19: 5 | H19: 6 | I19: 7 | J19: 8 | K19: 9 | L19: 10
B20: 1 | C20: 843.15 | D20: 647.86982 | E20: 1.5076016 | F20: 111.45569 | G20: 144.50733 | H20: 0.17138983 | I20: 195.28018 | J20: 34.447921 | K20: Q7 | L20: 1.5287446
B21: 2 | C21: 803 | D21: 630.60532 | E21: 1.1017638 | F21: 90.628114 | G21: 127.57206 | H21: 0.15886932 | I21: 172.39468 | J21: 34.287321 | K21: Q8 | L21: 1.4732968
B22: 3 | C22: 742.775 | D22: 624.98857 | E22: 0.40241041 | F22: 35.767409 | G22: 87.161958 | H22: 0.11734638 | I22: 117.78643 | J22: 36.360196 | K22: Q18 | L22: 1.3143729
B24: C1. PRICE SENSITIVITY – sales price shock
B25: Current model → | C25: =CASHFLOW!$C$69 -> 1.1017638 | D25: =CASHFLOW!$C$72 -> 90.628114 | E25: =OUTPUT!$D$60 -> 127.57206 | F25: =OUTPUT!$F$60 -> 0.15886932 | G25: =OUTPUT!$D$58 -> 172.39468 | H25: =CASHFLOW!$C$73 -> 34.287321 | I25: =CASHFLOW!$C$81 -> Q8
B26: Lever value | C26: Developer IRR | D26: Developer NPV (₹ Cr) | E26: PAT (₹ Cr) | F26: PAT margin | G26: EBITDA (₹ Cr) | H26: Peak investment (₹ Cr) | I26: Payback
B27: =CHOOSE($C$13,CASHFLOW!$C$69,CASHFLOW!$C$72,OUTPUT!$D$60,OUTPUT!$F$60,OUTPUT!$D$58,CASHFLOW!$C$73,CASHFLOW!$C$81) -> 1.1017638 | C27: 1 | D27: 2 | E27: 3 | F27: 4 | G27: 5 | H27: 6 | I27: 7
B28: -0.15 | C28: 0.73101435 | D28: 49.224078 | E28: 76.766253 | F28: 0.11246979 | G28: 103.73818 | H28: 33.805521 | I28: Q10
B29: -0.1 | C29: 0.86152253 | D29: 63.025423 | E29: 93.701523 | F29: 0.1296548 | G29: 126.62368 | H29: 33.966121 | I29: Q8
B30: -0.05 | C30: 0.98472309 | D30: 76.826768 | E30: 110.63679 | F30: 0.14503086 | G30: 149.50918 | H30: 34.126721 | I30: Q8
B31: 0 | C31: 1.1017638 | D31: 90.628114 | E31: 127.57206 | F31: 0.15886932 | G31: 172.39468 | H31: 34.287321 | I31: Q8
B32: 0.05 | C32: 1.2135404 | D32: 104.42946 | E32: 144.50733 | F32: 0.17138983 | G32: 195.28018 | H32: 34.447921 | I32: Q8
B33: 0.1 | C33: 1.3207605 | D33: 118.2308 | E33: 161.4426 | F33: 0.18277211 | G33: 218.16568 | H33: 34.608521 | I33: Q8
B34: 0.15 | C34: 1.4223881 | D34: 132.01644 | E34: 178.37787 | F34: 0.19316462 | G34: 241.05118 | H34: 34.769121 | I34: Q8
B36: C2. CONSTRUCTION COST SENSITIVITY – cost overrun
B37: Current model → | C37: =CASHFLOW!$C$69 -> 1.1017638 | D37: =CASHFLOW!$C$72 -> 90.628114 | E37: =OUTPUT!$D$60 -> 127.57206 | F37: =OUTPUT!$F$60 -> 0.15886932 | G37: =OUTPUT!$D$58 -> 172.39468 | H37: =CASHFLOW!$C$73 -> 34.287321 | I37: =CASHFLOW!$C$81 -> Q8
B38: Lever value | C38: Developer IRR | D38: Developer NPV (₹ Cr) | E38: PAT (₹ Cr) | F38: PAT margin | G38: EBITDA (₹ Cr) | H38: Peak investment (₹ Cr) | I38: Payback
B39: =CHOOSE($C$13,CASHFLOW!$C$69,CASHFLOW!$C$72,OUTPUT!$D$60,OUTPUT!$F$60,OUTPUT!$D$58,CASHFLOW!$C$73,CASHFLOW!$C$81) -> 1.1017638 | C39: 1 | D39: 2 | E39: 3 | F39: 4 | G39: 5 | H39: 6 | I39: 7
B40: -0.05 | C40: 1.1781589 | D40: 99.077332 | E40: 137.57686 | F40: 0.1713286 | G40: 185.91468 | H40: 34.287321 | I40: Q8
B41: 0 | C41: 1.1017638 | D41: 90.628114 | E41: 127.57206 | F41: 0.15886932 | G41: 172.39468 | H41: 34.287321 | I41: Q8
B42: 0.05 | C42: 1.0237829 | D42: 82.178895 | E42: 117.56726 | F42: 0.14641004 | G42: 158.87468 | H42: 34.287321 | I42: Q8
B43: 0.1 | C43: 0.94413312 | D43: 73.729677 | E43: 107.56246 | F43: 0.13395076 | G43: 145.35468 | H43: 34.287321 | I43: Q8
B44: 0.15 | C44: 0.86273903 | D44: 65.280459 | E44: 97.557663 | F44: 0.12149149 | G44: 131.83468 | H44: 34.287321 | I44: Q8
B45: 0.2 | C45: 0.77954188 | D45: 56.83124 | E45: 87.552863 | F45: 0.10903221 | G45: 118.31468 | H45: 34.287321 | I45: Q10
B47: C3. SALES SPEED SENSITIVITY – how long products take to sell
B48: Current model → | C48: =CASHFLOW!$C$69 -> 1.1017638 | D48: =CASHFLOW!$C$72 -> 90.628114 | E48: =OUTPUT!$D$60 -> 127.57206 | F48: =OUTPUT!$F$60 -> 0.15886932 | G48: =OUTPUT!$D$58 -> 172.39468 | H48: =CASHFLOW!$C$73 -> 34.287321 | I48: =CASHFLOW!$C$81 -> Q8
B49: Lever value | C49: Developer IRR | D49: Developer NPV (₹ Cr) | E49: PAT (₹ Cr) | F49: PAT margin | G49: EBITDA (₹ Cr) | H49: Peak investment (₹ Cr) | I49: Payback
B50: =CHOOSE($C$13,CASHFLOW!$C$69,CASHFLOW!$C$72,OUTPUT!$D$60,OUTPUT!$F$60,OUTPUT!$D$58,CASHFLOW!$C$73,CASHFLOW!$C$81) -> 1.1017638 | C50: 1 | D50: 2 | E50: 3 | F50: 4 | G50: 5 | H50: 6 | I50: 7
B51: 0.75 | C51: 1.3813142 | D51: 97.348012 | E51: 127.57206 | F51: 0.15886932 | G51: 172.39468 | H51: 34.287321 | I51: Q8
B52: 1 | C52: 1.1017638 | D52: 90.628114 | E52: 127.57206 | F52: 0.15886932 | G52: 172.39468 | H52: 34.287321 | I52: Q8
B53: 1.25 | C53: 0.88145054 | D53: 82.795184 | E53: 127.57206 | F53: 0.15886932 | G53: 172.39468 | H53: 34.393321 | I53: Q10
B54: 1.5 | C54: 0.71716266 | D54: 74.541284 | E54: 127.57206 | F54: 0.15886932 | G54: 172.39468 | H54: 34.394662 | I54: Q11
B55: 2 | C55: 0.50623043 | D55: 58.581605 | E55: 127.57206 | F55: 0.15886932 | G55: 172.39468 | H55: 35.370122 | I55: Q16
B57: C4. DELAY SENSITIVITY – approvals / launch slip
B58: Current model → | C58: =CASHFLOW!$C$69 -> 1.1017638 | D58: =CASHFLOW!$C$72 -> 90.628114 | E58: =OUTPUT!$D$60 -> 127.57206 | F58: =OUTPUT!$F$60 -> 0.15886932 | G58: =OUTPUT!$D$58 -> 172.39468 | H58: =CASHFLOW!$C$73 -> 34.287321 | I58: =CASHFLOW!$C$81 -> Q8
B59: Lever value | C59: Developer IRR | D59: Developer NPV (₹ Cr) | E59: PAT (₹ Cr) | F59: PAT margin | G59: EBITDA (₹ Cr) | H59: Peak investment (₹ Cr) | I59: Payback
B60: =CHOOSE($C$13,CASHFLOW!$C$69,CASHFLOW!$C$72,OUTPUT!$D$60,OUTPUT!$F$60,OUTPUT!$D$58,CASHFLOW!$C$73,CASHFLOW!$C$81) -> 1.1017638 | C60: 1 | D60: 2 | E60: 3 | F60: 4 | G60: 5 | H60: 6 | I60: 7
B61: 0 | C61: 1.1017638 | D61: 90.628114 | E61: 127.57206 | F61: 0.15886932 | G61: 172.39468 | H61: 34.287321 | I61: Q8
B62: 1 | C62: 0.91893369 | D62: 85.276766 | E62: 127.57206 | F62: 0.15886932 | G62: 172.39468 | H62: 35.663892 | I62: Q9
B63: 2 | C63: 0.79177086 | D63: 80.148134 | E63: 127.57206 | F63: 0.15886932 | G63: 172.39468 | H63: 36.915321 | I63: Q10
B64: 3 | C64: 0.69741689 | D64: 75.233082 | E64: 127.57206 | F64: 0.15886932 | G64: 172.39468 | H64: 38.05793 | I64: Q11
B65: 4 | C65: 0.62423894 | D65: 70.522846 | E65: 127.57206 | F65: 0.15886932 | G65: 172.39468 | H65: 39.105321 | I65: Q12
B66: 6 | C66: 0.51749208 | D66: 61.683547 | E66: 127.57206 | F66: 0.15886932 | G66: 172.39468 | H66: 40.958398 | I66: Q14
B68: D1. DEVELOPER IRR – price × construction cost
B69: Down: construction cost shock | Across: price shock
B70: =CASHFLOW!$C$69 -> 1.1017638 | C70: -0.1 | D70: -0.05 | E70: 0 | F70: 0.05 | G70: 0.1
B71: 0 | C71: 0.86152253 | D71: 0.98472309 | E71: 1.1017638 | F71: 1.2135404 | G71: 1.3207605
B72: 0.05 | C72: 0.77646902 | D72: 0.90346776 | E72: 1.0237829 | F72: 1.1384077 | G72: 1.2481282
B73: 0.1 | C73: 0.68928485 | D73: 0.82032474 | E73: 0.94413312 | F73: 1.0617951 | G73: 1.1741771
B74: 0.15 | C74: 0.59993669 | D74: 0.73522673 | E74: 0.86273903 | F74: 0.98362964 | G74: 1.0988403
B75: 0.2 | C75: 0.50846869 | D75: 0.64814263 | E75: 0.77954188 | F75: 0.90384521 | G75: 1.0220531
B77: D2. PAT (₹ Cr) – price × construction cost
B78: Down: construction cost shock | Across: price shock
B79: =OUTPUT!$D$60 -> 127.57206 | C79: -0.1 | D79: -0.05 | E79: 0 | F79: 0.05 | G79: 0.1
B80: 0 | C80: 93.701523 | D80: 110.63679 | E80: 127.57206 | F80: 144.50733 | G80: 161.4426
B81: 0.05 | C81: 83.696723 | D81: 100.63199 | E81: 117.56726 | F81: 134.50253 | G81: 151.4378
B82: 0.1 | C82: 73.691923 | D82: 90.627193 | E82: 107.56246 | F82: 124.49773 | G82: 141.433
B83: 0.15 | C83: 63.687123 | D83: 80.622393 | E83: 97.557663 | F83: 114.49293 | G83: 131.4282
B84: 0.2 | C84: 53.682323 | D84: 70.617593 | E84: 87.552863 | F84: 104.48813 | G84: 121.4234
B86: D3. PEAK INVESTMENT (₹ Cr) – sales speed × delay
B87: Down: sales period multiplier | Across: extra delay
B88: =CASHFLOW!$C$73 -> 34.287321 | C88: 0 | D88: 1 | E88: 2 | F88: 4
B89: 0.75 | C89: 34.287321 | D89: 35.663892 | E89: 36.915321 | F89: 39.105321
B90: 1 | C90: 34.287321 | D90: 35.663892 | E90: 36.915321 | F90: 39.105321
B91: 1.25 | C91: 34.393321 | D91: 35.693416 | E91: 36.915321 | F91: 39.105321
B92: 1.5 | C92: 34.394662 | D92: 35.64609 | E92: 36.788699 | F92: 38.79969
B93: 2 | C93: 35.370122 | D93: 35.964937 | E93: 36.523714 | F93: 37.809943
B95: E. HEADROOM – how much can go wrong before profit disappears
B96: Price fall that wipes out EBITDA | C96: =IFERROR(-G31/((G31-G28)/0.15),"n/a") -> -0.37664608 | D96: Price shock (all products) at which EBITDA reaches zero
B97: Construction overrun that wipes out EBITDA | C97: =IFERROR(G41/((G41-G45)/0.2),"n/a") -> 0.63755429 | D97: Construction cost shock at which EBITDA reaches zero
B98: Exact because EBITDA moves in a straight line with price and construction cost (read from the tables above).
B100: F. DEVELOPER IRR UNDER EACH STRESS
B101: Base case | C101: =C25 -> 1.1017638
B102: Price −10% | C102: =C29 -> 0.86152253
B103: Construction cost +10% | C103: =C43 -> 0.94413312
B104: Sales 1.5x slower | C104: =C54 -> 0.71716266
B105: Delay +2 quarters | C105: =C63 -> 0.79177086
B106: Worst Case scenario | C106: =E22 -> 0.40241041

Sheet INPUTS
B2: REAL ESTATE FEASIBILITY ENGINE — INPUT SHEET
B3: Amounts in ₹ Crore | Areas in sq ft unless stated | Q1 = project start quarter; all timing inputs are quarter numbers (type 3 → shows Q3)
B4: Legend: | C4: Blue on yellow = input | D4: Black = formula | E4: OK / ERROR
B6: 0. MODEL HEALTH
B7: Model status | C7: =IF(C8=0,IF(STRESS!$C$14="Neutral","✔ ALL CHECKS PASSED","⚠ CHECKS PASSED – but STRESS levers are active, results are stressed"),"✖ "&C8&" ERROR(S) – see Section 10") -> ✔ ALL CHECKS PASSED
B8: Number of errors | C8: =COUNTIF($C$438:$C$460,"ERROR") -> 0
B9: GDV (₹ Cr) | C9: =$T$98 -> 803
B10: Total cost (₹ Cr) | C10: =$G$152 -> 630.60532
B11: EBITDA margin | C11: =IF(C9>0,(C9-C10)/C9,0) -> 0.21468827
B12: PAT (₹ Cr) | C12: =(C9-C10)-MAX(0,C9-C10)*$C$425 -> 127.57206
B13: Full statements and key metrics are on the OUTPUT sheet.
B15: 1. PROJECT & TIMELINE
B16: Parameter | C16: Value | D16: Unit | E16: Notes
B17: Project name | C17: Project Aurora (Sample) | D17: Text | E17: Dummy project – illustrative figures only
B18: Location | C18: Sample City, Rajasthan | D18: Text
B19: Project type | C19: Mixed Development | D19: List | E19: Villa / Plotted / Apartments / Mixed Development
B20: Project start (quarter-end date) = Q1 | C20: 46568 | D20: Date | E20: 31-Mar, 30-Jun, 30-Sep or 31-Dec
B21: Deal type | C21: JV | D21: List | E21: JV = landowner revenue share | Outright = land bought for cash
B22: Taxable entity | C22: Company | D22: List | E22: Drives the tax rate (Section 9)
B23: Active scenario | C23: Base Case | D23: List | E23: Section 3
B24: Model horizon (quarters) | C24: 40 | D24: Quarters | E24: Engine length (40 = 10 years). Change only if the engine is extended
B25: Crore divisor | C25: 10000000 | D25: ₹ | E25: 1 Crore = 1,00,00,000 – unit constant
B26: Project lifecycle for ROCE / CAGR – override (optional) | D26: Years | E26: Leave blank to use the derived span below
B27: Derived
B28: Horizon end date | C28: =EOMONTH($C$20,3*($C$24-1)) -> 50130 | D28: Date
B29: Project last active quarter | C29: =MAX($Q$88:$Q$97,$S$88:$S$97) -> 20 | D29: Quarter | E29: Latest product sales-end / construction-end
B30: Project last active date | C30: =IF($C$29>0,EOMONTH($C$20,3*($C$29-1)),"") -> 48304 | D30: Date
B31: Project span (years) | C31: =$C$29/4 -> 5 | D31: Years
B32: Project lifecycle used for ROCE / CAGR | C32: =IF(ISNUMBER($C$26),$C$26,$C$31) -> 5 | D32: Years
B34: 2. LAND
B35: Parameter | C35: Value | D35: Unit | E35: Notes
B36: Land area | C36: 30000 | D36: Sq yd | E36: As per title / sale deed
B37: Land area | C37: =$C$36*LISTS!$C$20 -> 270000 | D37: Sq ft | E37: Conversion factors in LISTS
B38: Land area | C38: =$C$36*LISTS!$C$21 -> 25083.821 | D38: Sq m
B39: Land area | C39: =$C$36*LISTS!$C$22 -> 6.1983471 | D39: Acres
B40: Land area | C40: =$C$36*LISTS!$C$23 -> 9.9173554 | D40: Bigha
B41: Current market rate | C41: 60000 | D41: ₹/sq yd | E41: Put sq yd rate only
B42: DLC rate | C42: 13000 | D42: ₹/sq m | E42: Government guideline value (usually notified per sq m)
B43: DLC rate | C43: =$C$42*LISTS!$C$21 -> 10869.656 | D43: ₹/sq yd | E43: Converted from ₹/sq m
B44: If JV
B45: JV ratio – Landowner (revenue share) | C45: 0.32 | D45: % | E45: As per JV / JDA revenue share
B46: JV ratio – Developer | C46: =IF($C$21="JV",1-$C$45,1) -> 0.68 | D46: % | E46: 100% for Outright
B47: Stamp duty + registration – JV (% of DLC value) | C47: 0.0275 | D47: % | E47: Verify current state rate
B48: If Outright
B49: Land rate for purchase | C49: 60000 | D49: ₹/sq yd | E49: Negotiated price (often = market rate)
B50: Stamp duty + registration – Outright | C50: 0.088 | D50: % | E50: On higher of DLC value and purchase price. Verify rate
B51: Land payment curve | C51: Upfront | D51: List
B52: Land payment start quarter | C52: 1 | D52: Quarter
B53: Land payment end quarter | C53: 1 | D53: Quarter | E53: Ignored when Upfront
B54: Derived
B55: Land value at market rate | C55: =$C$36*$C$41/$C$25 -> 180 | D55: ₹ Cr
B56: Land value at purchase rate | C56: =$C$36*$C$49/$C$25 -> 180 | D56: ₹ Cr
B57: Land cost (Outright) / LO revenue share (JV) | C57: =IF($C$21="JV",$C$45*$T$98,$C$56) -> 256.96 | D57: ₹ Cr | E57: JV: LO % × total revenue | Outright: purchase rate × area
B58: Stamp duty + registration | C58: =IF($C$21="JV",$C$36*$C$43*$C$47,$C$36*MAX($C$43,$C$49)*$C$50)/$C$25 -> 0.89674659 | D58: ₹ Cr | E58: JV: on DLC value | Outright: on higher of DLC & price
B59: Brokerage base (land value) | C59: =IF($C$21="JV",$C$55,$C$56) -> 180 | D59: ₹ Cr | E59: Brokerage % is entered in the cost table
B60: Total land cost + stamp duty + brokerage | C60: =$G$128+$G$129+$G$130 -> 259.98075 | D60: ₹ Cr | E60: From cost heads 1–3
B62: Land price check
C63: ₹ Cr per bigha | D63: ₹ per sq yd | E63: Total for land (₹ Cr)
B64: Current market price | C64: =$C$41/LISTS!$C$23/$C$25 -> 18.15 | D64: =$C$41 -> 60000 | E64: =$C$55 -> 180
B65: Land price being offered to LO | C65: =D65/LISTS!$C$23/$C$25 -> 25.910133 | D65: =IF($C$36>0,$C$57*$C$25/$C$36,0) -> 85653.333 | E65: =$C$57 -> 256.96
B66: Difference / return to the LO | C66: =IF(C64>0,C65/C64-1,0) -> 0.42755556 | D66: =IF(D64>0,D65/D64-1,0) -> 0.42755556 | E66: =E65-E64 -> 76.96
B67: JV: what the landowner's revenue share is worth per sq yd vs selling at today's market price.
B69: 3. SCENARIOS
B70: Scenario name | C70: Sales period multiplier | D70: Sales price change % | E70: Construction cost change % | F70: Launch & construction delay (quarters) | G70: Row check
B71: Best Case | C71: 0.75 | D71: 0.05 | E71: 0 | F71: 0 | G71: =IF(AND(LEN(B71)>0,ISNUMBER(C71),C71>0,ISNUMBER(D71),D71>-1,ISNUMBER(E71),E71>-1,ISNUMBER(F71),F71>=0,INT(F71)=F71),"OK","ERROR") -> OK
B72: Base Case | C72: 1 | D72: 0 | E72: 0 | F72: 0 | G72: =IF(AND(LEN(B72)>0,ISNUMBER(C72),C72>0,ISNUMBER(D72),D72>-1,ISNUMBER(E72),E72>-1,ISNUMBER(F72),F72>=0,INT(F72)=F72),"OK","ERROR") -> OK
B73: Worst Case | C73: 1.5 | D73: -0.075 | E73: 0.075 | F73: 2 | G73: =IF(AND(LEN(B73)>0,ISNUMBER(C73),C73>0,ISNUMBER(D73),D73>-1,ISNUMBER(E73),E73>-1,ISNUMBER(F73),F73>=0,INT(F73)=F73),"OK","ERROR") -> OK
B74: Active scenario values (incl. STRESS levers) → | C74: =IFERROR(INDEX($C$71:$C$73,MATCH(IF(STRESS!$C$12>=1,INDEX($B$71:$B$73,STRESS!$C$12),$C$23),$B$71:$B$73,0)),1)*STRESS!$C$10 -> 1 | D74: =(1+IFERROR(INDEX($D$71:$D$73,MATCH(IF(STRESS!$C$12>=1,INDEX($B$71:$B$73,STRESS!$C$12),$C$23),$B$71:$B$73,0)),0))*(1+STRESS!$C$8)-1 -> 0 | E74: =(1+IFERROR(INDEX($E$71:$E$73,MATCH(IF(STRESS!$C$12>=1,INDEX($B$71:$B$73,STRESS!$C$12),$C$23),$B$71:$B$73,0)),0))*(1+STRESS!$C$9)-1 -> 0 | F74: =IFERROR(INDEX($F$71:$F$73,MATCH(IF(STRESS!$C$12>=1,INDEX($B$71:$B$73,STRESS!$C$12),$C$23),$B$71:$B$73,0)),0)+STRESS!$C$11 -> 0
B76: 4. DEVELOPMENT ZONES (share of land)
B77: Development zone | C77: Area share % of land | D77: Land area (sq ft) | E77: Saleable area (sq ft) | F77: Revenue (₹ Cr) | G77: In this project type?
B78: Villa Development | C78: 0.35 | D78: =C78*$C$37 -> 94500 | E78: =SUMIFS($F$88:$F$97,$C$88:$C$97,B78,$E$88:$E$97,"Yes") -> 250000 | F78: =SUMIF($C$88:$C$97,B78,$T$88:$T$97) -> 275 | G78: =IF(OR($C$19="Mixed Development",B78="Other / Clubhouse",AND($C$19="Villa",B78="Villa Development"),AND($C$19="Apartments",B78="Apartment Development"),AND($C$19="Plotted",B78="Plotted Development")),"Used","Not used") -> Used
B79: Apartment Development | C79: 0.5 | D79: =C79*$C$37 -> 135000 | E79: =SUMIFS($F$88:$F$97,$C$88:$C$97,B79,$E$88:$E$97,"Yes") -> 670000 | F79: =SUMIF($C$88:$C$97,B79,$T$88:$T$97) -> 528 | G79: =IF(OR($C$19="Mixed Development",B79="Other / Clubhouse",AND($C$19="Villa",B79="Villa Development"),AND($C$19="Apartments",B79="Apartment Development"),AND($C$19="Plotted",B79="Plotted Development")),"Used","Not used") -> Used
B80: Plotted Development | C80: 0.15 | D80: =C80*$C$37 -> 40500 | E80: =SUMIFS($F$88:$F$97,$C$88:$C$97,B80,$E$88:$E$97,"Yes") -> 0 | F80: =SUMIF($C$88:$C$97,B80,$T$88:$T$97) -> 0 | G80: =IF(OR($C$19="Mixed Development",B80="Other / Clubhouse",AND($C$19="Villa",B80="Villa Development"),AND($C$19="Apartments",B80="Apartment Development"),AND($C$19="Plotted",B80="Plotted Development")),"Used","Not used") -> Used
B81: Other / Clubhouse | C81: 0 | D81: =C81*$C$37 -> 0 | E81: =SUMIFS($F$88:$F$97,$C$88:$C$97,B81,$E$88:$E$97,"Yes") -> 0 | F81: =SUMIF($C$88:$C$97,B81,$T$88:$T$97) -> 0 | G81: =IF(OR($C$19="Mixed Development",B81="Other / Clubhouse",AND($C$19="Villa",B81="Villa Development"),AND($C$19="Apartments",B81="Apartment Development"),AND($C$19="Plotted",B81="Plotted Development")),"Used","Not used") -> Used
B82: TOTAL | C82: =SUM(C78:C81) -> 1 | D82: =SUM(D78:D81) -> 270000 | E82: =SUM(E78:E81) -> 920000 | F82: =SUM(F78:F81) -> 803
B83: Total share must not exceed 100%. Saleable area and revenue come from the product mix below.
B85: 5. PRODUCT MIX (one row per product – fill a spare row and set 'Include? (your choice)' = Yes in column X)
B86: Column E is automatic: a product is active only if you include it (column X) AND its development zone belongs to the selected Project type (Mixed Development = all zones). Inactive products disappear from every calculation.
B87: Product name | C87: Development zone | D87: Category | E87: Active? (auto: your choice × project type) | F87: Saleable area (sq ft) | G87: Base sales rate (₹/sq ft) | H87: Construction cost (₹/sq ft) | I87: Launch quarter (used if 'Fixed') | J87: Sales period (quarters) | K87: Sales curve | L87: CLP / payment plan | M87: Construction start quarter (used if 'Fixed') | N87: Construction duration (quarters) | O87: Construction curve | P87: Launch Q (after scenario) | Q87: Sales end Q | R87: Constr. start Q | S87: Constr. end Q | T87: Revenue (₹ Cr) | U87: Construction cost (₹ Cr) | V87: Launch date | W87: Row check | X87: Include? (your choice)
B88: Villas | C88: Villa Development | D88: Villa | E88: =IF(AND(X88="Yes",OR($C$19="Mixed Development",C88="Other / Clubhouse",AND($C$19="Villa",C88="Villa Development"),AND($C$19="Apartments",C88="Apartment Development"),AND($C$19="Plotted",C88="Plotted Development"))),"Yes","No") -> Yes | F88: 250000 | G88: 11000 | H88: 2900 | I88: 3 | J88: 8 | K88: Front-loaded | L88: CLP – Villa | M88: 4 | N88: 12 | O88: S-curve | P88: =IF($E88="Yes",L105,"") -> 3 | Q88: =IF(AND($E88="Yes",ISNUMBER(P88),ISNUMBER(J88)),P88+MAX(1,ROUNDUP(J88*$C$74,0))-1,"") -> 10 | R88: =IF($E88="Yes",M105,"") -> 4 | S88: =IF(AND($E88="Yes",ISNUMBER(R88),ISNUMBER(N88)),R88+N88-1,"") -> 15 | T88: =IF($E88="Yes",F88*G88*(1+$D$74)/$C$25,0) -> 275 | U88: =IF($E88="Yes",F88*H88*(1+$E$74)/$C$25,0) -> 72.5 | V88: =IF(AND($E88="Yes",ISNUMBER(P88)),EOMONTH($C$20,3*(P88-1)),"") -> 46752 | W88: =IF(X88="No","Off",IF(X88<>"Yes","ERROR",IF(E88<>"Yes","Excluded",IF(AND(LEN(B88)>0,COUNTIF(LISTS!$F$5:$F$8,C88)=1,COUNTIF(LISTS!$G$5:$G$11,D88)=1,ISNUMBER(F88),F88>0,ISNUMBER(G88),G88>=0,ISNUMBER(H88),H88>=0,ISNUMBER(J88),J88>=1,INT(J88)=J88,COUNTIF(LISTS!$H$5:$H$8,K88)=1,IFERROR(INDEX(LISTS!$S$5:$S$10,MATCH(L88,LISTS!$R$5:$R$10,0))="OK",FALSE()),ISNUMBER(N88),N88>=1,INT(N88)=N88,COUNTIF(LISTS!$H$5:$H$8,O88)=1,N105="OK",ISNUMBER(P88),ISNUMBER(R88),Q88<=$C$24,S88<=$C$24),"OK","ERROR")))) -> OK | X88: Yes
B89: Apartments – Towers A & B | C89: Apartment Development | D89: Apartment | E89: =IF(AND(X89="Yes",OR($C$19="Mixed Development",C89="Other / Clubhouse",AND($C$19="Villa",C89="Villa Development"),AND($C$19="Apartments",C89="Apartment Development"),AND($C$19="Plotted",C89="Plotted Development"))),"Yes","No") -> Yes | F89: 600000 | G89: 7500 | H89: 2900 | I89: 4 | J89: 12 | K89: Even | L89: CLP – Apartment | M89: 5 | N89: 16 | O89: S-curve | P89: =IF($E89="Yes",L106,"") -> 4 | Q89: =IF(AND($E89="Yes",ISNUMBER(P89),ISNUMBER(J89)),P89+MAX(1,ROUNDUP(J89*$C$74,0))-1,"") -> 15 | R89: =IF($E89="Yes",M106,"") -> 5 | S89: =IF(AND($E89="Yes",ISNUMBER(R89),ISNUMBER(N89)),R89+N89-1,"") -> 20 | T89: =IF($E89="Yes",F89*G89*(1+$D$74)/$C$25,0) -> 450 | U89: =IF($E89="Yes",F89*H89*(1+$E$74)/$C$25,0) -> 174 | V89: =IF(AND($E89="Yes",ISNUMBER(P89)),EOMONTH($C$20,3*(P89-1)),"") -> 46843 | W89: =IF(X89="No","Off",IF(X89<>"Yes","ERROR",IF(E89<>"Yes","Excluded",IF(AND(LEN(B89)>0,COUNTIF(LISTS!$F$5:$F$8,C89)=1,COUNTIF(LISTS!$G$5:$G$11,D89)=1,ISNUMBER(F89),F89>0,ISNUMBER(G89),G89>=0,ISNUMBER(H89),H89>=0,ISNUMBER(J89),J89>=1,INT(J89)=J89,COUNTIF(LISTS!$H$5:$H$8,K89)=1,IFERROR(INDEX(LISTS!$S$5:$S$10,MATCH(L89,LISTS!$R$5:$R$10,0))="OK",FALSE()),ISNUMBER(N89),N89>=1,INT(N89)=N89,COUNTIF(LISTS!$H$5:$H$8,O89)=1,N106="OK",ISNUMBER(P89),ISNUMBER(R89),Q89<=$C$24,S89<=$C$24),"OK","ERROR")))) -> OK | X89: Yes
B90: Studios | C90: Apartment Development | D90: Studio | E90: =IF(AND(X90="Yes",OR($C$19="Mixed Development",C90="Other / Clubhouse",AND($C$19="Villa",C90="Villa Development"),AND($C$19="Apartments",C90="Apartment Development"),AND($C$19="Plotted",C90="Plotted Development"))),"Yes","No") -> Yes | F90: 40000 | G90: 9000 | H90: 3800 | I90: 6 | J90: 8 | K90: Even | L90: CLP – Apartment | M90: 6 | N90: 12 | O90: S-curve | P90: =IF($E90="Yes",L107,"") -> 6 | Q90: =IF(AND($E90="Yes",ISNUMBER(P90),ISNUMBER(J90)),P90+MAX(1,ROUNDUP(J90*$C$74,0))-1,"") -> 13 | R90: =IF($E90="Yes",M107,"") -> 6 | S90: =IF(AND($E90="Yes",ISNUMBER(R90),ISNUMBER(N90)),R90+N90-1,"") -> 17 | T90: =IF($E90="Yes",F90*G90*(1+$D$74)/$C$25,0) -> 36 | U90: =IF($E90="Yes",F90*H90*(1+$E$74)/$C$25,0) -> 15.2 | V90: =IF(AND($E90="Yes",ISNUMBER(P90)),EOMONTH($C$20,3*(P90-1)),"") -> 47026 | W90: =IF(X90="No","Off",IF(X90<>"Yes","ERROR",IF(E90<>"Yes","Excluded",IF(AND(LEN(B90)>0,COUNTIF(LISTS!$F$5:$F$8,C90)=1,COUNTIF(LISTS!$G$5:$G$11,D90)=1,ISNUMBER(F90),F90>0,ISNUMBER(G90),G90>=0,ISNUMBER(H90),H90>=0,ISNUMBER(J90),J90>=1,INT(J90)=J90,COUNTIF(LISTS!$H$5:$H$8,K90)=1,IFERROR(INDEX(LISTS!$S$5:$S$10,MATCH(L90,LISTS!$R$5:$R$10,0))="OK",FALSE()),ISNUMBER(N90),N90>=1,INT(N90)=N90,COUNTIF(LISTS!$H$5:$H$8,O90)=1,N107="OK",ISNUMBER(P90),ISNUMBER(R90),Q90<=$C$24,S90<=$C$24),"OK","ERROR")))) -> OK | X90: Yes
B91: High-street retail | C91: Apartment Development | D91: Commercial | E91: =IF(AND(X91="Yes",OR($C$19="Mixed Development",C91="Other / Clubhouse",AND($C$19="Villa",C91="Villa Development"),AND($C$19="Apartments",C91="Apartment Development"),AND($C$19="Plotted",C91="Plotted Development"))),"Yes","No") -> Yes | F91: 30000 | G91: 14000 | H91: 2900 | I91: 8 | J91: 8 | K91: Back-loaded | L91: Down Payment Plan | M91: 6 | N91: 12 | O91: S-curve | P91: =IF($E91="Yes",L108,"") -> 8 | Q91: =IF(AND($E91="Yes",ISNUMBER(P91),ISNUMBER(J91)),P91+MAX(1,ROUNDUP(J91*$C$74,0))-1,"") -> 15 | R91: =IF($E91="Yes",M108,"") -> 6 | S91: =IF(AND($E91="Yes",ISNUMBER(R91),ISNUMBER(N91)),R91+N91-1,"") -> 17 | T91: =IF($E91="Yes",F91*G91*(1+$D$74)/$C$25,0) -> 42 | U91: =IF($E91="Yes",F91*H91*(1+$E$74)/$C$25,0) -> 8.7 | V91: =IF(AND($E91="Yes",ISNUMBER(P91)),EOMONTH($C$20,3*(P91-1)),"") -> 47208 | W91: =IF(X91="No","Off",IF(X91<>"Yes","ERROR",IF(E91<>"Yes","Excluded",IF(AND(LEN(B91)>0,COUNTIF(LISTS!$F$5:$F$8,C91)=1,COUNTIF(LISTS!$G$5:$G$11,D91)=1,ISNUMBER(F91),F91>0,ISNUMBER(G91),G91>=0,ISNUMBER(H91),H91>=0,ISNUMBER(J91),J91>=1,INT(J91)=J91,COUNTIF(LISTS!$H$5:$H$8,K91)=1,IFERROR(INDEX(LISTS!$S$5:$S$10,MATCH(L91,LISTS!$R$5:$R$10,0))="OK",FALSE()),ISNUMBER(N91),N91>=1,INT(N91)=N91,COUNTIF(LISTS!$H$5:$H$8,O91)=1,N108="OK",ISNUMBER(P91),ISNUMBER(R91),Q91<=$C$24,S91<=$C$24),"OK","ERROR")))) -> OK | X91: Yes
B92: Residential plots | C92: Plotted Development | D92: Plot | E92: =IF(AND(X92="Yes",OR($C$19="Mixed Development",C92="Other / Clubhouse",AND($C$19="Villa",C92="Villa Development"),AND($C$19="Apartments",C92="Apartment Development"),AND($C$19="Plotted",C92="Plotted Development"))),"Yes","No") -> No | F92: 150000 | G92: 4500 | H92: 450 | I92: 10 | J92: 8 | K92: Even | L92: Plot – Development Linked | M92: 9 | N92: 8 | O92: Even | P92: =IF($E92="Yes",L109,"") | Q92: =IF(AND($E92="Yes",ISNUMBER(P92),ISNUMBER(J92)),P92+MAX(1,ROUNDUP(J92*$C$74,0))-1,"") | R92: =IF($E92="Yes",M109,"") | S92: =IF(AND($E92="Yes",ISNUMBER(R92),ISNUMBER(N92)),R92+N92-1,"") | T92: =IF($E92="Yes",F92*G92*(1+$D$74)/$C$25,0) -> 0 | U92: =IF($E92="Yes",F92*H92*(1+$E$74)/$C$25,0) -> 0 | V92: =IF(AND($E92="Yes",ISNUMBER(P92)),EOMONTH($C$20,3*(P92-1)),"") | W92: =IF(X92="No","Off",IF(X92<>"Yes","ERROR",IF(E92<>"Yes","Excluded",IF(AND(LEN(B92)>0,COUNTIF(LISTS!$F$5:$F$8,C92)=1,COUNTIF(LISTS!$G$5:$G$11,D92)=1,ISNUMBER(F92),F92>0,ISNUMBER(G92),G92>=0,ISNUMBER(H92),H92>=0,ISNUMBER(J92),J92>=1,INT(J92)=J92,COUNTIF(LISTS!$H$5:$H$8,K92)=1,IFERROR(INDEX(LISTS!$S$5:$S$10,MATCH(L92,LISTS!$R$5:$R$10,0))="OK",FALSE()),ISNUMBER(N92),N92>=1,INT(N92)=N92,COUNTIF(LISTS!$H$5:$H$8,O92)=1,N109="OK",ISNUMBER(P92),ISNUMBER(R92),Q92<=$C$24,S92<=$C$24),"OK","ERROR")))) -> Off | X92: No
B93: Institutional plots | C93: Plotted Development | D93: Institutional | E93: =IF(AND(X93="Yes",OR($C$19="Mixed Development",C93="Other / Clubhouse",AND($C$19="Villa",C93="Villa Development"),AND($C$19="Apartments",C93="Apartment Development"),AND($C$19="Plotted",C93="Plotted Development"))),"Yes","No") -> No | F93: 30000 | G93: 4000 | H93: 400 | I93: 12 | J93: 8 | K93: Even | L93: Plot – Development Linked | M93: 9 | N93: 8 | O93: Even | P93: =IF($E93="Yes",L110,"") | Q93: =IF(AND($E93="Yes",ISNUMBER(P93),ISNUMBER(J93)),P93+MAX(1,ROUNDUP(J93*$C$74,0))-1,"") | R93: =IF($E93="Yes",M110,"") | S93: =IF(AND($E93="Yes",ISNUMBER(R93),ISNUMBER(N93)),R93+N93-1,"") | T93: =IF($E93="Yes",F93*G93*(1+$D$74)/$C$25,0) -> 0 | U93: =IF($E93="Yes",F93*H93*(1+$E$74)/$C$25,0) -> 0 | V93: =IF(AND($E93="Yes",ISNUMBER(P93)),EOMONTH($C$20,3*(P93-1)),"") | W93: =IF(X93="No","Off",IF(X93<>"Yes","ERROR",IF(E93<>"Yes","Excluded",IF(AND(LEN(B93)>0,COUNTIF(LISTS!$F$5:$F$8,C93)=1,COUNTIF(LISTS!$G$5:$G$11,D93)=1,ISNUMBER(F93),F93>0,ISNUMBER(G93),G93>=0,ISNUMBER(H93),H93>=0,ISNUMBER(J93),J93>=1,INT(J93)=J93,COUNTIF(LISTS!$H$5:$H$8,K93)=1,IFERROR(INDEX(LISTS!$S$5:$S$10,MATCH(L93,LISTS!$R$5:$R$10,0))="OK",FALSE()),ISNUMBER(N93),N93>=1,INT(N93)=N93,COUNTIF(LISTS!$H$5:$H$8,O93)=1,N110="OK",ISNUMBER(P93),ISNUMBER(R93),Q93<=$C$24,S93<=$C$24),"OK","ERROR")))) -> Off | X93: No
B94: EWS / LIG plots | C94: Plotted Development | D94: EWS/LIG | E94: =IF(AND(X94="Yes",OR($C$19="Mixed Development",C94="Other / Clubhouse",AND($C$19="Villa",C94="Villa Development"),AND($C$19="Apartments",C94="Apartment Development"),AND($C$19="Plotted",C94="Plotted Development"))),"Yes","No") -> No | F94: 20000 | G94: 1500 | H94: 400 | I94: 10 | J94: 8 | K94: Even | L94: Plot – Development Linked | M94: 9 | N94: 8 | O94: Even | P94: =IF($E94="Yes",L111,"") | Q94: =IF(AND($E94="Yes",ISNUMBER(P94),ISNUMBER(J94)),P94+MAX(1,ROUNDUP(J94*$C$74,0))-1,"") | R94: =IF($E94="Yes",M111,"") | S94: =IF(AND($E94="Yes",ISNUMBER(R94),ISNUMBER(N94)),R94+N94-1,"") | T94: =IF($E94="Yes",F94*G94*(1+$D$74)/$C$25,0) -> 0 | U94: =IF($E94="Yes",F94*H94*(1+$E$74)/$C$25,0) -> 0 | V94: =IF(AND($E94="Yes",ISNUMBER(P94)),EOMONTH($C$20,3*(P94-1)),"") | W94: =IF(X94="No","Off",IF(X94<>"Yes","ERROR",IF(E94<>"Yes","Excluded",IF(AND(LEN(B94)>0,COUNTIF(LISTS!$F$5:$F$8,C94)=1,COUNTIF(LISTS!$G$5:$G$11,D94)=1,ISNUMBER(F94),F94>0,ISNUMBER(G94),G94>=0,ISNUMBER(H94),H94>=0,ISNUMBER(J94),J94>=1,INT(J94)=J94,COUNTIF(LISTS!$H$5:$H$8,K94)=1,IFERROR(INDEX(LISTS!$S$5:$S$10,MATCH(L94,LISTS!$R$5:$R$10,0))="OK",FALSE()),ISNUMBER(N94),N94>=1,INT(N94)=N94,COUNTIF(LISTS!$H$5:$H$8,O94)=1,N111="OK",ISNUMBER(P94),ISNUMBER(R94),Q94<=$C$24,S94<=$C$24),"OK","ERROR")))) -> Off | X94: No
E95: =IF(AND(X95="Yes",OR($C$19="Mixed Development",C95="Other / Clubhouse",AND($C$19="Villa",C95="Villa Development"),AND($C$19="Apartments",C95="Apartment Development"),AND($C$19="Plotted",C95="Plotted Development"))),"Yes","No") -> No | P95: =IF($E95="Yes",L112,"") | Q95: =IF(AND($E95="Yes",ISNUMBER(P95),ISNUMBER(J95)),P95+MAX(1,ROUNDUP(J95*$C$74,0))-1,"") | R95: =IF($E95="Yes",M112,"") | S95: =IF(AND($E95="Yes",ISNUMBER(R95),ISNUMBER(N95)),R95+N95-1,"") | T95: =IF($E95="Yes",F95*G95*(1+$D$74)/$C$25,0) -> 0 | U95: =IF($E95="Yes",F95*H95*(1+$E$74)/$C$25,0) -> 0 | V95: =IF(AND($E95="Yes",ISNUMBER(P95)),EOMONTH($C$20,3*(P95-1)),"") | W95: =IF(X95="No","Off",IF(X95<>"Yes","ERROR",IF(E95<>"Yes","Excluded",IF(AND(LEN(B95)>0,COUNTIF(LISTS!$F$5:$F$8,C95)=1,COUNTIF(LISTS!$G$5:$G$11,D95)=1,ISNUMBER(F95),F95>0,ISNUMBER(G95),G95>=0,ISNUMBER(H95),H95>=0,ISNUMBER(J95),J95>=1,INT(J95)=J95,COUNTIF(LISTS!$H$5:$H$8,K95)=1,IFERROR(INDEX(LISTS!$S$5:$S$10,MATCH(L95,LISTS!$R$5:$R$10,0))="OK",FALSE()),ISNUMBER(N95),N95>=1,INT(N95)=N95,COUNTIF(LISTS!$H$5:$H$8,O95)=1,N112="OK",ISNUMBER(P95),ISNUMBER(R95),Q95<=$C$24,S95<=$C$24),"OK","ERROR")))) -> Off | X95: No
E96: =IF(AND(X96="Yes",OR($C$19="Mixed Development",C96="Other / Clubhouse",AND($C$19="Villa",C96="Villa Development"),AND($C$19="Apartments",C96="Apartment Development"),AND($C$19="Plotted",C96="Plotted Development"))),"Yes","No") -> No | P96: =IF($E96="Yes",L113,"") | Q96: =IF(AND($E96="Yes",ISNUMBER(P96),ISNUMBER(J96)),P96+MAX(1,ROUNDUP(J96*$C$74,0))-1,"") | R96: =IF($E96="Yes",M113,"") | S96: =IF(AND($E96="Yes",ISNUMBER(R96),ISNUMBER(N96)),R96+N96-1,"") | T96: =IF($E96="Yes",F96*G96*(1+$D$74)/$C$25,0) -> 0 | U96: =IF($E96="Yes",F96*H96*(1+$E$74)/$C$25,0) -> 0 | V96: =IF(AND($E96="Yes",ISNUMBER(P96)),EOMONTH($C$20,3*(P96-1)),"") | W96: =IF(X96="No","Off",IF(X96<>"Yes","ERROR",IF(E96<>"Yes","Excluded",IF(AND(LEN(B96)>0,COUNTIF(LISTS!$F$5:$F$8,C96)=1,COUNTIF(LISTS!$G$5:$G$11,D96)=1,ISNUMBER(F96),F96>0,ISNUMBER(G96),G96>=0,ISNUMBER(H96),H96>=0,ISNUMBER(J96),J96>=1,INT(J96)=J96,COUNTIF(LISTS!$H$5:$H$8,K96)=1,IFERROR(INDEX(LISTS!$S$5:$S$10,MATCH(L96,LISTS!$R$5:$R$10,0))="OK",FALSE()),ISNUMBER(N96),N96>=1,INT(N96)=N96,COUNTIF(LISTS!$H$5:$H$8,O96)=1,N113="OK",ISNUMBER(P96),ISNUMBER(R96),Q96<=$C$24,S96<=$C$24),"OK","ERROR")))) -> Off | X96: No
E97: =IF(AND(X97="Yes",OR($C$19="Mixed Development",C97="Other / Clubhouse",AND($C$19="Villa",C97="Villa Development"),AND($C$19="Apartments",C97="Apartment Development"),AND($C$19="Plotted",C97="Plotted Development"))),"Yes","No") -> No | P97: =IF($E97="Yes",L114,"") | Q97: =IF(AND($E97="Yes",ISNUMBER(P97),ISNUMBER(J97)),P97+MAX(1,ROUNDUP(J97*$C$74,0))-1,"") | R97: =IF($E97="Yes",M114,"") | S97: =IF(AND($E97="Yes",ISNUMBER(R97),ISNUMBER(N97)),R97+N97-1,"") | T97: =IF($E97="Yes",F97*G97*(1+$D$74)/$C$25,0) -> 0 | U97: =IF($E97="Yes",F97*H97*(1+$E$74)/$C$25,0) -> 0 | V97: =IF(AND($E97="Yes",ISNUMBER(P97)),EOMONTH($C$20,3*(P97-1)),"") | W97: =IF(X97="No","Off",IF(X97<>"Yes","ERROR",IF(E97<>"Yes","Excluded",IF(AND(LEN(B97)>0,COUNTIF(LISTS!$F$5:$F$8,C97)=1,COUNTIF(LISTS!$G$5:$G$11,D97)=1,ISNUMBER(F97),F97>0,ISNUMBER(G97),G97>=0,ISNUMBER(H97),H97>=0,ISNUMBER(J97),J97>=1,INT(J97)=J97,COUNTIF(LISTS!$H$5:$H$8,K97)=1,IFERROR(INDEX(LISTS!$S$5:$S$10,MATCH(L97,LISTS!$R$5:$R$10,0))="OK",FALSE()),ISNUMBER(N97),N97>=1,INT(N97)=N97,COUNTIF(LISTS!$H$5:$H$8,O97)=1,N114="OK",ISNUMBER(P97),ISNUMBER(R97),Q97<=$C$24,S97<=$C$24),"OK","ERROR")))) -> Off | X97: No
B98: TOTAL (included products) | F98: =SUMIF($E$88:$E$97,"Yes",$F$88:$F$97) -> 920000 | G98: =IF(F98>0,T98*$C$25/F98,0) -> 8728.2609 | H98: =IF(F98>0,U98*$C$25/F98,0) -> 2939.1304 | T98: =SUM(T88:T97) -> 803 | U98: =SUM(U88:U97) -> 270.4
B99: Totals row shows weighted-average rates. Revenue is before price escalation. Zone 'Plotted Development' revenue attracts the plotted marketing rate.
B101: 5B. PRODUCT TIMING – how each product's launch and construction start are decided
B102: Fixed quarter = uses the quarter typed in Section 5. Linked = X quarters after an event of another product listed ABOVE it (put your lead product first).
B103: Offset 0 = same quarter as the event; 1 = next quarter; −1 = one quarter before. Scenario delay is applied once, to fixed quarters only – linked products inherit it.
B104: Product | C104: Launch timing | D104: Launch – linked product | E104: Launch – linked event | F104: Launch offset (quarters) | G104: Construction timing | H104: Construction – linked product | I104: Construction – linked event | J104: Construction offset (quarters) | K104: Constr. start (pre-calc) | L104: Launch Q (final) | M104: Constr. start Q (final) | N104: Row check | O104: Plain-English result
B105: =IF(B88="","(row 1)",B88) -> Villas | C105: Fixed quarter | G105: After own launch | J105: 1 | K105: =IF(G105="Fixed quarter",IF(ISNUMBER(M88),M88+$F$74,""),IF(G105="Linked to another product",IF(ISNUMBER(""),"",IF(ISNUMBER(M88),M88+$F$74,"")),"")) | L105: =IF(C105="Fixed quarter",IF(ISNUMBER(I88),I88+$F$74,""),IF(C105="Linked to another product",IF(ISNUMBER(""),"",IF(ISNUMBER(I88),I88+$F$74,"")),IF(C105="After own construction start",IFERROR(K105+F105,""),""))) -> 3 | M105: =IF(G105="After own launch",IFERROR(L105+J105,""),K105) -> 4 | N105: =IF(E88<>"Yes","Off",IF(AND(IF(C105="Fixed quarter",AND(AND(ISNUMBER(I88),INT(I88)=I88),I88>=1),IF(C105="Linked to another product",AND(FALSE(),COUNTIF(LISTS!$V$5:$V$9,E105)=1,AND(ISNUMBER(F105),INT(F105)=F105)),IF(C105="After own construction start",AND(AND(ISNUMBER(F105),INT(F105)=F105),G105<>"After own launch"),FALSE()))),IF(G105="Fixed quarter",AND(AND(ISNUMBER(M88),INT(M88)=M88),M88>=1),IF(G105="After own launch",AND(AND(ISNUMBER(J105),INT(J105)=J105),C105<>"After own construction start"),IF(G105="Linked to another product",AND(FALSE(),COUNTIF(LISTS!$V$5:$V$9,I105)=1,AND(ISNUMBER(J105),INT(J105)=J105)),FALSE()))),ISNUMBER(L105),L105>=1,ISNUMBER(M105),M105>=1),"OK","ERROR")) -> OK | O105: =IF(OR(N105="Off",E88<>"Yes"),"—",IF(N105<>"OK","Fix this row","Launch "&"Q"&L105&" ("&IF(C105="Fixed quarter","fixed",IF(C105="Linked to another product",IF(IFERROR(INDEX($E$88:$E$97,MATCH(D105,$B$88:$B$97,0))="Yes",FALSE()),IF(F105<0,ABS(F105)&" qtr(s) before ",F105&" qtr(s) after ")&D105&" – "&LOWER(E105),"fixed fallback – "&D105&" not active"),IF(F105<0,ABS(F105)&" qtr(s) before ",F105&" qtr(s) after ")&"own construction start"))&") | Construction "&"Q"&M105&" ("&IF(G105="Fixed quarter","fixed",IF(G105="After own launch",IF(J105<0,ABS(J105)&" qtr(s) before ",J105&" qtr(s) after ")&"own launch",IF(IFERROR(INDEX($E$88:$E$97,MATCH(H105,$B$88:$B$97,0))="Yes",FALSE()),IF(J105<0,ABS(J105)&" qtr(s) before ",J105&" qtr(s) after ")&H105&" – "&LOWER(I105),"fixed fallback – "&H105&" not active")))&")")) -> Launch Q3 (fixed) | Construction Q4 (1 qtr(s) after own launch)
B106: =IF(B89="","(row 2)",B89) -> Apartments – Towers A & B | C106: Linked to another product | D106: Villas | E106: Launch | F106: 1 | G106: After own launch | J106: 1 | K106: =IF(G106="Fixed quarter",IF(ISNUMBER(M89),M89+$F$74,""),IF(G106="Linked to another product",IF(ISNUMBER(IFERROR(CHOOSE(MATCH(I106,LISTS!$V$5:$V$9,0),INDEX($P$88:$P$88,MATCH(H106,$B$88:$B$88,0)),INDEX($Q$88:$Q$88,MATCH(H106,$B$88:$B$88,0)),INDEX($R$88:$R$88,MATCH(H106,$B$88:$B$88,0)),INDEX($R$88:$R$88,MATCH(H106,$B$88:$B$88,0))+ROUNDUP(INDEX($N$88:$N$88,MATCH(H106,$B$88:$B$88,0))/2,0)-1,INDEX($S$88:$S$88,MATCH(H106,$B$88:$B$88,0)))+J106,"")),IFERROR(CHOOSE(MATCH(I106,LISTS!$V$5:$V$9,0),INDEX($P$88:$P$88,MATCH(H106,$B$88:$B$88,0)),INDEX($Q$88:$Q$88,MATCH(H106,$B$88:$B$88,0)),INDEX($R$88:$R$88,MATCH(H106,$B$88:$B$88,0)),INDEX($R$88:$R$88,MATCH(H106,$B$88:$B$88,0))+ROUNDUP(INDEX($N$88:$N$88,MATCH(H106,$B$88:$B$88,0))/2,0)-1,INDEX($S$88:$S$88,MATCH(H106,$B$88:$B$88,0)))+J106,""),IF(ISNUMBER(M89),M89+$F$74,"")),"")) | L106: =IF(C106="Fixed quarter",IF(ISNUMBER(I89),I89+$F$74,""),IF(C106="Linked to another product",IF(ISNUMBER(IFERROR(CHOOSE(MATCH(E106,LISTS!$V$5:$V$9,0),INDEX($P$88:$P$88,MATCH(D106,$B$88:$B$88,0)),INDEX($Q$88:$Q$88,MATCH(D106,$B$88:$B$88,0)),INDEX($R$88:$R$88,MATCH(D106,$B$88:$B$88,0)),INDEX($R$88:$R$88,MATCH(D106,$B$88:$B$88,0))+ROUNDUP(INDEX($N$88:$N$88,MATCH(D106,$B$88:$B$88,0))/2,0)-1,INDEX($S$88:$S$88,MATCH(D106,$B$88:$B$88,0)))+F106,"")),IFERROR(CHOOSE(MATCH(E106,LISTS!$V$5:$V$9,0),INDEX($P$88:$P$88,MATCH(D106,$B$88:$B$88,0)),INDEX($Q$88:$Q$88,MATCH(D106,$B$88:$B$88,0)),INDEX($R$88:$R$88,MATCH(D106,$B$88:$B$88,0)),INDEX($R$88:$R$88,MATCH(D106,$B$88:$B$88,0))+ROUNDUP(INDEX($N$88:$N$88,MATCH(D106,$B$88:$B$88,0))/2,0)-1,INDEX($S$88:$S$88,MATCH(D106,$B$88:$B$88,0)))+F106,""),IF(ISNUMBER(I89),I89+$F$74,"")),IF(C106="After own construction start",IFERROR(K106+F106,""),""))) -> 4 | M106: =IF(G106="After own launch",IFERROR(L106+J106,""),K106) -> 5 | N106: =IF(E89<>"Yes","Off",IF(AND(IF(C106="Fixed quarter",AND(AND(ISNUMBER(I89),INT(I89)=I89),I89>=1),IF(C106="Linked to another product",AND(AND(ISNUMBER(MATCH(D106,$B$88:$B$88,0)),OR(IFERROR(INDEX($E$88:$E$88,MATCH(D106,$B$88:$B$88,0))="Yes",FALSE()),AND(ISNUMBER(I89),I89>=1,INT(I89)=I89))),COUNTIF(LISTS!$V$5:$V$9,E106)=1,AND(ISNUMBER(F106),INT(F106)=F106)),IF(C106="After own construction start",AND(AND(ISNUMBER(F106),INT(F106)=F106),G106<>"After own launch"),FALSE()))),IF(G106="Fixed quarter",AND(AND(ISNUMBER(M89),INT(M89)=M89),M89>=1),IF(G106="After own launch",AND(AND(ISNUMBER(J106),INT(J106)=J106),C106<>"After own construction start"),IF(G106="Linked to another product",AND(AND(ISNUMBER(MATCH(H106,$B$88:$B$88,0)),OR(IFERROR(INDEX($E$88:$E$88,MATCH(H106,$B$88:$B$88,0))="Yes",FALSE()),AND(ISNUMBER(M89),M89>=1,INT(M89)=M89))),COUNTIF(LISTS!$V$5:$V$9,I106)=1,AND(ISNUMBER(J106),INT(J106)=J106)),FALSE()))),ISNUMBER(L106),L106>=1,ISNUMBER(M106),M106>=1),"OK","ERROR")) -> OK | O106: =IF(OR(N106="Off",E89<>"Yes"),"—",IF(N106<>"OK","Fix this row","Launch "&"Q"&L106&" ("&IF(C106="Fixed quarter","fixed",IF(C106="Linked to another product",IF(IFERROR(INDEX($E$88:$E$97,MATCH(D106,$B$88:$B$97,0))="Yes",FALSE()),IF(F106<0,ABS(F106)&" qtr(s) before ",F106&" qtr(s) after ")&D106&" – "&LOWER(E106),"fixed fallback – "&D106&" not active"),IF(F106<0,ABS(F106)&" qtr(s) before ",F106&" qtr(s) after ")&"own construction start"))&") | Construction "&"Q"&M106&" ("&IF(G106="Fixed quarter","fixed",IF(G106="After own launch",IF(J106<0,ABS(J106)&" qtr(s) before ",J106&" qtr(s) after ")&"own launch",IF(IFERROR(INDEX($E$88:$E$97,MATCH(H106,$B$88:$B$97,0))="Yes",FALSE()),IF(J106<0,ABS(J106)&" qtr(s) before ",J106&" qtr(s) after ")&H106&" – "&LOWER(I106),"fixed fallback – "&H106&" not active")))&")")) -> Launch Q4 (1 qtr(s) after Villas – launch) | Construction Q5 (1 qtr(s) after own launch)
B107: =IF(B90="","(row 3)",B90) -> Studios | C107: Linked to another product | D107: Apartments – Towers A & B | E107: Construction start | F107: 1 | G107: After own launch | J107: 0 | K107: =IF(G107="Fixed quarter",IF(ISNUMBER(M90),M90+$F$74,""),IF(G107="Linked to another product",IF(ISNUMBER(IFERROR(CHOOSE(MATCH(I107,LISTS!$V$5:$V$9,0),INDEX($P$88:$P$89,MATCH(H107,$B$88:$B$89,0)),INDEX($Q$88:$Q$89,MATCH(H107,$B$88:$B$89,0)),INDEX($R$88:$R$89,MATCH(H107,$B$88:$B$89,0)),INDEX($R$88:$R$89,MATCH(H107,$B$88:$B$89,0))+ROUNDUP(INDEX($N$88:$N$89,MATCH(H107,$B$88:$B$89,0))/2,0)-1,INDEX($S$88:$S$89,MATCH(H107,$B$88:$B$89,0)))+J107,"")),IFERROR(CHOOSE(MATCH(I107,LISTS!$V$5:$V$9,0),INDEX($P$88:$P$89,MATCH(H107,$B$88:$B$89,0)),INDEX($Q$88:$Q$89,MATCH(H107,$B$88:$B$89,0)),INDEX($R$88:$R$89,MATCH(H107,$B$88:$B$89,0)),INDEX($R$88:$R$89,MATCH(H107,$B$88:$B$89,0))+ROUNDUP(INDEX($N$88:$N$89,MATCH(H107,$B$88:$B$89,0))/2,0)-1,INDEX($S$88:$S$89,MATCH(H107,$B$88:$B$89,0)))+J107,""),IF(ISNUMBER(M90),M90+$F$74,"")),"")) | L107: =IF(C107="Fixed quarter",IF(ISNUMBER(I90),I90+$F$74,""),IF(C107="Linked to another product",IF(ISNUMBER(IFERROR(CHOOSE(MATCH(E107,LISTS!$V$5:$V$9,0),INDEX($P$88:$P$89,MATCH(D107,$B$88:$B$89,0)),INDEX($Q$88:$Q$89,MATCH(D107,$B$88:$B$89,0)),INDEX($R$88:$R$89,MATCH(D107,$B$88:$B$89,0)),INDEX($R$88:$R$89,MATCH(D107,$B$88:$B$89,0))+ROUNDUP(INDEX($N$88:$N$89,MATCH(D107,$B$88:$B$89,0))/2,0)-1,INDEX($S$88:$S$89,MATCH(D107,$B$88:$B$89,0)))+F107,"")),IFERROR(CHOOSE(MATCH(E107,LISTS!$V$5:$V$9,0),INDEX($P$88:$P$89,MATCH(D107,$B$88:$B$89,0)),INDEX($Q$88:$Q$89,MATCH(D107,$B$88:$B$89,0)),INDEX($R$88:$R$89,MATCH(D107,$B$88:$B$89,0)),INDEX($R$88:$R$89,MATCH(D107,$B$88:$B$89,0))+ROUNDUP(INDEX($N$88:$N$89,MATCH(D107,$B$88:$B$89,0))/2,0)-1,INDEX($S$88:$S$89,MATCH(D107,$B$88:$B$89,0)))+F107,""),IF(ISNUMBER(I90),I90+$F$74,"")),IF(C107="After own construction start",IFERROR(K107+F107,""),""))) -> 6 | M107: =IF(G107="After own launch",IFERROR(L107+J107,""),K107) -> 6 | N107: =IF(E90<>"Yes","Off",IF(AND(IF(C107="Fixed quarter",AND(AND(ISNUMBER(I90),INT(I90)=I90),I90>=1),IF(C107="Linked to another product",AND(AND(ISNUMBER(MATCH(D107,$B$88:$B$89,0)),OR(IFERROR(INDEX($E$88:$E$89,MATCH(D107,$B$88:$B$89,0))="Yes",FALSE()),AND(ISNUMBER(I90),I90>=1,INT(I90)=I90))),COUNTIF(LISTS!$V$5:$V$9,E107)=1,AND(ISNUMBER(F107),INT(F107)=F107)),IF(C107="After own construction start",AND(AND(ISNUMBER(F107),INT(F107)=F107),G107<>"After own launch"),FALSE()))),IF(G107="Fixed quarter",AND(AND(ISNUMBER(M90),INT(M90)=M90),M90>=1),IF(G107="After own launch",AND(AND(ISNUMBER(J107),INT(J107)=J107),C107<>"After own construction start"),IF(G107="Linked to another product",AND(AND(ISNUMBER(MATCH(H107,$B$88:$B$89,0)),OR(IFERROR(INDEX($E$88:$E$89,MATCH(H107,$B$88:$B$89,0))="Yes",FALSE()),AND(ISNUMBER(M90),M90>=1,INT(M90)=M90))),COUNTIF(LISTS!$V$5:$V$9,I107)=1,AND(ISNUMBER(J107),INT(J107)=J107)),FALSE()))),ISNUMBER(L107),L107>=1,ISNUMBER(M107),M107>=1),"OK","ERROR")) -> OK | O107: =IF(OR(N107="Off",E90<>"Yes"),"—",IF(N107<>"OK","Fix this row","Launch "&"Q"&L107&" ("&IF(C107="Fixed quarter","fixed",IF(C107="Linked to another product",IF(IFERROR(INDEX($E$88:$E$97,MATCH(D107,$B$88:$B$97,0))="Yes",FALSE()),IF(F107<0,ABS(F107)&" qtr(s) before ",F107&" qtr(s) after ")&D107&" – "&LOWER(E107),"fixed fallback – "&D107&" not active"),IF(F107<0,ABS(F107)&" qtr(s) before ",F107&" qtr(s) after ")&"own construction start"))&") | Construction "&"Q"&M107&" ("&IF(G107="Fixed quarter","fixed",IF(G107="After own launch",IF(J107<0,ABS(J107)&" qtr(s) before ",J107&" qtr(s) after ")&"own launch",IF(IFERROR(INDEX($E$88:$E$97,MATCH(H107,$B$88:$B$97,0))="Yes",FALSE()),IF(J107<0,ABS(J107)&" qtr(s) before ",J107&" qtr(s) after ")&H107&" – "&LOWER(I107),"fixed fallback – "&H107&" not active")))&")")) -> Launch Q6 (1 qtr(s) after Apartments – Towers A & B – construction start) | Construction Q6 (0 qtr(s) after own launch)
B108: =IF(B91="","(row 4)",B91) -> High-street retail | C108: Linked to another product | D108: Apartments – Towers A & B | E108: Launch | F108: 4 | G108: Linked to another product | H108: Apartments – Towers A & B | I108: Construction start | J108: 1 | K108: =IF(G108="Fixed quarter",IF(ISNUMBER(M91),M91+$F$74,""),IF(G108="Linked to another product",IF(ISNUMBER(IFERROR(CHOOSE(MATCH(I108,LISTS!$V$5:$V$9,0),INDEX($P$88:$P$90,MATCH(H108,$B$88:$B$90,0)),INDEX($Q$88:$Q$90,MATCH(H108,$B$88:$B$90,0)),INDEX($R$88:$R$90,MATCH(H108,$B$88:$B$90,0)),INDEX($R$88:$R$90,MATCH(H108,$B$88:$B$90,0))+ROUNDUP(INDEX($N$88:$N$90,MATCH(H108,$B$88:$B$90,0))/2,0)-1,INDEX($S$88:$S$90,MATCH(H108,$B$88:$B$90,0)))+J108,"")),IFERROR(CHOOSE(MATCH(I108,LISTS!$V$5:$V$9,0),INDEX($P$88:$P$90,MATCH(H108,$B$88:$B$90,0)),INDEX($Q$88:$Q$90,MATCH(H108,$B$88:$B$90,0)),INDEX($R$88:$R$90,MATCH(H108,$B$88:$B$90,0)),INDEX($R$88:$R$90,MATCH(H108,$B$88:$B$90,0))+ROUNDUP(INDEX($N$88:$N$90,MATCH(H108,$B$88:$B$90,0))/2,0)-1,INDEX($S$88:$S$90,MATCH(H108,$B$88:$B$90,0)))+J108,""),IF(ISNUMBER(M91),M91+$F$74,"")),"")) -> 6 | L108: =IF(C108="Fixed quarter",IF(ISNUMBER(I91),I91+$F$74,""),IF(C108="Linked to another product",IF(ISNUMBER(IFERROR(CHOOSE(MATCH(E108,LISTS!$V$5:$V$9,0),INDEX($P$88:$P$90,MATCH(D108,$B$88:$B$90,0)),INDEX($Q$88:$Q$90,MATCH(D108,$B$88:$B$90,0)),INDEX($R$88:$R$90,MATCH(D108,$B$88:$B$90,0)),INDEX($R$88:$R$90,MATCH(D108,$B$88:$B$90,0))+ROUNDUP(INDEX($N$88:$N$90,MATCH(D108,$B$88:$B$90,0))/2,0)-1,INDEX($S$88:$S$90,MATCH(D108,$B$88:$B$90,0)))+F108,"")),IFERROR(CHOOSE(MATCH(E108,LISTS!$V$5:$V$9,0),INDEX($P$88:$P$90,MATCH(D108,$B$88:$B$90,0)),INDEX($Q$88:$Q$90,MATCH(D108,$B$88:$B$90,0)),INDEX($R$88:$R$90,MATCH(D108,$B$88:$B$90,0)),INDEX($R$88:$R$90,MATCH(D108,$B$88:$B$90,0))+ROUNDUP(INDEX($N$88:$N$90,MATCH(D108,$B$88:$B$90,0))/2,0)-1,INDEX($S$88:$S$90,MATCH(D108,$B$88:$B$90,0)))+F108,""),IF(ISNUMBER(I91),I91+$F$74,"")),IF(C108="After own construction start",IFERROR(K108+F108,""),""))) -> 8 | M108: =IF(G108="After own launch",IFERROR(L108+J108,""),K108) -> 6 | N108: =IF(E91<>"Yes","Off",IF(AND(IF(C108="Fixed quarter",AND(AND(ISNUMBER(I91),INT(I91)=I91),I91>=1),IF(C108="Linked to another product",AND(AND(ISNUMBER(MATCH(D108,$B$88:$B$90,0)),OR(IFERROR(INDEX($E$88:$E$90,MATCH(D108,$B$88:$B$90,0))="Yes",FALSE()),AND(ISNUMBER(I91),I91>=1,INT(I91)=I91))),COUNTIF(LISTS!$V$5:$V$9,E108)=1,AND(ISNUMBER(F108),INT(F108)=F108)),IF(C108="After own construction start",AND(AND(ISNUMBER(F108),INT(F108)=F108),G108<>"After own launch"),FALSE()))),IF(G108="Fixed quarter",AND(AND(ISNUMBER(M91),INT(M91)=M91),M91>=1),IF(G108="After own launch",AND(AND(ISNUMBER(J108),INT(J108)=J108),C108<>"After own construction start"),IF(G108="Linked to another product",AND(AND(ISNUMBER(MATCH(H108,$B$88:$B$90,0)),OR(IFERROR(INDEX($E$88:$E$90,MATCH(H108,$B$88:$B$90,0))="Yes",FALSE()),AND(ISNUMBER(M91),M91>=1,INT(M91)=M91))),COUNTIF(LISTS!$V$5:$V$9,I108)=1,AND(ISNUMBER(J108),INT(J108)=J108)),FALSE()))),ISNUMBER(L108),L108>=1,ISNUMBER(M108),M108>=1),"OK","ERROR")) -> OK | O108: =IF(OR(N108="Off",E91<>"Yes"),"—",IF(N108<>"OK","Fix this row","Launch "&"Q"&L108&" ("&IF(C108="Fixed quarter","fixed",IF(C108="Linked to another product",IF(IFERROR(INDEX($E$88:$E$97,MATCH(D108,$B$88:$B$97,0))="Yes",FALSE()),IF(F108<0,ABS(F108)&" qtr(s) before ",F108&" qtr(s) after ")&D108&" – "&LOWER(E108),"fixed fallback – "&D108&" not active"),IF(F108<0,ABS(F108)&" qtr(s) before ",F108&" qtr(s) after ")&"own construction start"))&") | Construction "&"Q"&M108&" ("&IF(G108="Fixed quarter","fixed",IF(G108="After own launch",IF(J108<0,ABS(J108)&" qtr(s) before ",J108&" qtr(s) after ")&"own launch",IF(IFERROR(INDEX($E$88:$E$97,MATCH(H108,$B$88:$B$97,0))="Yes",FALSE()),IF(J108<0,ABS(J108)&" qtr(s) before ",J108&" qtr(s) after ")&H108&" – "&LOWER(I108),"fixed fallback – "&H108&" not active")))&")")) -> Launch Q8 (4 qtr(s) after Apartments – Towers A & B – launch) | Construction Q6 (1 qtr(s) after Apartments – Towers A & B – construction start)
B109: =IF(B92="","(row 5)",B92) -> Residential plots | C109: Fixed quarter | G109: Fixed quarter | K109: =IF(G109="Fixed quarter",IF(ISNUMBER(M92),M92+$F$74,""),IF(G109="Linked to another product",IF(ISNUMBER(IFERROR(CHOOSE(MATCH(I109,LISTS!$V$5:$V$9,0),INDEX($P$88:$P$91,MATCH(H109,$B$88:$B$91,0)),INDEX($Q$88:$Q$91,MATCH(H109,$B$88:$B$91,0)),INDEX($R$88:$R$91,MATCH(H109,$B$88:$B$91,0)),INDEX($R$88:$R$91,MATCH(H109,$B$88:$B$91,0))+ROUNDUP(INDEX($N$88:$N$91,MATCH(H109,$B$88:$B$91,0))/2,0)-1,INDEX($S$88:$S$91,MATCH(H109,$B$88:$B$91,0)))+J109,"")),IFERROR(CHOOSE(MATCH(I109,LISTS!$V$5:$V$9,0),INDEX($P$88:$P$91,MATCH(H109,$B$88:$B$91,0)),INDEX($Q$88:$Q$91,MATCH(H109,$B$88:$B$91,0)),INDEX($R$88:$R$91,MATCH(H109,$B$88:$B$91,0)),INDEX($R$88:$R$91,MATCH(H109,$B$88:$B$91,0))+ROUNDUP(INDEX($N$88:$N$91,MATCH(H109,$B$88:$B$91,0))/2,0)-1,INDEX($S$88:$S$91,MATCH(H109,$B$88:$B$91,0)))+J109,""),IF(ISNUMBER(M92),M92+$F$74,"")),"")) -> 9 | L109: =IF(C109="Fixed quarter",IF(ISNUMBER(I92),I92+$F$74,""),IF(C109="Linked to another product",IF(ISNUMBER(IFERROR(CHOOSE(MATCH(E109,LISTS!$V$5:$V$9,0),INDEX($P$88:$P$91,MATCH(D109,$B$88:$B$91,0)),INDEX($Q$88:$Q$91,MATCH(D109,$B$88:$B$91,0)),INDEX($R$88:$R$91,MATCH(D109,$B$88:$B$91,0)),INDEX($R$88:$R$91,MATCH(D109,$B$88:$B$91,0))+ROUNDUP(INDEX($N$88:$N$91,MATCH(D109,$B$88:$B$91,0))/2,0)-1,INDEX($S$88:$S$91,MATCH(D109,$B$88:$B$91,0)))+F109,"")),IFERROR(CHOOSE(MATCH(E109,LISTS!$V$5:$V$9,0),INDEX($P$88:$P$91,MATCH(D109,$B$88:$B$91,0)),INDEX($Q$88:$Q$91,MATCH(D109,$B$88:$B$91,0)),INDEX($R$88:$R$91,MATCH(D109,$B$88:$B$91,0)),INDEX($R$88:$R$91,MATCH(D109,$B$88:$B$91,0))+ROUNDUP(INDEX($N$88:$N$91,MATCH(D109,$B$88:$B$91,0))/2,0)-1,INDEX($S$88:$S$91,MATCH(D109,$B$88:$B$91,0)))+F109,""),IF(ISNUMBER(I92),I92+$F$74,"")),IF(C109="After own construction start",IFERROR(K109+F109,""),""))) -> 10 | M109: =IF(G109="After own launch",IFERROR(L109+J109,""),K109) -> 9 | N109: =IF(E92<>"Yes","Off",IF(AND(IF(C109="Fixed quarter",AND(AND(ISNUMBER(I92),INT(I92)=I92),I92>=1),IF(C109="Linked to another product",AND(AND(ISNUMBER(MATCH(D109,$B$88:$B$91,0)),OR(IFERROR(INDEX($E$88:$E$91,MATCH(D109,$B$88:$B$91,0))="Yes",FALSE()),AND(ISNUMBER(I92),I92>=1,INT(I92)=I92))),COUNTIF(LISTS!$V$5:$V$9,E109)=1,AND(ISNUMBER(F109),INT(F109)=F109)),IF(C109="After own construction start",AND(AND(ISNUMBER(F109),INT(F109)=F109),G109<>"After own launch"),FALSE()))),IF(G109="Fixed quarter",AND(AND(ISNUMBER(M92),INT(M92)=M92),M92>=1),IF(G109="After own launch",AND(AND(ISNUMBER(J109),INT(J109)=J109),C109<>"After own construction start"),IF(G109="Linked to another product",AND(AND(ISNUMBER(MATCH(H109,$B$88:$B$91,0)),OR(IFERROR(INDEX($E$88:$E$91,MATCH(H109,$B$88:$B$91,0))="Yes",FALSE()),AND(ISNUMBER(M92),M92>=1,INT(M92)=M92))),COUNTIF(LISTS!$V$5:$V$9,I109)=1,AND(ISNUMBER(J109),INT(J109)=J109)),FALSE()))),ISNUMBER(L109),L109>=1,ISNUMBER(M109),M109>=1),"OK","ERROR")) -> Off | O109: =IF(OR(N109="Off",E92<>"Yes"),"—",IF(N109<>"OK","Fix this row","Launch "&"Q"&L109&" ("&IF(C109="Fixed quarter","fixed",IF(C109="Linked to another product",IF(IFERROR(INDEX($E$88:$E$97,MATCH(D109,$B$88:$B$97,0))="Yes",FALSE()),IF(F109<0,ABS(F109)&" qtr(s) before ",F109&" qtr(s) after ")&D109&" – "&LOWER(E109),"fixed fallback – "&D109&" not active"),IF(F109<0,ABS(F109)&" qtr(s) before ",F109&" qtr(s) after ")&"own construction start"))&") | Construction "&"Q"&M109&" ("&IF(G109="Fixed quarter","fixed",IF(G109="After own launch",IF(J109<0,ABS(J109)&" qtr(s) before ",J109&" qtr(s) after ")&"own launch",IF(IFERROR(INDEX($E$88:$E$97,MATCH(H109,$B$88:$B$97,0))="Yes",FALSE()),IF(J109<0,ABS(J109)&" qtr(s) before ",J109&" qtr(s) after ")&H109&" – "&LOWER(I109),"fixed fallback – "&H109&" not active")))&")")) -> —
...

Sheet TIMELINE
B2: TIMELINE ENGINE — 40 quarters that switch themselves on and off
B3: Timeline engine status | C3: =IF(COUNTIF(C205:C210,"ERROR")=0,"OK","ERROR") -> OK
B4: No inputs on this sheet. Every cell reads the INPUTS sheet, so changing a date, duration or scenario re-draws everything here.
B6: A. QUARTER CALENDAR
B7: Quarter number | D7: =COLUMN()-COLUMN($C$7) -> 1 | E7: =COLUMN()-COLUMN($C$7) -> 2 | F7: =COLUMN()-COLUMN($C$7) -> 3 | G7: =COLUMN()-COLUMN($C$7) -> 4 | H7: =COLUMN()-COLUMN($C$7) -> 5 | I7: =COLUMN()-COLUMN($C$7) -> 6 | J7: =COLUMN()-COLUMN($C$7) -> 7 | K7: =COLUMN()-COLUMN($C$7) -> 8 | ... AQ7: =COLUMN()-COLUMN($C$7) -> 40
B8: Quarter label | D8: ="Q"&D$7 -> Q1 | E8: ="Q"&E$7 -> Q2 | F8: ="Q"&F$7 -> Q3 | G8: ="Q"&G$7 -> Q4 | H8: ="Q"&H$7 -> Q5 | I8: ="Q"&I$7 -> Q6 | J8: ="Q"&J$7 -> Q7 | K8: ="Q"&K$7 -> Q8 | ... AQ8: ="Q"&AQ$7 -> Q40
B9: Quarter end date | D9: =EOMONTH(INPUTS!$C$20,3*(D$7-1)) -> 46568 | E9: =EOMONTH(INPUTS!$C$20,3*(E$7-1)) -> 46660 | F9: =EOMONTH(INPUTS!$C$20,3*(F$7-1)) -> 46752 | G9: =EOMONTH(INPUTS!$C$20,3*(G$7-1)) -> 46843 | H9: =EOMONTH(INPUTS!$C$20,3*(H$7-1)) -> 46934 | I9: =EOMONTH(INPUTS!$C$20,3*(I$7-1)) -> 47026 | J9: =EOMONTH(INPUTS!$C$20,3*(J$7-1)) -> 47118 | K9: =EOMONTH(INPUTS!$C$20,3*(K$7-1)) -> 47208 | ... AQ9: =EOMONTH(INPUTS!$C$20,3*(AQ$7-1)) -> 50130
B10: Quarter start date | D10: =EOMONTH(D$9,-3)+1 -> 46478 | E10: =EOMONTH(E$9,-3)+1 -> 46569 | F10: =EOMONTH(F$9,-3)+1 -> 46661 | G10: =EOMONTH(G$9,-3)+1 -> 46753 | H10: =EOMONTH(H$9,-3)+1 -> 46844 | I10: =EOMONTH(I$9,-3)+1 -> 46935 | J10: =EOMONTH(J$9,-3)+1 -> 47027 | K10: =EOMONTH(K$9,-3)+1 -> 47119 | ... AQ10: =EOMONTH(AQ$9,-3)+1 -> 50041
B11: Period | D11: =TEXT(D$10,"mmm")&"–"&TEXT(D$9,"mmm yy") -> Apr–Jun 27 | E11: =TEXT(E$10,"mmm")&"–"&TEXT(E$9,"mmm yy") -> Jul–Sep 27 | F11: =TEXT(F$10,"mmm")&"–"&TEXT(F$9,"mmm yy") -> Oct–Dec 27 | G11: =TEXT(G$10,"mmm")&"–"&TEXT(G$9,"mmm yy") -> Jan–Mar 28 | H11: =TEXT(H$10,"mmm")&"–"&TEXT(H$9,"mmm yy") -> Apr–Jun 28 | I11: =TEXT(I$10,"mmm")&"–"&TEXT(I$9,"mmm yy") -> Jul–Sep 28 | J11: =TEXT(J$10,"mmm")&"–"&TEXT(J$9,"mmm yy") -> Oct–Dec 28 | K11: =TEXT(K$10,"mmm")&"–"&TEXT(K$9,"mmm yy") -> Jan–Mar 29 | ... AQ11: =TEXT(AQ$10,"mmm")&"–"&TEXT(AQ$9,"mmm yy") -> Jan–Mar 37
B12: Financial year end (Apr–Mar) | D12: =YEAR(D$9)+IF(MONTH(D$9)>3,1,0) -> 2028 | E12: =YEAR(E$9)+IF(MONTH(E$9)>3,1,0) -> 2028 | F12: =YEAR(F$9)+IF(MONTH(F$9)>3,1,0) -> 2028 | G12: =YEAR(G$9)+IF(MONTH(G$9)>3,1,0) -> 2028 | H12: =YEAR(H$9)+IF(MONTH(H$9)>3,1,0) -> 2029 | I12: =YEAR(I$9)+IF(MONTH(I$9)>3,1,0) -> 2029 | J12: =YEAR(J$9)+IF(MONTH(J$9)>3,1,0) -> 2029 | K12: =YEAR(K$9)+IF(MONTH(K$9)>3,1,0) -> 2029 | ... AQ12: =YEAR(AQ$9)+IF(MONTH(AQ$9)>3,1,0) -> 2037
B13: Financial year | D13: ="FY "&(D$12-1)&"-"&RIGHT(D$12,2) -> FY 2027-28 | E13: ="FY "&(E$12-1)&"-"&RIGHT(E$12,2) -> FY 2027-28 | F13: ="FY "&(F$12-1)&"-"&RIGHT(F$12,2) -> FY 2027-28 | G13: ="FY "&(G$12-1)&"-"&RIGHT(G$12,2) -> FY 2027-28 | H13: ="FY "&(H$12-1)&"-"&RIGHT(H$12,2) -> FY 2028-29 | I13: ="FY "&(I$12-1)&"-"&RIGHT(I$12,2) -> FY 2028-29 | J13: ="FY "&(J$12-1)&"-"&RIGHT(J$12,2) -> FY 2028-29 | K13: ="FY "&(K$12-1)&"-"&RIGHT(K$12,2) -> FY 2028-29 | ... AQ13: ="FY "&(AQ$12-1)&"-"&RIGHT(AQ$12,2) -> FY 2036-37
B14: Quarter of financial year | D14: ="Q"&(INT(MOD(MONTH(D$9)-4,12)/3)+1) -> Q1 | E14: ="Q"&(INT(MOD(MONTH(E$9)-4,12)/3)+1) -> Q2 | F14: ="Q"&(INT(MOD(MONTH(F$9)-4,12)/3)+1) -> Q3 | G14: ="Q"&(INT(MOD(MONTH(G$9)-4,12)/3)+1) -> Q4 | H14: ="Q"&(INT(MOD(MONTH(H$9)-4,12)/3)+1) -> Q1 | I14: ="Q"&(INT(MOD(MONTH(I$9)-4,12)/3)+1) -> Q2 | J14: ="Q"&(INT(MOD(MONTH(J$9)-4,12)/3)+1) -> Q3 | K14: ="Q"&(INT(MOD(MONTH(K$9)-4,12)/3)+1) -> Q4 | ... AQ14: ="Q"&(INT(MOD(MONTH(AQ$9)-4,12)/3)+1) -> Q4
B15: Project year | D15: ="Y"&ROUNDUP(D$7/4,0) -> Y1 | E15: ="Y"&ROUNDUP(E$7/4,0) -> Y1 | F15: ="Y"&ROUNDUP(F$7/4,0) -> Y1 | G15: ="Y"&ROUNDUP(G$7/4,0) -> Y1 | H15: ="Y"&ROUNDUP(H$7/4,0) -> Y2 | I15: ="Y"&ROUNDUP(I$7/4,0) -> Y2 | J15: ="Y"&ROUNDUP(J$7/4,0) -> Y2 | K15: ="Y"&ROUNDUP(K$7/4,0) -> Y2 | ... AQ15: ="Y"&ROUNDUP(AQ$7/4,0) -> Y10
B16: Within model horizon (1 = yes) | C16: =SUM(D16:AQ16) -> 40 | D16: =--(D$7<=INPUTS!$C$24) -> 1 | E16: =--(E$7<=INPUTS!$C$24) -> 1 | F16: =--(F$7<=INPUTS!$C$24) -> 1 | G16: =--(G$7<=INPUTS!$C$24) -> 1 | H16: =--(H$7<=INPUTS!$C$24) -> 1 | I16: =--(I$7<=INPUTS!$C$24) -> 1 | J16: =--(J$7<=INPUTS!$C$24) -> 1 | K16: =--(K$7<=INPUTS!$C$24) -> 1 | ... AQ16: =--(AQ$7<=INPUTS!$C$24) -> 1
B17: Project active (1 = yes) | C17: =SUM(D17:AQ17) -> 20 | D17: =D$16*--(D$7<=INPUTS!$C$29) -> 1 | E17: =E$16*--(E$7<=INPUTS!$C$29) -> 1 | F17: =F$16*--(F$7<=INPUTS!$C$29) -> 1 | G17: =G$16*--(G$7<=INPUTS!$C$29) -> 1 | H17: =H$16*--(H$7<=INPUTS!$C$29) -> 1 | I17: =I$16*--(I$7<=INPUTS!$C$29) -> 1 | J17: =J$16*--(J$7<=INPUTS!$C$29) -> 1 | K17: =K$16*--(K$7<=INPUTS!$C$29) -> 1 | ... AQ17: =AQ$16*--(AQ$7<=INPUTS!$C$29) -> 0
B18: Project phase | D18: =IF(D$17=0,IF(D$16=0,"Beyond horizon","Post-project"),IF(AND(SUMPRODUCT((INPUTS!$E$88:$E$97="Yes")*(INPUTS!$P$88:$P$97<=D$7)*(INPUTS!$Q$88:$Q$97>=D$7))>0,SUMPRODUCT((INPUTS!$E$88:$E$97="Yes")*(INPUTS!$R$88:$R$97<=D$7)*(INPUTS!$S$88:$S$97>=D$7))>0),"Sales + Constr.",IF(SUMPRODUCT((INPUTS!$E$88:$E$97="Yes")*(INPUTS!$P$88:$P$97<=D$7)*(INPUTS!$Q$88:$Q$97>=D$7))>0,"Sales",IF(SUMPRODUCT((INPUTS!$E$88:$E$97="Yes")*(INPUTS!$R$88:$R$97<=D$7)*(INPUTS!$S$88:$S$97>=D$7))>0,"Construction",IF(D$7<MIN(INPUTS!$P$88:$P$97),"Pre-launch","Completion / handover"))))) -> Pre-launch | E18: =IF(E$17=0,IF(E$16=0,"Beyond horizon","Post-project"),IF(AND(SUMPRODUCT((INPUTS!$E$88:$E$97="Yes")*(INPUTS!$P$88:$P$97<=E$7)*(INPUTS!$Q$88:$Q$97>=E$7))>0,SUMPRODUCT((INPUTS!$E$88:$E$97="Yes")*(INPUTS!$R$88:$R$97<=E$7)*(INPUTS!$S$88:$S$97>=E$7))>0),"Sales + Constr.",IF(SUMPRODUCT((INPUTS!$E$88:$E$97="Yes")*(INPUTS!$P$88:$P$97<=E$7)*(INPUTS!$Q$88:$Q$97>=E$7))>0,"Sales",IF(SUMPRODUCT((INPUTS!$E$88:$E$97="Yes")*(INPUTS!$R$88:$R$97<=E$7)*(INPUTS!$S$88:$S$97>=E$7))>0,"Construction",IF(E$7<MIN(INPUTS!$P$88:$P$97),"Pre-launch","Completion / handover"))))) -> Pre-launch | F18: =IF(F$17=0,IF(F$16=0,"Beyond horizon","Post-project"),IF(AND(SUMPRODUCT((INPUTS!$E$88:$E$97="Yes")*(INPUTS!$P$88:$P$97<=F$7)*(INPUTS!$Q$88:$Q$97>=F$7))>0,SUMPRODUCT((INPUTS!$E$88:$E$97="Yes")*(INPUTS!$R$88:$R$97<=F$7)*(INPUTS!$S$88:$S$97>=F$7))>0),"Sales + Constr.",IF(SUMPRODUCT((INPUTS!$E$88:$E$97="Yes")*(INPUTS!$P$88:$P$97<=F$7)*(INPUTS!$Q$88:$Q$97>=F$7))>0,"Sales",IF(SUMPRODUCT((INPUTS!$E$88:$E$97="Yes")*(INPUTS!$R$88:$R$97<=F$7)*(INPUTS!$S$88:$S$97>=F$7))>0,"Construction",IF(F$7<MIN(INPUTS!$P$88:$P$97),"Pre-launch","Completion / handover"))))) -> Sales | G18: =IF(G$17=0,IF(G$16=0,"Beyond horizon","Post-project"),IF(AND(SUMPRODUCT((INPUTS!$E$88:$E$97="Yes")*(INPUTS!$P$88:$P$97<=G$7)*(INPUTS!$Q$88:$Q$97>=G$7))>0,SUMPRODUCT((INPUTS!$E$88:$E$97="Yes")*(INPUTS!$R$88:$R$97<=G$7)*(INPUTS!$S$88:$S$97>=G$7))>0),"Sales + Constr.",IF(SUMPRODUCT((INPUTS!$E$88:$E$97="Yes")*(INPUTS!$P$88:$P$97<=G$7)*(INPUTS!$Q$88:$Q$97>=G$7))>0,"Sales",IF(SUMPRODUCT((INPUTS!$E$88:$E$97="Yes")*(INPUTS!$R$88:$R$97<=G$7)*(INPUTS!$S$88:$S$97>=G$7))>0,"Construction",IF(G$7<MIN(INPUTS!$P$88:$P$97),"Pre-launch","Completion / handover"))))) -> Sales + Constr. | H18: =IF(H$17=0,IF(H$16=0,"Beyond horizon","Post-project"),IF(AND(SUMPRODUCT((INPUTS!$E$88:$E$97="Yes")*(INPUTS!$P$88:$P$97<=H$7)*(INPUTS!$Q$88:$Q$97>=H$7))>0,SUMPRODUCT((INPUTS!$E$88:$E$97="Yes")*(INPUTS!$R$88:$R$97<=H$7)*(INPUTS!$S$88:$S$97>=H$7))>0),"Sales + Constr.",IF(SUMPRODUCT((INPUTS!$E$88:$E$97="Yes")*(INPUTS!$P$88:$P$97<=H$7)*(INPUTS!$Q$88:$Q$97>=H$7))>0,"Sales",IF(SUMPRODUCT((INPUTS!$E$88:$E$97="Yes")*(INPUTS!$R$88:$R$97<=H$7)*(INPUTS!$S$88:$S$97>=H$7))>0,"Construction",IF(H$7<MIN(INPUTS!$P$88:$P$97),"Pre-launch","Completion / handover"))))) -> Sales + Constr. | I18: =IF(I$17=0,IF(I$16=0,"Beyond horizon","Post-project"),IF(AND(SUMPRODUCT((INPUTS!$E$88:$E$97="Yes")*(INPUTS!$P$88:$P$97<=I$7)*(INPUTS!$Q$88:$Q$97>=I$7))>0,SUMPRODUCT((INPUTS!$E$88:$E$97="Yes")*(INPUTS!$R$88:$R$97<=I$7)*(INPUTS!$S$88:$S$97>=I$7))>0),"Sales + Constr.",IF(SUMPRODUCT((INPUTS!$E$88:$E$97="Yes")*(INPUTS!$P$88:$P$97<=I$7)*(INPUTS!$Q$88:$Q$97>=I$7))>0,"Sales",IF(SUMPRODUCT((INPUTS!$E$88:$E$97="Yes")*(INPUTS!$R$88:$R$97<=I$7)*(INPUTS!$S$88:$S$97>=I$7))>0,"Construction",IF(I$7<MIN(INPUTS!$P$88:$P$97),"Pre-launch","Completion / handover"))))) -> Sales + Constr. | J18: =IF(J$17=0,IF(J$16=0,"Beyond horizon","Post-project"),IF(AND(SUMPRODUCT((INPUTS!$E$88:$E$97="Yes")*(INPUTS!$P$88:$P$97<=J$7)*(INPUTS!$Q$88:$Q$97>=J$7))>0,SUMPRODUCT((INPUTS!$E$88:$E$97="Yes")*(INPUTS!$R$88:$R$97<=J$7)*(INPUTS!$S$88:$S$97>=J$7))>0),"Sales + Constr.",IF(SUMPRODUCT((INPUTS!$E$88:$E$97="Yes")*(INPUTS!$P$88:$P$97<=J$7)*(INPUTS!$Q$88:$Q$97>=J$7))>0,"Sales",IF(SUMPRODUCT((INPUTS!$E$88:$E$97="Yes")*(INPUTS!$R$88:$R$97<=J$7)*(INPUTS!$S$88:$S$97>=J$7))>0,"Construction",IF(J$7<MIN(INPUTS!$P$88:$P$97),"Pre-launch","Completion / handover"))))) -> Sales + Constr. | K18: =IF(K$17=0,IF(K$16=0,"Beyond horizon","Post-project"),IF(AND(SUMPRODUCT((INPUTS!$E$88:$E$97="Yes")*(INPUTS!$P$88:$P$97<=K$7)*(INPUTS!$Q$88:$Q$97>=K$7))>0,SUMPRODUCT((INPUTS!$E$88:$E$97="Yes")*(INPUTS!$R$88:$R$97<=K$7)*(INPUTS!$S$88:$S$97>=K$7))>0),"Sales + Constr.",IF(SUMPRODUCT((INPUTS!$E$88:$E$97="Yes")*(INPUTS!$P$88:$P$97<=K$7)*(INPUTS!$Q$88:$Q$97>=K$7))>0,"Sales",IF(SUMPRODUCT((INPUTS!$E$88:$E$97="Yes")*(INPUTS!$R$88:$R$97<=K$7)*(INPUTS!$S$88:$S$97>=K$7))>0,"Construction",IF(K$7<MIN(INPUTS!$P$88:$P$97),"Pre-launch","Completion / handover"))))) -> Sales + Constr. | ... AQ18: =IF(AQ$17=0,IF(AQ$16=0,"Beyond horizon","Post-project"),IF(AND(SUMPRODUCT((INPUTS!$E$88:$E$97="Yes")*(INPUTS!$P$88:$P$97<=AQ$7)*(INPUTS!$Q$88:$Q$97>=AQ$7))>0,SUMPRODUCT((INPUTS!$E$88:$E$97="Yes")*(INPUTS!$R$88:$R$97<=AQ$7)*(INPUTS!$S$88:$S$97>=AQ$7))>0),"Sales + Constr.",IF(SUMPRODUCT((INPUTS!$E$88:$E$97="Yes")*(INPUTS!$P$88:$P$97<=AQ$7)*(INPUTS!$Q$88:$Q$97>=AQ$7))>0,"Sales",IF(SUMPRODUCT((INPUTS!$E$88:$E$97="Yes")*(INPUTS!$R$88:$R$97<=AQ$7)*(INPUTS!$S$88:$S$97>=AQ$7))>0,"Construction",IF(AQ$7<MIN(INPUTS!$P$88:$P$97),"Pre-launch","Completion / handover"))))) -> Post-project
B20: B. GANTT VIEW (S = selling, C = under construction, S+C = both, ✓ = construction complete)
B21: =IF(INPUTS!$E$88="Yes",INPUTS!$B$88,"(product row 1 – off)") -> Villas | D21: =IF(AND(AND(INPUTS!$E$88="Yes",D$16=1,D$7>=INPUTS!$P$88,D$7<=INPUTS!$Q$88),AND(INPUTS!$E$88="Yes",D$16=1,D$7>=INPUTS!$R$88,D$7<=INPUTS!$S$88)),"S+C",IF(AND(INPUTS!$E$88="Yes",D$16=1,D$7>=INPUTS!$P$88,D$7<=INPUTS!$Q$88),"S",IF(AND(INPUTS!$E$88="Yes",D$16=1,D$7>=INPUTS!$R$88,D$7<=INPUTS!$S$88),"C",IF(AND(INPUTS!$E$88="Yes",D$17=1,D$7>INPUTS!$S$88),"✓","")))) | E21: =IF(AND(AND(INPUTS!$E$88="Yes",E$16=1,E$7>=INPUTS!$P$88,E$7<=INPUTS!$Q$88),AND(INPUTS!$E$88="Yes",E$16=1,E$7>=INPUTS!$R$88,E$7<=INPUTS!$S$88)),"S+C",IF(AND(INPUTS!$E$88="Yes",E$16=1,E$7>=INPUTS!$P$88,E$7<=INPUTS!$Q$88),"S",IF(AND(INPUTS!$E$88="Yes",E$16=1,E$7>=INPUTS!$R$88,E$7<=INPUTS!$S$88),"C",IF(AND(INPUTS!$E$88="Yes",E$17=1,E$7>INPUTS!$S$88),"✓","")))) | F21: =IF(AND(AND(INPUTS!$E$88="Yes",F$16=1,F$7>=INPUTS!$P$88,F$7<=INPUTS!$Q$88),AND(INPUTS!$E$88="Yes",F$16=1,F$7>=INPUTS!$R$88,F$7<=INPUTS!$S$88)),"S+C",IF(AND(INPUTS!$E$88="Yes",F$16=1,F$7>=INPUTS!$P$88,F$7<=INPUTS!$Q$88),"S",IF(AND(INPUTS!$E$88="Yes",F$16=1,F$7>=INPUTS!$R$88,F$7<=INPUTS!$S$88),"C",IF(AND(INPUTS!$E$88="Yes",F$17=1,F$7>INPUTS!$S$88),"✓","")))) -> S | G21: =IF(AND(AND(INPUTS!$E$88="Yes",G$16=1,G$7>=INPUTS!$P$88,G$7<=INPUTS!$Q$88),AND(INPUTS!$E$88="Yes",G$16=1,G$7>=INPUTS!$R$88,G$7<=INPUTS!$S$88)),"S+C",IF(AND(INPUTS!$E$88="Yes",G$16=1,G$7>=INPUTS!$P$88,G$7<=INPUTS!$Q$88),"S",IF(AND(INPUTS!$E$88="Yes",G$16=1,G$7>=INPUTS!$R$88,G$7<=INPUTS!$S$88),"C",IF(AND(INPUTS!$E$88="Yes",G$17=1,G$7>INPUTS!$S$88),"✓","")))) -> S+C | H21: =IF(AND(AND(INPUTS!$E$88="Yes",H$16=1,H$7>=INPUTS!$P$88,H$7<=INPUTS!$Q$88),AND(INPUTS!$E$88="Yes",H$16=1,H$7>=INPUTS!$R$88,H$7<=INPUTS!$S$88)),"S+C",IF(AND(INPUTS!$E$88="Yes",H$16=1,H$7>=INPUTS!$P$88,H$7<=INPUTS!$Q$88),"S",IF(AND(INPUTS!$E$88="Yes",H$16=1,H$7>=INPUTS!$R$88,H$7<=INPUTS!$S$88),"C",IF(AND(INPUTS!$E$88="Yes",H$17=1,H$7>INPUTS!$S$88),"✓","")))) -> S+C | I21: =IF(AND(AND(INPUTS!$E$88="Yes",I$16=1,I$7>=INPUTS!$P$88,I$7<=INPUTS!$Q$88),AND(INPUTS!$E$88="Yes",I$16=1,I$7>=INPUTS!$R$88,I$7<=INPUTS!$S$88)),"S+C",IF(AND(INPUTS!$E$88="Yes",I$16=1,I$7>=INPUTS!$P$88,I$7<=INPUTS!$Q$88),"S",IF(AND(INPUTS!$E$88="Yes",I$16=1,I$7>=INPUTS!$R$88,I$7<=INPUTS!$S$88),"C",IF(AND(INPUTS!$E$88="Yes",I$17=1,I$7>INPUTS!$S$88),"✓","")))) -> S+C | J21: =IF(AND(AND(INPUTS!$E$88="Yes",J$16=1,J$7>=INPUTS!$P$88,J$7<=INPUTS!$Q$88),AND(INPUTS!$E$88="Yes",J$16=1,J$7>=INPUTS!$R$88,J$7<=INPUTS!$S$88)),"S+C",IF(AND(INPUTS!$E$88="Yes",J$16=1,J$7>=INPUTS!$P$88,J$7<=INPUTS!$Q$88),"S",IF(AND(INPUTS!$E$88="Yes",J$16=1,J$7>=INPUTS!$R$88,J$7<=INPUTS!$S$88),"C",IF(AND(INPUTS!$E$88="Yes",J$17=1,J$7>INPUTS!$S$88),"✓","")))) -> S+C | K21: =IF(AND(AND(INPUTS!$E$88="Yes",K$16=1,K$7>=INPUTS!$P$88,K$7<=INPUTS!$Q$88),AND(INPUTS!$E$88="Yes",K$16=1,K$7>=INPUTS!$R$88,K$7<=INPUTS!$S$88)),"S+C",IF(AND(INPUTS!$E$88="Yes",K$16=1,K$7>=INPUTS!$P$88,K$7<=INPUTS!$Q$88),"S",IF(AND(INPUTS!$E$88="Yes",K$16=1,K$7>=INPUTS!$R$88,K$7<=INPUTS!$S$88),"C",IF(AND(INPUTS!$E$88="Yes",K$17=1,K$7>INPUTS!$S$88),"✓","")))) -> S+C | ... AQ21: =IF(AND(AND(INPUTS!$E$88="Yes",AQ$16=1,AQ$7>=INPUTS!$P$88,AQ$7<=INPUTS!$Q$88),AND(INPUTS!$E$88="Yes",AQ$16=1,AQ$7>=INPUTS!$R$88,AQ$7<=INPUTS!$S$88)),"S+C",IF(AND(INPUTS!$E$88="Yes",AQ$16=1,AQ$7>=INPUTS!$P$88,AQ$7<=INPUTS!$Q$88),"S",IF(AND(INPUTS!$E$88="Yes",AQ$16=1,AQ$7>=INPUTS!$R$88,AQ$7<=INPUTS!$S$88),"C",IF(AND(INPUTS!$E$88="Yes",AQ$17=1,AQ$7>INPUTS!$S$88),"✓",""))))
B22: =IF(INPUTS!$E$89="Yes",INPUTS!$B$89,"(product row 2 – off)") -> Apartments – Towers A & B | D22: =IF(AND(AND(INPUTS!$E$89="Yes",D$16=1,D$7>=INPUTS!$P$89,D$7<=INPUTS!$Q$89),AND(INPUTS!$E$89="Yes",D$16=1,D$7>=INPUTS!$R$89,D$7<=INPUTS!$S$89)),"S+C",IF(AND(INPUTS!$E$89="Yes",D$16=1,D$7>=INPUTS!$P$89,D$7<=INPUTS!$Q$89),"S",IF(AND(INPUTS!$E$89="Yes",D$16=1,D$7>=INPUTS!$R$89,D$7<=INPUTS!$S$89),"C",IF(AND(INPUTS!$E$89="Yes",D$17=1,D$7>INPUTS!$S$89),"✓","")))) | E22: =IF(AND(AND(INPUTS!$E$89="Yes",E$16=1,E$7>=INPUTS!$P$89,E$7<=INPUTS!$Q$89),AND(INPUTS!$E$89="Yes",E$16=1,E$7>=INPUTS!$R$89,E$7<=INPUTS!$S$89)),"S+C",IF(AND(INPUTS!$E$89="Yes",E$16=1,E$7>=INPUTS!$P$89,E$7<=INPUTS!$Q$89),"S",IF(AND(INPUTS!$E$89="Yes",E$16=1,E$7>=INPUTS!$R$89,E$7<=INPUTS!$S$89),"C",IF(AND(INPUTS!$E$89="Yes",E$17=1,E$7>INPUTS!$S$89),"✓","")))) | F22: =IF(AND(AND(INPUTS!$E$89="Yes",F$16=1,F$7>=INPUTS!$P$89,F$7<=INPUTS!$Q$89),AND(INPUTS!$E$89="Yes",F$16=1,F$7>=INPUTS!$R$89,F$7<=INPUTS!$S$89)),"S+C",IF(AND(INPUTS!$E$89="Yes",F$16=1,F$7>=INPUTS!$P$89,F$7<=INPUTS!$Q$89),"S",IF(AND(INPUTS!$E$89="Yes",F$16=1,F$7>=INPUTS!$R$89,F$7<=INPUTS!$S$89),"C",IF(AND(INPUTS!$E$89="Yes",F$17=1,F$7>INPUTS!$S$89),"✓","")))) | G22: =IF(AND(AND(INPUTS!$E$89="Yes",G$16=1,G$7>=INPUTS!$P$89,G$7<=INPUTS!$Q$89),AND(INPUTS!$E$89="Yes",G$16=1,G$7>=INPUTS!$R$89,G$7<=INPUTS!$S$89)),"S+C",IF(AND(INPUTS!$E$89="Yes",G$16=1,G$7>=INPUTS!$P$89,G$7<=INPUTS!$Q$89),"S",IF(AND(INPUTS!$E$89="Yes",G$16=1,G$7>=INPUTS!$R$89,G$7<=INPUTS!$S$89),"C",IF(AND(INPUTS!$E$89="Yes",G$17=1,G$7>INPUTS!$S$89),"✓","")))) -> S | H22: =IF(AND(AND(INPUTS!$E$89="Yes",H$16=1,H$7>=INPUTS!$P$89,H$7<=INPUTS!$Q$89),AND(INPUTS!$E$89="Yes",H$16=1,H$7>=INPUTS!$R$89,H$7<=INPUTS!$S$89)),"S+C",IF(AND(INPUTS!$E$89="Yes",H$16=1,H$7>=INPUTS!$P$89,H$7<=INPUTS!$Q$89),"S",IF(AND(INPUTS!$E$89="Yes",H$16=1,H$7>=INPUTS!$R$89,H$7<=INPUTS!$S$89),"C",IF(AND(INPUTS!$E$89="Yes",H$17=1,H$7>INPUTS!$S$89),"✓","")))) -> S+C | I22: =IF(AND(AND(INPUTS!$E$89="Yes",I$16=1,I$7>=INPUTS!$P$89,I$7<=INPUTS!$Q$89),AND(INPUTS!$E$89="Yes",I$16=1,I$7>=INPUTS!$R$89,I$7<=INPUTS!$S$89)),"S+C",IF(AND(INPUTS!$E$89="Yes",I$16=1,I$7>=INPUTS!$P$89,I$7<=INPUTS!$Q$89),"S",IF(AND(INPUTS!$E$89="Yes",I$16=1,I$7>=INPUTS!$R$89,I$7<=INPUTS!$S$89),"C",IF(AND(INPUTS!$E$89="Yes",I$17=1,I$7>INPUTS!$S$89),"✓","")))) -> S+C | J22: =IF(AND(AND(INPUTS!$E$89="Yes",J$16=1,J$7>=INPUTS!$P$89,J$7<=INPUTS!$Q$89),AND(INPUTS!$E$89="Yes",J$16=1,J$7>=INPUTS!$R$89,J$7<=INPUTS!$S$89)),"S+C",IF(AND(INPUTS!$E$89="Yes",J$16=1,J$7>=INPUTS!$P$89,J$7<=INPUTS!$Q$89),"S",IF(AND(INPUTS!$E$89="Yes",J$16=1,J$7>=INPUTS!$R$89,J$7<=INPUTS!$S$89),"C",IF(AND(INPUTS!$E$89="Yes",J$17=1,J$7>INPUTS!$S$89),"✓","")))) -> S+C | K22: =IF(AND(AND(INPUTS!$E$89="Yes",K$16=1,K$7>=INPUTS!$P$89,K$7<=INPUTS!$Q$89),AND(INPUTS!$E$89="Yes",K$16=1,K$7>=INPUTS!$R$89,K$7<=INPUTS!$S$89)),"S+C",IF(AND(INPUTS!$E$89="Yes",K$16=1,K$7>=INPUTS!$P$89,K$7<=INPUTS!$Q$89),"S",IF(AND(INPUTS!$E$89="Yes",K$16=1,K$7>=INPUTS!$R$89,K$7<=INPUTS!$S$89),"C",IF(AND(INPUTS!$E$89="Yes",K$17=1,K$7>INPUTS!$S$89),"✓","")))) -> S+C | ... AQ22: =IF(AND(AND(INPUTS!$E$89="Yes",AQ$16=1,AQ$7>=INPUTS!$P$89,AQ$7<=INPUTS!$Q$89),AND(INPUTS!$E$89="Yes",AQ$16=1,AQ$7>=INPUTS!$R$89,AQ$7<=INPUTS!$S$89)),"S+C",IF(AND(INPUTS!$E$89="Yes",AQ$16=1,AQ$7>=INPUTS!$P$89,AQ$7<=INPUTS!$Q$89),"S",IF(AND(INPUTS!$E$89="Yes",AQ$16=1,AQ$7>=INPUTS!$R$89,AQ$7<=INPUTS!$S$89),"C",IF(AND(INPUTS!$E$89="Yes",AQ$17=1,AQ$7>INPUTS!$S$89),"✓",""))))
B23: =IF(INPUTS!$E$90="Yes",INPUTS!$B$90,"(product row 3 – off)") -> Studios | D23: =IF(AND(AND(INPUTS!$E$90="Yes",D$16=1,D$7>=INPUTS!$P$90,D$7<=INPUTS!$Q$90),AND(INPUTS!$E$90="Yes",D$16=1,D$7>=INPUTS!$R$90,D$7<=INPUTS!$S$90)),"S+C",IF(AND(INPUTS!$E$90="Yes",D$16=1,D$7>=INPUTS!$P$90,D$7<=INPUTS!$Q$90),"S",IF(AND(INPUTS!$E$90="Yes",D$16=1,D$7>=INPUTS!$R$90,D$7<=INPUTS!$S$90),"C",IF(AND(INPUTS!$E$90="Yes",D$17=1,D$7>INPUTS!$S$90),"✓","")))) | E23: =IF(AND(AND(INPUTS!$E$90="Yes",E$16=1,E$7>=INPUTS!$P$90,E$7<=INPUTS!$Q$90),AND(INPUTS!$E$90="Yes",E$16=1,E$7>=INPUTS!$R$90,E$7<=INPUTS!$S$90)),"S+C",IF(AND(INPUTS!$E$90="Yes",E$16=1,E$7>=INPUTS!$P$90,E$7<=INPUTS!$Q$90),"S",IF(AND(INPUTS!$E$90="Yes",E$16=1,E$7>=INPUTS!$R$90,E$7<=INPUTS!$S$90),"C",IF(AND(INPUTS!$E$90="Yes",E$17=1,E$7>INPUTS!$S$90),"✓","")))) | F23: =IF(AND(AND(INPUTS!$E$90="Yes",F$16=1,F$7>=INPUTS!$P$90,F$7<=INPUTS!$Q$90),AND(INPUTS!$E$90="Yes",F$16=1,F$7>=INPUTS!$R$90,F$7<=INPUTS!$S$90)),"S+C",IF(AND(INPUTS!$E$90="Yes",F$16=1,F$7>=INPUTS!$P$90,F$7<=INPUTS!$Q$90),"S",IF(AND(INPUTS!$E$90="Yes",F$16=1,F$7>=INPUTS!$R$90,F$7<=INPUTS!$S$90),"C",IF(AND(INPUTS!$E$90="Yes",F$17=1,F$7>INPUTS!$S$90),"✓","")))) | G23: =IF(AND(AND(INPUTS!$E$90="Yes",G$16=1,G$7>=INPUTS!$P$90,G$7<=INPUTS!$Q$90),AND(INPUTS!$E$90="Yes",G$16=1,G$7>=INPUTS!$R$90,G$7<=INPUTS!$S$90)),"S+C",IF(AND(INPUTS!$E$90="Yes",G$16=1,G$7>=INPUTS!$P$90,G$7<=INPUTS!$Q$90),"S",IF(AND(INPUTS!$E$90="Yes",G$16=1,G$7>=INPUTS!$R$90,G$7<=INPUTS!$S$90),"C",IF(AND(INPUTS!$E$90="Yes",G$17=1,G$7>INPUTS!$S$90),"✓","")))) | H23: =IF(AND(AND(INPUTS!$E$90="Yes",H$16=1,H$7>=INPUTS!$P$90,H$7<=INPUTS!$Q$90),AND(INPUTS!$E$90="Yes",H$16=1,H$7>=INPUTS!$R$90,H$7<=INPUTS!$S$90)),"S+C",IF(AND(INPUTS!$E$90="Yes",H$16=1,H$7>=INPUTS!$P$90,H$7<=INPUTS!$Q$90),"S",IF(AND(INPUTS!$E$90="Yes",H$16=1,H$7>=INPUTS!$R$90,H$7<=INPUTS!$S$90),"C",IF(AND(INPUTS!$E$90="Yes",H$17=1,H$7>INPUTS!$S$90),"✓","")))) | I23: =IF(AND(AND(INPUTS!$E$90="Yes",I$16=1,I$7>=INPUTS!$P$90,I$7<=INPUTS!$Q$90),AND(INPUTS!$E$90="Yes",I$16=1,I$7>=INPUTS!$R$90,I$7<=INPUTS!$S$90)),"S+C",IF(AND(INPUTS!$E$90="Yes",I$16=1,I$7>=INPUTS!$P$90,I$7<=INPUTS!$Q$90),"S",IF(AND(INPUTS!$E$90="Yes",I$16=1,I$7>=INPUTS!$R$90,I$7<=INPUTS!$S$90),"C",IF(AND(INPUTS!$E$90="Yes",I$17=1,I$7>INPUTS!$S$90),"✓","")))) -> S+C | J23: =IF(AND(AND(INPUTS!$E$90="Yes",J$16=1,J$7>=INPUTS!$P$90,J$7<=INPUTS!$Q$90),AND(INPUTS!$E$90="Yes",J$16=1,J$7>=INPUTS!$R$90,J$7<=INPUTS!$S$90)),"S+C",IF(AND(INPUTS!$E$90="Yes",J$16=1,J$7>=INPUTS!$P$90,J$7<=INPUTS!$Q$90),"S",IF(AND(INPUTS!$E$90="Yes",J$16=1,J$7>=INPUTS!$R$90,J$7<=INPUTS!$S$90),"C",IF(AND(INPUTS!$E$90="Yes",J$17=1,J$7>INPUTS!$S$90),"✓","")))) -> S+C | K23: =IF(AND(AND(INPUTS!$E$90="Yes",K$16=1,K$7>=INPUTS!$P$90,K$7<=INPUTS!$Q$90),AND(INPUTS!$E$90="Yes",K$16=1,K$7>=INPUTS!$R$90,K$7<=INPUTS!$S$90)),"S+C",IF(AND(INPUTS!$E$90="Yes",K$16=1,K$7>=INPUTS!$P$90,K$7<=INPUTS!$Q$90),"S",IF(AND(INPUTS!$E$90="Yes",K$16=1,K$7>=INPUTS!$R$90,K$7<=INPUTS!$S$90),"C",IF(AND(INPUTS!$E$90="Yes",K$17=1,K$7>INPUTS!$S$90),"✓","")))) -> S+C | ... AQ23: =IF(AND(AND(INPUTS!$E$90="Yes",AQ$16=1,AQ$7>=INPUTS!$P$90,AQ$7<=INPUTS!$Q$90),AND(INPUTS!$E$90="Yes",AQ$16=1,AQ$7>=INPUTS!$R$90,AQ$7<=INPUTS!$S$90)),"S+C",IF(AND(INPUTS!$E$90="Yes",AQ$16=1,AQ$7>=INPUTS!$P$90,AQ$7<=INPUTS!$Q$90),"S",IF(AND(INPUTS!$E$90="Yes",AQ$16=1,AQ$7>=INPUTS!$R$90,AQ$7<=INPUTS!$S$90),"C",IF(AND(INPUTS!$E$90="Yes",AQ$17=1,AQ$7>INPUTS!$S$90),"✓",""))))
B24: =IF(INPUTS!$E$91="Yes",INPUTS!$B$91,"(product row 4 – off)") -> High-street retail | D24: =IF(AND(AND(INPUTS!$E$91="Yes",D$16=1,D$7>=INPUTS!$P$91,D$7<=INPUTS!$Q$91),AND(INPUTS!$E$91="Yes",D$16=1,D$7>=INPUTS!$R$91,D$7<=INPUTS!$S$91)),"S+C",IF(AND(INPUTS!$E$91="Yes",D$16=1,D$7>=INPUTS!$P$91,D$7<=INPUTS!$Q$91),"S",IF(AND(INPUTS!$E$91="Yes",D$16=1,D$7>=INPUTS!$R$91,D$7<=INPUTS!$S$91),"C",IF(AND(INPUTS!$E$91="Yes",D$17=1,D$7>INPUTS!$S$91),"✓","")))) | E24: =IF(AND(AND(INPUTS!$E$91="Yes",E$16=1,E$7>=INPUTS!$P$91,E$7<=INPUTS!$Q$91),AND(INPUTS!$E$91="Yes",E$16=1,E$7>=INPUTS!$R$91,E$7<=INPUTS!$S$91)),"S+C",IF(AND(INPUTS!$E$91="Yes",E$16=1,E$7>=INPUTS!$P$91,E$7<=INPUTS!$Q$91),"S",IF(AND(INPUTS!$E$91="Yes",E$16=1,E$7>=INPUTS!$R$91,E$7<=INPUTS!$S$91),"C",IF(AND(INPUTS!$E$91="Yes",E$17=1,E$7>INPUTS!$S$91),"✓","")))) | F24: =IF(AND(AND(INPUTS!$E$91="Yes",F$16=1,F$7>=INPUTS!$P$91,F$7<=INPUTS!$Q$91),AND(INPUTS!$E$91="Yes",F$16=1,F$7>=INPUTS!$R$91,F$7<=INPUTS!$S$91)),"S+C",IF(AND(INPUTS!$E$91="Yes",F$16=1,F$7>=INPUTS!$P$91,F$7<=INPUTS!$Q$91),"S",IF(AND(INPUTS!$E$91="Yes",F$16=1,F$7>=INPUTS!$R$91,F$7<=INPUTS!$S$91),"C",IF(AND(INPUTS!$E$91="Yes",F$17=1,F$7>INPUTS!$S$91),"✓","")))) | G24: =IF(AND(AND(INPUTS!$E$91="Yes",G$16=1,G$7>=INPUTS!$P$91,G$7<=INPUTS!$Q$91),AND(INPUTS!$E$91="Yes",G$16=1,G$7>=INPUTS!$R$91,G$7<=INPUTS!$S$91)),"S+C",IF(AND(INPUTS!$E$91="Yes",G$16=1,G$7>=INPUTS!$P$91,G$7<=INPUTS!$Q$91),"S",IF(AND(INPUTS!$E$91="Yes",G$16=1,G$7>=INPUTS!$R$91,G$7<=INPUTS!$S$91),"C",IF(AND(INPUTS!$E$91="Yes",G$17=1,G$7>INPUTS!$S$91),"✓","")))) | H24: =IF(AND(AND(INPUTS!$E$91="Yes",H$16=1,H$7>=INPUTS!$P$91,H$7<=INPUTS!$Q$91),AND(INPUTS!$E$91="Yes",H$16=1,H$7>=INPUTS!$R$91,H$7<=INPUTS!$S$91)),"S+C",IF(AND(INPUTS!$E$91="Yes",H$16=1,H$7>=INPUTS!$P$91,H$7<=INPUTS!$Q$91),"S",IF(AND(INPUTS!$E$91="Yes",H$16=1,H$7>=INPUTS!$R$91,H$7<=INPUTS!$S$91),"C",IF(AND(INPUTS!$E$91="Yes",H$17=1,H$7>INPUTS!$S$91),"✓","")))) | I24: =IF(AND(AND(INPUTS!$E$91="Yes",I$16=1,I$7>=INPUTS!$P$91,I$7<=INPUTS!$Q$91),AND(INPUTS!$E$91="Yes",I$16=1,I$7>=INPUTS!$R$91,I$7<=INPUTS!$S$91)),"S+C",IF(AND(INPUTS!$E$91="Yes",I$16=1,I$7>=INPUTS!$P$91,I$7<=INPUTS!$Q$91),"S",IF(AND(INPUTS!$E$91="Yes",I$16=1,I$7>=INPUTS!$R$91,I$7<=INPUTS!$S$91),"C",IF(AND(INPUTS!$E$91="Yes",I$17=1,I$7>INPUTS!$S$91),"✓","")))) -> C | J24: =IF(AND(AND(INPUTS!$E$91="Yes",J$16=1,J$7>=INPUTS!$P$91,J$7<=INPUTS!$Q$91),AND(INPUTS!$E$91="Yes",J$16=1,J$7>=INPUTS!$R$91,J$7<=INPUTS!$S$91)),"S+C",IF(AND(INPUTS!$E$91="Yes",J$16=1,J$7>=INPUTS!$P$91,J$7<=INPUTS!$Q$91),"S",IF(AND(INPUTS!$E$91="Yes",J$16=1,J$7>=INPUTS!$R$91,J$7<=INPUTS!$S$91),"C",IF(AND(INPUTS!$E$91="Yes",J$17=1,J$7>INPUTS!$S$91),"✓","")))) -> C | K24: =IF(AND(AND(INPUTS!$E$91="Yes",K$16=1,K$7>=INPUTS!$P$91,K$7<=INPUTS!$Q$91),AND(INPUTS!$E$91="Yes",K$16=1,K$7>=INPUTS!$R$91,K$7<=INPUTS!$S$91)),"S+C",IF(AND(INPUTS!$E$91="Yes",K$16=1,K$7>=INPUTS!$P$91,K$7<=INPUTS!$Q$91),"S",IF(AND(INPUTS!$E$91="Yes",K$16=1,K$7>=INPUTS!$R$91,K$7<=INPUTS!$S$91),"C",IF(AND(INPUTS!$E$91="Yes",K$17=1,K$7>INPUTS!$S$91),"✓","")))) -> S+C | ... AQ24: =IF(AND(AND(INPUTS!$E$91="Yes",AQ$16=1,AQ$7>=INPUTS!$P$91,AQ$7<=INPUTS!$Q$91),AND(INPUTS!$E$91="Yes",AQ$16=1,AQ$7>=INPUTS!$R$91,AQ$7<=INPUTS!$S$91)),"S+C",IF(AND(INPUTS!$E$91="Yes",AQ$16=1,AQ$7>=INPUTS!$P$91,AQ$7<=INPUTS!$Q$91),"S",IF(AND(INPUTS!$E$91="Yes",AQ$16=1,AQ$7>=INPUTS!$R$91,AQ$7<=INPUTS!$S$91),"C",IF(AND(INPUTS!$E$91="Yes",AQ$17=1,AQ$7>INPUTS!$S$91),"✓",""))))
B25: =IF(INPUTS!$E$92="Yes",INPUTS!$B$92,"(product row 5 – off)") -> (product row 5 – off) | D25: =IF(AND(AND(INPUTS!$E$92="Yes",D$16=1,D$7>=INPUTS!$P$92,D$7<=INPUTS!$Q$92),AND(INPUTS!$E$92="Yes",D$16=1,D$7>=INPUTS!$R$92,D$7<=INPUTS!$S$92)),"S+C",IF(AND(INPUTS!$E$92="Yes",D$16=1,D$7>=INPUTS!$P$92,D$7<=INPUTS!$Q$92),"S",IF(AND(INPUTS!$E$92="Yes",D$16=1,D$7>=INPUTS!$R$92,D$7<=INPUTS!$S$92),"C",IF(AND(INPUTS!$E$92="Yes",D$17=1,D$7>INPUTS!$S$92),"✓","")))) | E25: =IF(AND(AND(INPUTS!$E$92="Yes",E$16=1,E$7>=INPUTS!$P$92,E$7<=INPUTS!$Q$92),AND(INPUTS!$E$92="Yes",E$16=1,E$7>=INPUTS!$R$92,E$7<=INPUTS!$S$92)),"S+C",IF(AND(INPUTS!$E$92="Yes",E$16=1,E$7>=INPUTS!$P$92,E$7<=INPUTS!$Q$92),"S",IF(AND(INPUTS!$E$92="Yes",E$16=1,E$7>=INPUTS!$R$92,E$7<=INPUTS!$S$92),"C",IF(AND(INPUTS!$E$92="Yes",E$17=1,E$7>INPUTS!$S$92),"✓","")))) | F25: =IF(AND(AND(INPUTS!$E$92="Yes",F$16=1,F$7>=INPUTS!$P$92,F$7<=INPUTS!$Q$92),AND(INPUTS!$E$92="Yes",F$16=1,F$7>=INPUTS!$R$92,F$7<=INPUTS!$S$92)),"S+C",IF(AND(INPUTS!$E$92="Yes",F$16=1,F$7>=INPUTS!$P$92,F$7<=INPUTS!$Q$92),"S",IF(AND(INPUTS!$E$92="Yes",F$16=1,F$7>=INPUTS!$R$92,F$7<=INPUTS!$S$92),"C",IF(AND(INPUTS!$E$92="Yes",F$17=1,F$7>INPUTS!$S$92),"✓","")))) | G25: =IF(AND(AND(INPUTS!$E$92="Yes",G$16=1,G$7>=INPUTS!$P$92,G$7<=INPUTS!$Q$92),AND(INPUTS!$E$92="Yes",G$16=1,G$7>=INPUTS!$R$92,G$7<=INPUTS!$S$92)),"S+C",IF(AND(INPUTS!$E$92="Yes",G$16=1,G$7>=INPUTS!$P$92,G$7<=INPUTS!$Q$92),"S",IF(AND(INPUTS!$E$92="Yes",G$16=1,G$7>=INPUTS!$R$92,G$7<=INPUTS!$S$92),"C",IF(AND(INPUTS!$E$92="Yes",G$17=1,G$7>INPUTS!$S$92),"✓","")))) | H25: =IF(AND(AND(INPUTS!$E$92="Yes",H$16=1,H$7>=INPUTS!$P$92,H$7<=INPUTS!$Q$92),AND(INPUTS!$E$92="Yes",H$16=1,H$7>=INPUTS!$R$92,H$7<=INPUTS!$S$92)),"S+C",IF(AND(INPUTS!$E$92="Yes",H$16=1,H$7>=INPUTS!$P$92,H$7<=INPUTS!$Q$92),"S",IF(AND(INPUTS!$E$92="Yes",H$16=1,H$7>=INPUTS!$R$92,H$7<=INPUTS!$S$92),"C",IF(AND(INPUTS!$E$92="Yes",H$17=1,H$7>INPUTS!$S$92),"✓","")))) | I25: =IF(AND(AND(INPUTS!$E$92="Yes",I$16=1,I$7>=INPUTS!$P$92,I$7<=INPUTS!$Q$92),AND(INPUTS!$E$92="Yes",I$16=1,I$7>=INPUTS!$R$92,I$7<=INPUTS!$S$92)),"S+C",IF(AND(INPUTS!$E$92="Yes",I$16=1,I$7>=INPUTS!$P$92,I$7<=INPUTS!$Q$92),"S",IF(AND(INPUTS!$E$92="Yes",I$16=1,I$7>=INPUTS!$R$92,I$7<=INPUTS!$S$92),"C",IF(AND(INPUTS!$E$92="Yes",I$17=1,I$7>INPUTS!$S$92),"✓","")))) | J25: =IF(AND(AND(INPUTS!$E$92="Yes",J$16=1,J$7>=INPUTS!$P$92,J$7<=INPUTS!$Q$92),AND(INPUTS!$E$92="Yes",J$16=1,J$7>=INPUTS!$R$92,J$7<=INPUTS!$S$92)),"S+C",IF(AND(INPUTS!$E$92="Yes",J$16=1,J$7>=INPUTS!$P$92,J$7<=INPUTS!$Q$92),"S",IF(AND(INPUTS!$E$92="Yes",J$16=1,J$7>=INPUTS!$R$92,J$7<=INPUTS!$S$92),"C",IF(AND(INPUTS!$E$92="Yes",J$17=1,J$7>INPUTS!$S$92),"✓","")))) | K25: =IF(AND(AND(INPUTS!$E$92="Yes",K$16=1,K$7>=INPUTS!$P$92,K$7<=INPUTS!$Q$92),AND(INPUTS!$E$92="Yes",K$16=1,K$7>=INPUTS!$R$92,K$7<=INPUTS!$S$92)),"S+C",IF(AND(INPUTS!$E$92="Yes",K$16=1,K$7>=INPUTS!$P$92,K$7<=INPUTS!$Q$92),"S",IF(AND(INPUTS!$E$92="Yes",K$16=1,K$7>=INPUTS!$R$92,K$7<=INPUTS!$S$92),"C",IF(AND(INPUTS!$E$92="Yes",K$17=1,K$7>INPUTS!$S$92),"✓","")))) | ... AQ25: =IF(AND(AND(INPUTS!$E$92="Yes",AQ$16=1,AQ$7>=INPUTS!$P$92,AQ$7<=INPUTS!$Q$92),AND(INPUTS!$E$92="Yes",AQ$16=1,AQ$7>=INPUTS!$R$92,AQ$7<=INPUTS!$S$92)),"S+C",IF(AND(INPUTS!$E$92="Yes",AQ$16=1,AQ$7>=INPUTS!$P$92,AQ$7<=INPUTS!$Q$92),"S",IF(AND(INPUTS!$E$92="Yes",AQ$16=1,AQ$7>=INPUTS!$R$92,AQ$7<=INPUTS!$S$92),"C",IF(AND(INPUTS!$E$92="Yes",AQ$17=1,AQ$7>INPUTS!$S$92),"✓",""))))
B26: =IF(INPUTS!$E$93="Yes",INPUTS!$B$93,"(product row 6 – off)") -> (product row 6 – off) | D26: =IF(AND(AND(INPUTS!$E$93="Yes",D$16=1,D$7>=INPUTS!$P$93,D$7<=INPUTS!$Q$93),AND(INPUTS!$E$93="Yes",D$16=1,D$7>=INPUTS!$R$93,D$7<=INPUTS!$S$93)),"S+C",IF(AND(INPUTS!$E$93="Yes",D$16=1,D$7>=INPUTS!$P$93,D$7<=INPUTS!$Q$93),"S",IF(AND(INPUTS!$E$93="Yes",D$16=1,D$7>=INPUTS!$R$93,D$7<=INPUTS!$S$93),"C",IF(AND(INPUTS!$E$93="Yes",D$17=1,D$7>INPUTS!$S$93),"✓","")))) | E26: =IF(AND(AND(INPUTS!$E$93="Yes",E$16=1,E$7>=INPUTS!$P$93,E$7<=INPUTS!$Q$93),AND(INPUTS!$E$93="Yes",E$16=1,E$7>=INPUTS!$R$93,E$7<=INPUTS!$S$93)),"S+C",IF(AND(INPUTS!$E$93="Yes",E$16=1,E$7>=INPUTS!$P$93,E$7<=INPUTS!$Q$93),"S",IF(AND(INPUTS!$E$93="Yes",E$16=1,E$7>=INPUTS!$R$93,E$7<=INPUTS!$S$93),"C",IF(AND(INPUTS!$E$93="Yes",E$17=1,E$7>INPUTS!$S$93),"✓","")))) | F26: =IF(AND(AND(INPUTS!$E$93="Yes",F$16=1,F$7>=INPUTS!$P$93,F$7<=INPUTS!$Q$93),AND(INPUTS!$E$93="Yes",F$16=1,F$7>=INPUTS!$R$93,F$7<=INPUTS!$S$93)),"S+C",IF(AND(INPUTS!$E$93="Yes",F$16=1,F$7>=INPUTS!$P$93,F$7<=INPUTS!$Q$93),"S",IF(AND(INPUTS!$E$93="Yes",F$16=1,F$7>=INPUTS!$R$93,F$7<=INPUTS!$S$93),"C",IF(AND(INPUTS!$E$93="Yes",F$17=1,F$7>INPUTS!$S$93),"✓","")))) | G26: =IF(AND(AND(INPUTS!$E$93="Yes",G$16=1,G$7>=INPUTS!$P$93,G$7<=INPUTS!$Q$93),AND(INPUTS!$E$93="Yes",G$16=1,G$7>=INPUTS!$R$93,G$7<=INPUTS!$S$93)),"S+C",IF(AND(INPUTS!$E$93="Yes",G$16=1,G$7>=INPUTS!$P$93,G$7<=INPUTS!$Q$93),"S",IF(AND(INPUTS!$E$93="Yes",G$16=1,G$7>=INPUTS!$R$93,G$7<=INPUTS!$S$93),"C",IF(AND(INPUTS!$E$93="Yes",G$17=1,G$7>INPUTS!$S$93),"✓","")))) | H26: =IF(AND(AND(INPUTS!$E$93="Yes",H$16=1,H$7>=INPUTS!$P$93,H$7<=INPUTS!$Q$93),AND(INPUTS!$E$93="Yes",H$16=1,H$7>=INPUTS!$R$93,H$7<=INPUTS!$S$93)),"S+C",IF(AND(INPUTS!$E$93="Yes",H$16=1,H$7>=INPUTS!$P$93,H$7<=INPUTS!$Q$93),"S",IF(AND(INPUTS!$E$93="Yes",H$16=1,H$7>=INPUTS!$R$93,H$7<=INPUTS!$S$93),"C",IF(AND(INPUTS!$E$93="Yes",H$17=1,H$7>INPUTS!$S$93),"✓","")))) | I26: =IF(AND(AND(INPUTS!$E$93="Yes",I$16=1,I$7>=INPUTS!$P$93,I$7<=INPUTS!$Q$93),AND(INPUTS!$E$93="Yes",I$16=1,I$7>=INPUTS!$R$93,I$7<=INPUTS!$S$93)),"S+C",IF(AND(INPUTS!$E$93="Yes",I$16=1,I$7>=INPUTS!$P$93,I$7<=INPUTS!$Q$93),"S",IF(AND(INPUTS!$E$93="Yes",I$16=1,I$7>=INPUTS!$R$93,I$7<=INPUTS!$S$93),"C",IF(AND(INPUTS!$E$93="Yes",I$17=1,I$7>INPUTS!$S$93),"✓","")))) | J26: =IF(AND(AND(INPUTS!$E$93="Yes",J$16=1,J$7>=INPUTS!$P$93,J$7<=INPUTS!$Q$93),AND(INPUTS!$E$93="Yes",J$16=1,J$7>=INPUTS!$R$93,J$7<=INPUTS!$S$93)),"S+C",IF(AND(INPUTS!$E$93="Yes",J$16=1,J$7>=INPUTS!$P$93,J$7<=INPUTS!$Q$93),"S",IF(AND(INPUTS!$E$93="Yes",J$16=1,J$7>=INPUTS!$R$93,J$7<=INPUTS!$S$93),"C",IF(AND(INPUTS!$E$93="Yes",J$17=1,J$7>INPUTS!$S$93),"✓","")))) | K26: =IF(AND(AND(INPUTS!$E$93="Yes",K$16=1,K$7>=INPUTS!$P$93,K$7<=INPUTS!$Q$93),AND(INPUTS!$E$93="Yes",K$16=1,K$7>=INPUTS!$R$93,K$7<=INPUTS!$S$93)),"S+C",IF(AND(INPUTS!$E$93="Yes",K$16=1,K$7>=INPUTS!$P$93,K$7<=INPUTS!$Q$93),"S",IF(AND(INPUTS!$E$93="Yes",K$16=1,K$7>=INPUTS!$R$93,K$7<=INPUTS!$S$93),"C",IF(AND(INPUTS!$E$93="Yes",K$17=1,K$7>INPUTS!$S$93),"✓","")))) | ... AQ26: =IF(AND(AND(INPUTS!$E$93="Yes",AQ$16=1,AQ$7>=INPUTS!$P$93,AQ$7<=INPUTS!$Q$93),AND(INPUTS!$E$93="Yes",AQ$16=1,AQ$7>=INPUTS!$R$93,AQ$7<=INPUTS!$S$93)),"S+C",IF(AND(INPUTS!$E$93="Yes",AQ$16=1,AQ$7>=INPUTS!$P$93,AQ$7<=INPUTS!$Q$93),"S",IF(AND(INPUTS!$E$93="Yes",AQ$16=1,AQ$7>=INPUTS!$R$93,AQ$7<=INPUTS!$S$93),"C",IF(AND(INPUTS!$E$93="Yes",AQ$17=1,AQ$7>INPUTS!$S$93),"✓",""))))
B27: =IF(INPUTS!$E$94="Yes",INPUTS!$B$94,"(product row 7 – off)") -> (product row 7 – off) | D27: =IF(AND(AND(INPUTS!$E$94="Yes",D$16=1,D$7>=INPUTS!$P$94,D$7<=INPUTS!$Q$94),AND(INPUTS!$E$94="Yes",D$16=1,D$7>=INPUTS!$R$94,D$7<=INPUTS!$S$94)),"S+C",IF(AND(INPUTS!$E$94="Yes",D$16=1,D$7>=INPUTS!$P$94,D$7<=INPUTS!$Q$94),"S",IF(AND(INPUTS!$E$94="Yes",D$16=1,D$7>=INPUTS!$R$94,D$7<=INPUTS!$S$94),"C",IF(AND(INPUTS!$E$94="Yes",D$17=1,D$7>INPUTS!$S$94),"✓","")))) | E27: =IF(AND(AND(INPUTS!$E$94="Yes",E$16=1,E$7>=INPUTS!$P$94,E$7<=INPUTS!$Q$94),AND(INPUTS!$E$94="Yes",E$16=1,E$7>=INPUTS!$R$94,E$7<=INPUTS!$S$94)),"S+C",IF(AND(INPUTS!$E$94="Yes",E$16=1,E$7>=INPUTS!$P$94,E$7<=INPUTS!$Q$94),"S",IF(AND(INPUTS!$E$94="Yes",E$16=1,E$7>=INPUTS!$R$94,E$7<=INPUTS!$S$94),"C",IF(AND(INPUTS!$E$94="Yes",E$17=1,E$7>INPUTS!$S$94),"✓","")))) | F27: =IF(AND(AND(INPUTS!$E$94="Yes",F$16=1,F$7>=INPUTS!$P$94,F$7<=INPUTS!$Q$94),AND(INPUTS!$E$94="Yes",F$16=1,F$7>=INPUTS!$R$94,F$7<=INPUTS!$S$94)),"S+C",IF(AND(INPUTS!$E$94="Yes",F$16=1,F$7>=INPUTS!$P$94,F$7<=INPUTS!$Q$94),"S",IF(AND(INPUTS!$E$94="Yes",F$16=1,F$7>=INPUTS!$R$94,F$7<=INPUTS!$S$94),"C",IF(AND(INPUTS!$E$94="Yes",F$17=1,F$7>INPUTS!$S$94),"✓","")))) | G27: =IF(AND(AND(INPUTS!$E$94="Yes",G$16=1,G$7>=INPUTS!$P$94,G$7<=INPUTS!$Q$94),AND(INPUTS!$E$94="Yes",G$16=1,G$7>=INPUTS!$R$94,G$7<=INPUTS!$S$94)),"S+C",IF(AND(INPUTS!$E$94="Yes",G$16=1,G$7>=INPUTS!$P$94,G$7<=INPUTS!$Q$94),"S",IF(AND(INPUTS!$E$94="Yes",G$16=1,G$7>=INPUTS!$R$94,G$7<=INPUTS!$S$94),"C",IF(AND(INPUTS!$E$94="Yes",G$17=1,G$7>INPUTS!$S$94),"✓","")))) | H27: =IF(AND(AND(INPUTS!$E$94="Yes",H$16=1,H$7>=INPUTS!$P$94,H$7<=INPUTS!$Q$94),AND(INPUTS!$E$94="Yes",H$16=1,H$7>=INPUTS!$R$94,H$7<=INPUTS!$S$94)),"S+C",IF(AND(INPUTS!$E$94="Yes",H$16=1,H$7>=INPUTS!$P$94,H$7<=INPUTS!$Q$94),"S",IF(AND(INPUTS!$E$94="Yes",H$16=1,H$7>=INPUTS!$R$94,H$7<=INPUTS!$S$94),"C",IF(AND(INPUTS!$E$94="Yes",H$17=1,H$7>INPUTS!$S$94),"✓","")))) | I27: =IF(AND(AND(INPUTS!$E$94="Yes",I$16=1,I$7>=INPUTS!$P$94,I$7<=INPUTS!$Q$94),AND(INPUTS!$E$94="Yes",I$16=1,I$7>=INPUTS!$R$94,I$7<=INPUTS!$S$94)),"S+C",IF(AND(INPUTS!$E$94="Yes",I$16=1,I$7>=INPUTS!$P$94,I$7<=INPUTS!$Q$94),"S",IF(AND(INPUTS!$E$94="Yes",I$16=1,I$7>=INPUTS!$R$94,I$7<=INPUTS!$S$94),"C",IF(AND(INPUTS!$E$94="Yes",I$17=1,I$7>INPUTS!$S$94),"✓","")))) | J27: =IF(AND(AND(INPUTS!$E$94="Yes",J$16=1,J$7>=INPUTS!$P$94,J$7<=INPUTS!$Q$94),AND(INPUTS!$E$94="Yes",J$16=1,J$7>=INPUTS!$R$94,J$7<=INPUTS!$S$94)),"S+C",IF(AND(INPUTS!$E$94="Yes",J$16=1,J$7>=INPUTS!$P$94,J$7<=INPUTS!$Q$94),"S",IF(AND(INPUTS!$E$94="Yes",J$16=1,J$7>=INPUTS!$R$94,J$7<=INPUTS!$S$94),"C",IF(AND(INPUTS!$E$94="Yes",J$17=1,J$7>INPUTS!$S$94),"✓","")))) | K27: =IF(AND(AND(INPUTS!$E$94="Yes",K$16=1,K$7>=INPUTS!$P$94,K$7<=INPUTS!$Q$94),AND(INPUTS!$E$94="Yes",K$16=1,K$7>=INPUTS!$R$94,K$7<=INPUTS!$S$94)),"S+C",IF(AND(INPUTS!$E$94="Yes",K$16=1,K$7>=INPUTS!$P$94,K$7<=INPUTS!$Q$94),"S",IF(AND(INPUTS!$E$94="Yes",K$16=1,K$7>=INPUTS!$R$94,K$7<=INPUTS!$S$94),"C",IF(AND(INPUTS!$E$94="Yes",K$17=1,K$7>INPUTS!$S$94),"✓","")))) | ... AQ27: =IF(AND(AND(INPUTS!$E$94="Yes",AQ$16=1,AQ$7>=INPUTS!$P$94,AQ$7<=INPUTS!$Q$94),AND(INPUTS!$E$94="Yes",AQ$16=1,AQ$7>=INPUTS!$R$94,AQ$7<=INPUTS!$S$94)),"S+C",IF(AND(INPUTS!$E$94="Yes",AQ$16=1,AQ$7>=INPUTS!$P$94,AQ$7<=INPUTS!$Q$94),"S",IF(AND(INPUTS!$E$94="Yes",AQ$16=1,AQ$7>=INPUTS!$R$94,AQ$7<=INPUTS!$S$94),"C",IF(AND(INPUTS!$E$94="Yes",AQ$17=1,AQ$7>INPUTS!$S$94),"✓",""))))
B28: =IF(INPUTS!$E$95="Yes",INPUTS!$B$95,"(product row 8 – off)") -> (product row 8 – off) | D28: =IF(AND(AND(INPUTS!$E$95="Yes",D$16=1,D$7>=INPUTS!$P$95,D$7<=INPUTS!$Q$95),AND(INPUTS!$E$95="Yes",D$16=1,D$7>=INPUTS!$R$95,D$7<=INPUTS!$S$95)),"S+C",IF(AND(INPUTS!$E$95="Yes",D$16=1,D$7>=INPUTS!$P$95,D$7<=INPUTS!$Q$95),"S",IF(AND(INPUTS!$E$95="Yes",D$16=1,D$7>=INPUTS!$R$95,D$7<=INPUTS!$S$95),"C",IF(AND(INPUTS!$E$95="Yes",D$17=1,D$7>INPUTS!$S$95),"✓","")))) | E28: =IF(AND(AND(INPUTS!$E$95="Yes",E$16=1,E$7>=INPUTS!$P$95,E$7<=INPUTS!$Q$95),AND(INPUTS!$E$95="Yes",E$16=1,E$7>=INPUTS!$R$95,E$7<=INPUTS!$S$95)),"S+C",IF(AND(INPUTS!$E$95="Yes",E$16=1,E$7>=INPUTS!$P$95,E$7<=INPUTS!$Q$95),"S",IF(AND(INPUTS!$E$95="Yes",E$16=1,E$7>=INPUTS!$R$95,E$7<=INPUTS!$S$95),"C",IF(AND(INPUTS!$E$95="Yes",E$17=1,E$7>INPUTS!$S$95),"✓","")))) | F28: =IF(AND(AND(INPUTS!$E$95="Yes",F$16=1,F$7>=INPUTS!$P$95,F$7<=INPUTS!$Q$95),AND(INPUTS!$E$95="Yes",F$16=1,F$7>=INPUTS!$R$95,F$7<=INPUTS!$S$95)),"S+C",IF(AND(INPUTS!$E$95="Yes",F$16=1,F$7>=INPUTS!$P$95,F$7<=INPUTS!$Q$95),"S",IF(AND(INPUTS!$E$95="Yes",F$16=1,F$7>=INPUTS!$R$95,F$7<=INPUTS!$S$95),"C",IF(AND(INPUTS!$E$95="Yes",F$17=1,F$7>INPUTS!$S$95),"✓","")))) | G28: =IF(AND(AND(INPUTS!$E$95="Yes",G$16=1,G$7>=INPUTS!$P$95,G$7<=INPUTS!$Q$95),AND(INPUTS!$E$95="Yes",G$16=1,G$7>=INPUTS!$R$95,G$7<=INPUTS!$S$95)),"S+C",IF(AND(INPUTS!$E$95="Yes",G$16=1,G$7>=INPUTS!$P$95,G$7<=INPUTS!$Q$95),"S",IF(AND(INPUTS!$E$95="Yes",G$16=1,G$7>=INPUTS!$R$95,G$7<=INPUTS!$S$95),"C",IF(AND(INPUTS!$E$95="Yes",G$17=1,G$7>INPUTS!$S$95),"✓","")))) | H28: =IF(AND(AND(INPUTS!$E$95="Yes",H$16=1,H$7>=INPUTS!$P$95,H$7<=INPUTS!$Q$95),AND(INPUTS!$E$95="Yes",H$16=1,H$7>=INPUTS!$R$95,H$7<=INPUTS!$S$95)),"S+C",IF(AND(INPUTS!$E$95="Yes",H$16=1,H$7>=INPUTS!$P$95,H$7<=INPUTS!$Q$95),"S",IF(AND(INPUTS!$E$95="Yes",H$16=1,H$7>=INPUTS!$R$95,H$7<=INPUTS!$S$95),"C",IF(AND(INPUTS!$E$95="Yes",H$17=1,H$7>INPUTS!$S$95),"✓","")))) | I28: =IF(AND(AND(INPUTS!$E$95="Yes",I$16=1,I$7>=INPUTS!$P$95,I$7<=INPUTS!$Q$95),AND(INPUTS!$E$95="Yes",I$16=1,I$7>=INPUTS!$R$95,I$7<=INPUTS!$S$95)),"S+C",IF(AND(INPUTS!$E$95="Yes",I$16=1,I$7>=INPUTS!$P$95,I$7<=INPUTS!$Q$95),"S",IF(AND(INPUTS!$E$95="Yes",I$16=1,I$7>=INPUTS!$R$95,I$7<=INPUTS!$S$95),"C",IF(AND(INPUTS!$E$95="Yes",I$17=1,I$7>INPUTS!$S$95),"✓","")))) | J28: =IF(AND(AND(INPUTS!$E$95="Yes",J$16=1,J$7>=INPUTS!$P$95,J$7<=INPUTS!$Q$95),AND(INPUTS!$E$95="Yes",J$16=1,J$7>=INPUTS!$R$95,J$7<=INPUTS!$S$95)),"S+C",IF(AND(INPUTS!$E$95="Yes",J$16=1,J$7>=INPUTS!$P$95,J$7<=INPUTS!$Q$95),"S",IF(AND(INPUTS!$E$95="Yes",J$16=1,J$7>=INPUTS!$R$95,J$7<=INPUTS!$S$95),"C",IF(AND(INPUTS!$E$95="Yes",J$17=1,J$7>INPUTS!$S$95),"✓","")))) | K28: =IF(AND(AND(INPUTS!$E$95="Yes",K$16=1,K$7>=INPUTS!$P$95,K$7<=INPUTS!$Q$95),AND(INPUTS!$E$95="Yes",K$16=1,K$7>=INPUTS!$R$95,K$7<=INPUTS!$S$95)),"S+C",IF(AND(INPUTS!$E$95="Yes",K$16=1,K$7>=INPUTS!$P$95,K$7<=INPUTS!$Q$95),"S",IF(AND(INPUTS!$E$95="Yes",K$16=1,K$7>=INPUTS!$R$95,K$7<=INPUTS!$S$95),"C",IF(AND(INPUTS!$E$95="Yes",K$17=1,K$7>INPUTS!$S$95),"✓","")))) | ... AQ28: =IF(AND(AND(INPUTS!$E$95="Yes",AQ$16=1,AQ$7>=INPUTS!$P$95,AQ$7<=INPUTS!$Q$95),AND(INPUTS!$E$95="Yes",AQ$16=1,AQ$7>=INPUTS!$R$95,AQ$7<=INPUTS!$S$95)),"S+C",IF(AND(INPUTS!$E$95="Yes",AQ$16=1,AQ$7>=INPUTS!$P$95,AQ$7<=INPUTS!$Q$95),"S",IF(AND(INPUTS!$E$95="Yes",AQ$16=1,AQ$7>=INPUTS!$R$95,AQ$7<=INPUTS!$S$95),"C",IF(AND(INPUTS!$E$95="Yes",AQ$17=1,AQ$7>INPUTS!$S$95),"✓",""))))
B29: =IF(INPUTS!$E$96="Yes",INPUTS!$B$96,"(product row 9 – off)") -> (product row 9 – off) | D29: =IF(AND(AND(INPUTS!$E$96="Yes",D$16=1,D$7>=INPUTS!$P$96,D$7<=INPUTS!$Q$96),AND(INPUTS!$E$96="Yes",D$16=1,D$7>=INPUTS!$R$96,D$7<=INPUTS!$S$96)),"S+C",IF(AND(INPUTS!$E$96="Yes",D$16=1,D$7>=INPUTS!$P$96,D$7<=INPUTS!$Q$96),"S",IF(AND(INPUTS!$E$96="Yes",D$16=1,D$7>=INPUTS!$R$96,D$7<=INPUTS!$S$96),"C",IF(AND(INPUTS!$E$96="Yes",D$17=1,D$7>INPUTS!$S$96),"✓","")))) | E29: =IF(AND(AND(INPUTS!$E$96="Yes",E$16=1,E$7>=INPUTS!$P$96,E$7<=INPUTS!$Q$96),AND(INPUTS!$E$96="Yes",E$16=1,E$7>=INPUTS!$R$96,E$7<=INPUTS!$S$96)),"S+C",IF(AND(INPUTS!$E$96="Yes",E$16=1,E$7>=INPUTS!$P$96,E$7<=INPUTS!$Q$96),"S",IF(AND(INPUTS!$E$96="Yes",E$16=1,E$7>=INPUTS!$R$96,E$7<=INPUTS!$S$96),"C",IF(AND(INPUTS!$E$96="Yes",E$17=1,E$7>INPUTS!$S$96),"✓","")))) | F29: =IF(AND(AND(INPUTS!$E$96="Yes",F$16=1,F$7>=INPUTS!$P$96,F$7<=INPUTS!$Q$96),AND(INPUTS!$E$96="Yes",F$16=1,F$7>=INPUTS!$R$96,F$7<=INPUTS!$S$96)),"S+C",IF(AND(INPUTS!$E$96="Yes",F$16=1,F$7>=INPUTS!$P$96,F$7<=INPUTS!$Q$96),"S",IF(AND(INPUTS!$E$96="Yes",F$16=1,F$7>=INPUTS!$R$96,F$7<=INPUTS!$S$96),"C",IF(AND(INPUTS!$E$96="Yes",F$17=1,F$7>INPUTS!$S$96),"✓","")))) | G29: =IF(AND(AND(INPUTS!$E$96="Yes",G$16=1,G$7>=INPUTS!$P$96,G$7<=INPUTS!$Q$96),AND(INPUTS!$E$96="Yes",G$16=1,G$7>=INPUTS!$R$96,G$7<=INPUTS!$S$96)),"S+C",IF(AND(INPUTS!$E$96="Yes",G$16=1,G$7>=INPUTS!$P$96,G$7<=INPUTS!$Q$96),"S",IF(AND(INPUTS!$E$96="Yes",G$16=1,G$7>=INPUTS!$R$96,G$7<=INPUTS!$S$96),"C",IF(AND(INPUTS!$E$96="Yes",G$17=1,G$7>INPUTS!$S$96),"✓","")))) | H29: =IF(AND(AND(INPUTS!$E$96="Yes",H$16=1,H$7>=INPUTS!$P$96,H$7<=INPUTS!$Q$96),AND(INPUTS!$E$96="Yes",H$16=1,H$7>=INPUTS!$R$96,H$7<=INPUTS!$S$96)),"S+C",IF(AND(INPUTS!$E$96="Yes",H$16=1,H$7>=INPUTS!$P$96,H$7<=INPUTS!$Q$96),"S",IF(AND(INPUTS!$E$96="Yes",H$16=1,H$7>=INPUTS!$R$96,H$7<=INPUTS!$S$96),"C",IF(AND(INPUTS!$E$96="Yes",H$17=1,H$7>INPUTS!$S$96),"✓","")))) | I29: =IF(AND(AND(INPUTS!$E$96="Yes",I$16=1,I$7>=INPUTS!$P$96,I$7<=INPUTS!$Q$96),AND(INPUTS!$E$96="Yes",I$16=1,I$7>=INPUTS!$R$96,I$7<=INPUTS!$S$96)),"S+C",IF(AND(INPUTS!$E$96="Yes",I$16=1,I$7>=INPUTS!$P$96,I$7<=INPUTS!$Q$96),"S",IF(AND(INPUTS!$E$96="Yes",I$16=1,I$7>=INPUTS!$R$96,I$7<=INPUTS!$S$96),"C",IF(AND(INPUTS!$E$96="Yes",I$17=1,I$7>INPUTS!$S$96),"✓","")))) | J29: =IF(AND(AND(INPUTS!$E$96="Yes",J$16=1,J$7>=INPUTS!$P$96,J$7<=INPUTS!$Q$96),AND(INPUTS!$E$96="Yes",J$16=1,J$7>=INPUTS!$R$96,J$7<=INPUTS!$S$96)),"S+C",IF(AND(INPUTS!$E$96="Yes",J$16=1,J$7>=INPUTS!$P$96,J$7<=INPUTS!$Q$96),"S",IF(AND(INPUTS!$E$96="Yes",J$16=1,J$7>=INPUTS!$R$96,J$7<=INPUTS!$S$96),"C",IF(AND(INPUTS!$E$96="Yes",J$17=1,J$7>INPUTS!$S$96),"✓","")))) | K29: =IF(AND(AND(INPUTS!$E$96="Yes",K$16=1,K$7>=INPUTS!$P$96,K$7<=INPUTS!$Q$96),AND(INPUTS!$E$96="Yes",K$16=1,K$7>=INPUTS!$R$96,K$7<=INPUTS!$S$96)),"S+C",IF(AND(INPUTS!$E$96="Yes",K$16=1,K$7>=INPUTS!$P$96,K$7<=INPUTS!$Q$96),"S",IF(AND(INPUTS!$E$96="Yes",K$16=1,K$7>=INPUTS!$R$96,K$7<=INPUTS!$S$96),"C",IF(AND(INPUTS!$E$96="Yes",K$17=1,K$7>INPUTS!$S$96),"✓","")))) | ... AQ29: =IF(AND(AND(INPUTS!$E$96="Yes",AQ$16=1,AQ$7>=INPUTS!$P$96,AQ$7<=INPUTS!$Q$96),AND(INPUTS!$E$96="Yes",AQ$16=1,AQ$7>=INPUTS!$R$96,AQ$7<=INPUTS!$S$96)),"S+C",IF(AND(INPUTS!$E$96="Yes",AQ$16=1,AQ$7>=INPUTS!$P$96,AQ$7<=INPUTS!$Q$96),"S",IF(AND(INPUTS!$E$96="Yes",AQ$16=1,AQ$7>=INPUTS!$R$96,AQ$7<=INPUTS!$S$96),"C",IF(AND(INPUTS!$E$96="Yes",AQ$17=1,AQ$7>INPUTS!$S$96),"✓",""))))
B30: =IF(INPUTS!$E$97="Yes",INPUTS!$B$97,"(product row 10 – off)") -> (product row 10 – off) | D30: =IF(AND(AND(INPUTS!$E$97="Yes",D$16=1,D$7>=INPUTS!$P$97,D$7<=INPUTS!$Q$97),AND(INPUTS!$E$97="Yes",D$16=1,D$7>=INPUTS!$R$97,D$7<=INPUTS!$S$97)),"S+C",IF(AND(INPUTS!$E$97="Yes",D$16=1,D$7>=INPUTS!$P$97,D$7<=INPUTS!$Q$97),"S",IF(AND(INPUTS!$E$97="Yes",D$16=1,D$7>=INPUTS!$R$97,D$7<=INPUTS!$S$97),"C",IF(AND(INPUTS!$E$97="Yes",D$17=1,D$7>INPUTS!$S$97),"✓","")))) | E30: =IF(AND(AND(INPUTS!$E$97="Yes",E$16=1,E$7>=INPUTS!$P$97,E$7<=INPUTS!$Q$97),AND(INPUTS!$E$97="Yes",E$16=1,E$7>=INPUTS!$R$97,E$7<=INPUTS!$S$97)),"S+C",IF(AND(INPUTS!$E$97="Yes",E$16=1,E$7>=INPUTS!$P$97,E$7<=INPUTS!$Q$97),"S",IF(AND(INPUTS!$E$97="Yes",E$16=1,E$7>=INPUTS!$R$97,E$7<=INPUTS!$S$97),"C",IF(AND(INPUTS!$E$97="Yes",E$17=1,E$7>INPUTS!$S$97),"✓","")))) | F30: =IF(AND(AND(INPUTS!$E$97="Yes",F$16=1,F$7>=INPUTS!$P$97,F$7<=INPUTS!$Q$97),AND(INPUTS!$E$97="Yes",F$16=1,F$7>=INPUTS!$R$97,F$7<=INPUTS!$S$97)),"S+C",IF(AND(INPUTS!$E$97="Yes",F$16=1,F$7>=INPUTS!$P$97,F$7<=INPUTS!$Q$97),"S",IF(AND(INPUTS!$E$97="Yes",F$16=1,F$7>=INPUTS!$R$97,F$7<=INPUTS!$S$97),"C",IF(AND(INPUTS!$E$97="Yes",F$17=1,F$7>INPUTS!$S$97),"✓","")))) | G30: =IF(AND(AND(INPUTS!$E$97="Yes",G$16=1,G$7>=INPUTS!$P$97,G$7<=INPUTS!$Q$97),AND(INPUTS!$E$97="Yes",G$16=1,G$7>=INPUTS!$R$97,G$7<=INPUTS!$S$97)),"S+C",IF(AND(INPUTS!$E$97="Yes",G$16=1,G$7>=INPUTS!$P$97,G$7<=INPUTS!$Q$97),"S",IF(AND(INPUTS!$E$97="Yes",G$16=1,G$7>=INPUTS!$R$97,G$7<=INPUTS!$S$97),"C",IF(AND(INPUTS!$E$97="Yes",G$17=1,G$7>INPUTS!$S$97),"✓","")))) | H30: =IF(AND(AND(INPUTS!$E$97="Yes",H$16=1,H$7>=INPUTS!$P$97,H$7<=INPUTS!$Q$97),AND(INPUTS!$E$97="Yes",H$16=1,H$7>=INPUTS!$R$97,H$7<=INPUTS!$S$97)),"S+C",IF(AND(INPUTS!$E$97="Yes",H$16=1,H$7>=INPUTS!$P$97,H$7<=INPUTS!$Q$97),"S",IF(AND(INPUTS!$E$97="Yes",H$16=1,H$7>=INPUTS!$R$97,H$7<=INPUTS!$S$97),"C",IF(AND(INPUTS!$E$97="Yes",H$17=1,H$7>INPUTS!$S$97),"✓","")))) | I30: =IF(AND(AND(INPUTS!$E$97="Yes",I$16=1,I$7>=INPUTS!$P$97,I$7<=INPUTS!$Q$97),AND(INPUTS!$E$97="Yes",I$16=1,I$7>=INPUTS!$R$97,I$7<=INPUTS!$S$97)),"S+C",IF(AND(INPUTS!$E$97="Yes",I$16=1,I$7>=INPUTS!$P$97,I$7<=INPUTS!$Q$97),"S",IF(AND(INPUTS!$E$97="Yes",I$16=1,I$7>=INPUTS!$R$97,I$7<=INPUTS!$S$97),"C",IF(AND(INPUTS!$E$97="Yes",I$17=1,I$7>INPUTS!$S$97),"✓","")))) | J30: =IF(AND(AND(INPUTS!$E$97="Yes",J$16=1,J$7>=INPUTS!$P$97,J$7<=INPUTS!$Q$97),AND(INPUTS!$E$97="Yes",J$16=1,J$7>=INPUTS!$R$97,J$7<=INPUTS!$S$97)),"S+C",IF(AND(INPUTS!$E$97="Yes",J$16=1,J$7>=INPUTS!$P$97,J$7<=INPUTS!$Q$97),"S",IF(AND(INPUTS!$E$97="Yes",J$16=1,J$7>=INPUTS!$R$97,J$7<=INPUTS!$S$97),"C",IF(AND(INPUTS!$E$97="Yes",J$17=1,J$7>INPUTS!$S$97),"✓","")))) | K30: =IF(AND(AND(INPUTS!$E$97="Yes",K$16=1,K$7>=INPUTS!$P$97,K$7<=INPUTS!$Q$97),AND(INPUTS!$E$97="Yes",K$16=1,K$7>=INPUTS!$R$97,K$7<=INPUTS!$S$97)),"S+C",IF(AND(INPUTS!$E$97="Yes",K$16=1,K$7>=INPUTS!$P$97,K$7<=INPUTS!$Q$97),"S",IF(AND(INPUTS!$E$97="Yes",K$16=1,K$7>=INPUTS!$R$97,K$7<=INPUTS!$S$97),"C",IF(AND(INPUTS!$E$97="Yes",K$17=1,K$7>INPUTS!$S$97),"✓","")))) | ... AQ30: =IF(AND(AND(INPUTS!$E$97="Yes",AQ$16=1,AQ$7>=INPUTS!$P$97,AQ$7<=INPUTS!$Q$97),AND(INPUTS!$E$97="Yes",AQ$16=1,AQ$7>=INPUTS!$R$97,AQ$7<=INPUTS!$S$97)),"S+C",IF(AND(INPUTS!$E$97="Yes",AQ$16=1,AQ$7>=INPUTS!$P$97,AQ$7<=INPUTS!$Q$97),"S",IF(AND(INPUTS!$E$97="Yes",AQ$16=1,AQ$7>=INPUTS!$R$97,AQ$7<=INPUTS!$S$97),"C",IF(AND(INPUTS!$E$97="Yes",AQ$17=1,AQ$7>INPUTS!$S$97),"✓",""))))
B32: C. PRODUCT TIMING FLAGS (1 = on; 'Q#' = position inside the window, used by the curve engine)
C33: Count / n
B34: =IF(INPUTS!$E$88="Yes",INPUTS!$B$88,"Product row 1 (off)") -> Villas
B35: Sales window (1 = selling) | C35: =SUM(D35:AQ35) -> 8 | D35: =IF(AND((INPUTS!$E$88="Yes"),D$16=1,D$7>=INPUTS!$P$88,D$7<=INPUTS!$Q$88),1,0) -> 0 | E35: =IF(AND((INPUTS!$E$88="Yes"),E$16=1,E$7>=INPUTS!$P$88,E$7<=INPUTS!$Q$88),1,0) -> 0 | F35: =IF(AND((INPUTS!$E$88="Yes"),F$16=1,F$7>=INPUTS!$P$88,F$7<=INPUTS!$Q$88),1,0) -> 1 | G35: =IF(AND((INPUTS!$E$88="Yes"),G$16=1,G$7>=INPUTS!$P$88,G$7<=INPUTS!$Q$88),1,0) -> 1 | H35: =IF(AND((INPUTS!$E$88="Yes"),H$16=1,H$7>=INPUTS!$P$88,H$7<=INPUTS!$Q$88),1,0) -> 1 | I35: =IF(AND((INPUTS!$E$88="Yes"),I$16=1,I$7>=INPUTS!$P$88,I$7<=INPUTS!$Q$88),1,0) -> 1 | J35: =IF(AND((INPUTS!$E$88="Yes"),J$16=1,J$7>=INPUTS!$P$88,J$7<=INPUTS!$Q$88),1,0) -> 1 | K35: =IF(AND((INPUTS!$E$88="Yes"),K$16=1,K$7>=INPUTS!$P$88,K$7<=INPUTS!$Q$88),1,0) -> 1 | ... AQ35: =IF(AND((INPUTS!$E$88="Yes"),AQ$16=1,AQ$7>=INPUTS!$P$88,AQ$7<=INPUTS!$Q$88),1,0) -> 0
B36: Sales quarter # in window | C36: =MAX(D36:AQ36) -> 8 | D36: =IF(D35=1,D$7-INPUTS!$P$88+1,0) -> 0 | E36: =IF(E35=1,E$7-INPUTS!$P$88+1,0) -> 0 | F36: =IF(F35=1,F$7-INPUTS!$P$88+1,0) -> 1 | G36: =IF(G35=1,G$7-INPUTS!$P$88+1,0) -> 2 | H36: =IF(H35=1,H$7-INPUTS!$P$88+1,0) -> 3 | I36: =IF(I35=1,I$7-INPUTS!$P$88+1,0) -> 4 | J36: =IF(J35=1,J$7-INPUTS!$P$88+1,0) -> 5 | K36: =IF(K35=1,K$7-INPUTS!$P$88+1,0) -> 6 | ... AQ36: =IF(AQ35=1,AQ$7-INPUTS!$P$88+1,0) -> 0
B37: Construction window (1 = building) | C37: =SUM(D37:AQ37) -> 12 | D37: =IF(AND((INPUTS!$E$88="Yes"),D$16=1,D$7>=INPUTS!$R$88,D$7<=INPUTS!$S$88),1,0) -> 0 | E37: =IF(AND((INPUTS!$E$88="Yes"),E$16=1,E$7>=INPUTS!$R$88,E$7<=INPUTS!$S$88),1,0) -> 0 | F37: =IF(AND((INPUTS!$E$88="Yes"),F$16=1,F$7>=INPUTS!$R$88,F$7<=INPUTS!$S$88),1,0) -> 0 | G37: =IF(AND((INPUTS!$E$88="Yes"),G$16=1,G$7>=INPUTS!$R$88,G$7<=INPUTS!$S$88),1,0) -> 1 | H37: =IF(AND((INPUTS!$E$88="Yes"),H$16=1,H$7>=INPUTS!$R$88,H$7<=INPUTS!$S$88),1,0) -> 1 | I37: =IF(AND((INPUTS!$E$88="Yes"),I$16=1,I$7>=INPUTS!$R$88,I$7<=INPUTS!$S$88),1,0) -> 1 | J37: =IF(AND((INPUTS!$E$88="Yes"),J$16=1,J$7>=INPUTS!$R$88,J$7<=INPUTS!$S$88),1,0) -> 1 | K37: =IF(AND((INPUTS!$E$88="Yes"),K$16=1,K$7>=INPUTS!$R$88,K$7<=INPUTS!$S$88),1,0) -> 1 | ... AQ37: =IF(AND((INPUTS!$E$88="Yes"),AQ$16=1,AQ$7>=INPUTS!$R$88,AQ$7<=INPUTS!$S$88),1,0) -> 0
B38: Construction quarter # in window | C38: =MAX(D38:AQ38) -> 12 | D38: =IF(D37=1,D$7-INPUTS!$R$88+1,0) -> 0 | E38: =IF(E37=1,E$7-INPUTS!$R$88+1,0) -> 0 | F38: =IF(F37=1,F$7-INPUTS!$R$88+1,0) -> 0 | G38: =IF(G37=1,G$7-INPUTS!$R$88+1,0) -> 1 | H38: =IF(H37=1,H$7-INPUTS!$R$88+1,0) -> 2 | I38: =IF(I37=1,I$7-INPUTS!$R$88+1,0) -> 3 | J38: =IF(J37=1,J$7-INPUTS!$R$88+1,0) -> 4 | K38: =IF(K37=1,K$7-INPUTS!$R$88+1,0) -> 5 | ... AQ38: =IF(AQ37=1,AQ$7-INPUTS!$R$88+1,0) -> 0
B39: Construction complete (1 = after end) | C39: =SUM(D39:AQ39) -> 25 | D39: =IF(AND((INPUTS!$E$88="Yes"),D$16=1,D$7>INPUTS!$S$88),1,0) -> 0 | E39: =IF(AND((INPUTS!$E$88="Yes"),E$16=1,E$7>INPUTS!$S$88),1,0) -> 0 | F39: =IF(AND((INPUTS!$E$88="Yes"),F$16=1,F$7>INPUTS!$S$88),1,0) -> 0 | G39: =IF(AND((INPUTS!$E$88="Yes"),G$16=1,G$7>INPUTS!$S$88),1,0) -> 0 | H39: =IF(AND((INPUTS!$E$88="Yes"),H$16=1,H$7>INPUTS!$S$88),1,0) -> 0 | I39: =IF(AND((INPUTS!$E$88="Yes"),I$16=1,I$7>INPUTS!$S$88),1,0) -> 0 | J39: =IF(AND((INPUTS!$E$88="Yes"),J$16=1,J$7>INPUTS!$S$88),1,0) -> 0 | K39: =IF(AND((INPUTS!$E$88="Yes"),K$16=1,K$7>INPUTS!$S$88),1,0) -> 0 | ... AQ39: =IF(AND((INPUTS!$E$88="Yes"),AQ$16=1,AQ$7>INPUTS!$S$88),1,0) -> 1
B40: Timing check | C40: =IF(INPUTS!$E$88<>"Yes","Off",IF(OR(NOT(ISNUMBER(INPUTS!$P$88)),NOT(ISNUMBER(INPUTS!$Q$88)),NOT(ISNUMBER(INPUTS!$R$88)),NOT(ISNUMBER(INPUTS!$S$88))),"ERROR",IF(AND(C35=INPUTS!$Q$88-INPUTS!$P$88+1,C37=INPUTS!$S$88-INPUTS!$R$88+1,C39=MAX(0,INPUTS!$C$24-INPUTS!$S$88)),"OK","ERROR"))) -> OK
B41: =IF(INPUTS!$E$89="Yes",INPUTS!$B$89,"Product row 2 (off)") -> Apartments – Towers A & B
B42: Sales window (1 = selling) | C42: =SUM(D42:AQ42) -> 12 | D42: =IF(AND((INPUTS!$E$89="Yes"),D$16=1,D$7>=INPUTS!$P$89,D$7<=INPUTS!$Q$89),1,0) -> 0 | E42: =IF(AND((INPUTS!$E$89="Yes"),E$16=1,E$7>=INPUTS!$P$89,E$7<=INPUTS!$Q$89),1,0) -> 0 | F42: =IF(AND((INPUTS!$E$89="Yes"),F$16=1,F$7>=INPUTS!$P$89,F$7<=INPUTS!$Q$89),1,0) -> 0 | G42: =IF(AND((INPUTS!$E$89="Yes"),G$16=1,G$7>=INPUTS!$P$89,G$7<=INPUTS!$Q$89),1,0) -> 1 | H42: =IF(AND((INPUTS!$E$89="Yes"),H$16=1,H$7>=INPUTS!$P$89,H$7<=INPUTS!$Q$89),1,0) -> 1 | I42: =IF(AND((INPUTS!$E$89="Yes"),I$16=1,I$7>=INPUTS!$P$89,I$7<=INPUTS!$Q$89),1,0) -> 1 | J42: =IF(AND((INPUTS!$E$89="Yes"),J$16=1,J$7>=INPUTS!$P$89,J$7<=INPUTS!$Q$89),1,0) -> 1 | K42: =IF(AND((INPUTS!$E$89="Yes"),K$16=1,K$7>=INPUTS!$P$89,K$7<=INPUTS!$Q$89),1,0) -> 1 | ... AQ42: =IF(AND((INPUTS!$E$89="Yes"),AQ$16=1,AQ$7>=INPUTS!$P$89,AQ$7<=INPUTS!$Q$89),1,0) -> 0
B43: Sales quarter # in window | C43: =MAX(D43:AQ43) -> 12 | D43: =IF(D42=1,D$7-INPUTS!$P$89+1,0) -> 0 | E43: =IF(E42=1,E$7-INPUTS!$P$89+1,0) -> 0 | F43: =IF(F42=1,F$7-INPUTS!$P$89+1,0) -> 0 | G43: =IF(G42=1,G$7-INPUTS!$P$89+1,0) -> 1 | H43: =IF(H42=1,H$7-INPUTS!$P$89+1,0) -> 2 | I43: =IF(I42=1,I$7-INPUTS!$P$89+1,0) -> 3 | J43: =IF(J42=1,J$7-INPUTS!$P$89+1,0) -> 4 | K43: =IF(K42=1,K$7-INPUTS!$P$89+1,0) -> 5 | ... AQ43: =IF(AQ42=1,AQ$7-INPUTS!$P$89+1,0) -> 0
B44: Construction window (1 = building) | C44: =SUM(D44:AQ44) -> 16 | D44: =IF(AND((INPUTS!$E$89="Yes"),D$16=1,D$7>=INPUTS!$R$89,D$7<=INPUTS!$S$89),1,0) -> 0 | E44: =IF(AND((INPUTS!$E$89="Yes"),E$16=1,E$7>=INPUTS!$R$89,E$7<=INPUTS!$S$89),1,0) -> 0 | F44: =IF(AND((INPUTS!$E$89="Yes"),F$16=1,F$7>=INPUTS!$R$89,F$7<=INPUTS!$S$89),1,0) -> 0 | G44: =IF(AND((INPUTS!$E$89="Yes"),G$16=1,G$7>=INPUTS!$R$89,G$7<=INPUTS!$S$89),1,0) -> 0 | H44: =IF(AND((INPUTS!$E$89="Yes"),H$16=1,H$7>=INPUTS!$R$89,H$7<=INPUTS!$S$89),1,0) -> 1 | I44: =IF(AND((INPUTS!$E$89="Yes"),I$16=1,I$7>=INPUTS!$R$89,I$7<=INPUTS!$S$89),1,0) -> 1 | J44: =IF(AND((INPUTS!$E$89="Yes"),J$16=1,J$7>=INPUTS!$R$89,J$7<=INPUTS!$S$89),1,0) -> 1 | K44: =IF(AND((INPUTS!$E$89="Yes"),K$16=1,K$7>=INPUTS!$R$89,K$7<=INPUTS!$S$89),1,0) -> 1 | ... AQ44: =IF(AND((INPUTS!$E$89="Yes"),AQ$16=1,AQ$7>=INPUTS!$R$89,AQ$7<=INPUTS!$S$89),1,0) -> 0
B45: Construction quarter # in window | C45: =MAX(D45:AQ45) -> 16 | D45: =IF(D44=1,D$7-INPUTS!$R$89+1,0) -> 0 | E45: =IF(E44=1,E$7-INPUTS!$R$89+1,0) -> 0 | F45: =IF(F44=1,F$7-INPUTS!$R$89+1,0) -> 0 | G45: =IF(G44=1,G$7-INPUTS!$R$89+1,0) -> 0 | H45: =IF(H44=1,H$7-INPUTS!$R$89+1,0) -> 1 | I45: =IF(I44=1,I$7-INPUTS!$R$89+1,0) -> 2 | J45: =IF(J44=1,J$7-INPUTS!$R$89+1,0) -> 3 | K45: =IF(K44=1,K$7-INPUTS!$R$89+1,0) -> 4 | ... AQ45: =IF(AQ44=1,AQ$7-INPUTS!$R$89+1,0) -> 0
B46: Construction complete (1 = after end) | C46: =SUM(D46:AQ46) -> 20 | D46: =IF(AND((INPUTS!$E$89="Yes"),D$16=1,D$7>INPUTS!$S$89),1,0) -> 0 | E46: =IF(AND((INPUTS!$E$89="Yes"),E$16=1,E$7>INPUTS!$S$89),1,0) -> 0 | F46: =IF(AND((INPUTS!$E$89="Yes"),F$16=1,F$7>INPUTS!$S$89),1,0) -> 0 | G46: =IF(AND((INPUTS!$E$89="Yes"),G$16=1,G$7>INPUTS!$S$89),1,0) -> 0 | H46: =IF(AND((INPUTS!$E$89="Yes"),H$16=1,H$7>INPUTS!$S$89),1,0) -> 0 | I46: =IF(AND((INPUTS!$E$89="Yes"),I$16=1,I$7>INPUTS!$S$89),1,0) -> 0 | J46: =IF(AND((INPUTS!$E$89="Yes"),J$16=1,J$7>INPUTS!$S$89),1,0) -> 0 | K46: =IF(AND((INPUTS!$E$89="Yes"),K$16=1,K$7>INPUTS!$S$89),1,0) -> 0 | ... AQ46: =IF(AND((INPUTS!$E$89="Yes"),AQ$16=1,AQ$7>INPUTS!$S$89),1,0) -> 1
B47: Timing check | C47: =IF(INPUTS!$E$89<>"Yes","Off",IF(OR(NOT(ISNUMBER(INPUTS!$P$89)),NOT(ISNUMBER(INPUTS!$Q$89)),NOT(ISNUMBER(INPUTS!$R$89)),NOT(ISNUMBER(INPUTS!$S$89))),"ERROR",IF(AND(C42=INPUTS!$Q$89-INPUTS!$P$89+1,C44=INPUTS!$S$89-INPUTS!$R$89+1,C46=MAX(0,INPUTS!$C$24-INPUTS!$S$89)),"OK","ERROR"))) -> OK
B48: =IF(INPUTS!$E$90="Yes",INPUTS!$B$90,"Product row 3 (off)") -> Studios
B49: Sales window (1 = selling) | C49: =SUM(D49:AQ49) -> 8 | D49: =IF(AND((INPUTS!$E$90="Yes"),D$16=1,D$7>=INPUTS!$P$90,D$7<=INPUTS!$Q$90),1,0) -> 0 | E49: =IF(AND((INPUTS!$E$90="Yes"),E$16=1,E$7>=INPUTS!$P$90,E$7<=INPUTS!$Q$90),1,0) -> 0 | F49: =IF(AND((INPUTS!$E$90="Yes"),F$16=1,F$7>=INPUTS!$P$90,F$7<=INPUTS!$Q$90),1,0) -> 0 | G49: =IF(AND((INPUTS!$E$90="Yes"),G$16=1,G$7>=INPUTS!$P$90,G$7<=INPUTS!$Q$90),1,0) -> 0 | H49: =IF(AND((INPUTS!$E$90="Yes"),H$16=1,H$7>=INPUTS!$P$90,H$7<=INPUTS!$Q$90),1,0) -> 0 | I49: =IF(AND((INPUTS!$E$90="Yes"),I$16=1,I$7>=INPUTS!$P$90,I$7<=INPUTS!$Q$90),1,0) -> 1 | J49: =IF(AND((INPUTS!$E$90="Yes"),J$16=1,J$7>=INPUTS!$P$90,J$7<=INPUTS!$Q$90),1,0) -> 1 | K49: =IF(AND((INPUTS!$E$90="Yes"),K$16=1,K$7>=INPUTS!$P$90,K$7<=INPUTS!$Q$90),1,0) -> 1 | ... AQ49: =IF(AND((INPUTS!$E$90="Yes"),AQ$16=1,AQ$7>=INPUTS!$P$90,AQ$7<=INPUTS!$Q$90),1,0) -> 0
B50: Sales quarter # in window | C50: =MAX(D50:AQ50) -> 8 | D50: =IF(D49=1,D$7-INPUTS!$P$90+1,0) -> 0 | E50: =IF(E49=1,E$7-INPUTS!$P$90+1,0) -> 0 | F50: =IF(F49=1,F$7-INPUTS!$P$90+1,0) -> 0 | G50: =IF(G49=1,G$7-INPUTS!$P$90+1,0) -> 0 | H50: =IF(H49=1,H$7-INPUTS!$P$90+1,0) -> 0 | I50: =IF(I49=1,I$7-INPUTS!$P$90+1,0) -> 1 | J50: =IF(J49=1,J$7-INPUTS!$P$90+1,0) -> 2 | K50: =IF(K49=1,K$7-INPUTS!$P$90+1,0) -> 3 | ... AQ50: =IF(AQ49=1,AQ$7-INPUTS!$P$90+1,0) -> 0
B51: Construction window (1 = building) | C51: =SUM(D51:AQ51) -> 12 | D51: =IF(AND((INPUTS!$E$90="Yes"),D$16=1,D$7>=INPUTS!$R$90,D$7<=INPUTS!$S$90),1,0) -> 0 | E51: =IF(AND((INPUTS!$E$90="Yes"),E$16=1,E$7>=INPUTS!$R$90,E$7<=INPUTS!$S$90),1,0) -> 0 | F51: =IF(AND((INPUTS!$E$90="Yes"),F$16=1,F$7>=INPUTS!$R$90,F$7<=INPUTS!$S$90),1,0) -> 0 | G51: =IF(AND((INPUTS!$E$90="Yes"),G$16=1,G$7>=INPUTS!$R$90,G$7<=INPUTS!$S$90),1,0) -> 0 | H51: =IF(AND((INPUTS!$E$90="Yes"),H$16=1,H$7>=INPUTS!$R$90,H$7<=INPUTS!$S$90),1,0) -> 0 | I51: =IF(AND((INPUTS!$E$90="Yes"),I$16=1,I$7>=INPUTS!$R$90,I$7<=INPUTS!$S$90),1,0) -> 1 | J51: =IF(AND((INPUTS!$E$90="Yes"),J$16=1,J$7>=INPUTS!$R$90,J$7<=INPUTS!$S$90),1,0) -> 1 | K51: =IF(AND((INPUTS!$E$90="Yes"),K$16=1,K$7>=INPUTS!$R$90,K$7<=INPUTS!$S$90),1,0) -> 1 | ... AQ51: =IF(AND((INPUTS!$E$90="Yes"),AQ$16=1,AQ$7>=INPUTS!$R$90,AQ$7<=INPUTS!$S$90),1,0) -> 0
B52: Construction quarter # in window | C52: =MAX(D52:AQ52) -> 12 | D52: =IF(D51=1,D$7-INPUTS!$R$90+1,0) -> 0 | E52: =IF(E51=1,E$7-INPUTS!$R$90+1,0) -> 0 | F52: =IF(F51=1,F$7-INPUTS!$R$90+1,0) -> 0 | G52: =IF(G51=1,G$7-INPUTS!$R$90+1,0) -> 0 | H52: =IF(H51=1,H$7-INPUTS!$R$90+1,0) -> 0 | I52: =IF(I51=1,I$7-INPUTS!$R$90+1,0) -> 1 | J52: =IF(J51=1,J$7-INPUTS!$R$90+1,0) -> 2 | K52: =IF(K51=1,K$7-INPUTS!$R$90+1,0) -> 3 | ... AQ52: =IF(AQ51=1,AQ$7-INPUTS!$R$90+1,0) -> 0
B53: Construction complete (1 = after end) | C53: =SUM(D53:AQ53) -> 23 | D53: =IF(AND((INPUTS!$E$90="Yes"),D$16=1,D$7>INPUTS!$S$90),1,0) -> 0 | E53: =IF(AND((INPUTS!$E$90="Yes"),E$16=1,E$7>INPUTS!$S$90),1,0) -> 0 | F53: =IF(AND((INPUTS!$E$90="Yes"),F$16=1,F$7>INPUTS!$S$90),1,0) -> 0 | G53: =IF(AND((INPUTS!$E$90="Yes"),G$16=1,G$7>INPUTS!$S$90),1,0) -> 0 | H53: =IF(AND((INPUTS!$E$90="Yes"),H$16=1,H$7>INPUTS!$S$90),1,0) -> 0 | I53: =IF(AND((INPUTS!$E$90="Yes"),I$16=1,I$7>INPUTS!$S$90),1,0) -> 0 | J53: =IF(AND((INPUTS!$E$90="Yes"),J$16=1,J$7>INPUTS!$S$90),1,0) -> 0 | K53: =IF(AND((INPUTS!$E$90="Yes"),K$16=1,K$7>INPUTS!$S$90),1,0) -> 0 | ... AQ53: =IF(AND((INPUTS!$E$90="Yes"),AQ$16=1,AQ$7>INPUTS!$S$90),1,0) -> 1
B54: Timing check | C54: =IF(INPUTS!$E$90<>"Yes","Off",IF(OR(NOT(ISNUMBER(INPUTS!$P$90)),NOT(ISNUMBER(INPUTS!$Q$90)),NOT(ISNUMBER(INPUTS!$R$90)),NOT(ISNUMBER(INPUTS!$S$90))),"ERROR",IF(AND(C49=INPUTS!$Q$90-INPUTS!$P$90+1,C51=INPUTS!$S$90-INPUTS!$R$90+1,C53=MAX(0,INPUTS!$C$24-INPUTS!$S$90)),"OK","ERROR"))) -> OK
B55: =IF(INPUTS!$E$91="Yes",INPUTS!$B$91,"Product row 4 (off)") -> High-street retail
B56: Sales window (1 = selling) | C56: =SUM(D56:AQ56) -> 8 | D56: =IF(AND((INPUTS!$E$91="Yes"),D$16=1,D$7>=INPUTS!$P$91,D$7<=INPUTS!$Q$91),1,0) -> 0 | E56: =IF(AND((INPUTS!$E$91="Yes"),E$16=1,E$7>=INPUTS!$P$91,E$7<=INPUTS!$Q$91),1,0) -> 0 | F56: =IF(AND((INPUTS!$E$91="Yes"),F$16=1,F$7>=INPUTS!$P$91,F$7<=INPUTS!$Q$91),1,0) -> 0 | G56: =IF(AND((INPUTS!$E$91="Yes"),G$16=1,G$7>=INPUTS!$P$91,G$7<=INPUTS!$Q$91),1,0) -> 0 | H56: =IF(AND((INPUTS!$E$91="Yes"),H$16=1,H$7>=INPUTS!$P$91,H$7<=INPUTS!$Q$91),1,0) -> 0 | I56: =IF(AND((INPUTS!$E$91="Yes"),I$16=1,I$7>=INPUTS!$P$91,I$7<=INPUTS!$Q$91),1,0) -> 0 | J56: =IF(AND((INPUTS!$E$91="Yes"),J$16=1,J$7>=INPUTS!$P$91,J$7<=INPUTS!$Q$91),1,0) -> 0 | K56: =IF(AND((INPUTS!$E$91="Yes"),K$16=1,K$7>=INPUTS!$P$91,K$7<=INPUTS!$Q$91),1,0) -> 1 | ... AQ56: =IF(AND((INPUTS!$E$91="Yes"),AQ$16=1,AQ$7>=INPUTS!$P$91,AQ$7<=INPUTS!$Q$91),1,0) -> 0
B57: Sales quarter # in window | C57: =MAX(D57:AQ57) -> 8 | D57: =IF(D56=1,D$7-INPUTS!$P$91+1,0) -> 0 | E57: =IF(E56=1,E$7-INPUTS!$P$91+1,0) -> 0 | F57: =IF(F56=1,F$7-INPUTS!$P$91+1,0) -> 0 | G57: =IF(G56=1,G$7-INPUTS!$P$91+1,0) -> 0 | H57: =IF(H56=1,H$7-INPUTS!$P$91+1,0) -> 0 | I57: =IF(I56=1,I$7-INPUTS!$P$91+1,0) -> 0 | J57: =IF(J56=1,J$7-INPUTS!$P$91+1,0) -> 0 | K57: =IF(K56=1,K$7-INPUTS!$P$91+1,0) -> 1 | ... AQ57: =IF(AQ56=1,AQ$7-INPUTS!$P$91+1,0) -> 0
B58: Construction window (1 = building) | C58: =SUM(D58:AQ58) -> 12 | D58: =IF(AND((INPUTS!$E$91="Yes"),D$16=1,D$7>=INPUTS!$R$91,D$7<=INPUTS!$S$91),1,0) -> 0 | E58: =IF(AND((INPUTS!$E$91="Yes"),E$16=1,E$7>=INPUTS!$R$91,E$7<=INPUTS!$S$91),1,0) -> 0 | F58: =IF(AND((INPUTS!$E$91="Yes"),F$16=1,F$7>=INPUTS!$R$91,F$7<=INPUTS!$S$91),1,0) -> 0 | G58: =IF(AND((INPUTS!$E$91="Yes"),G$16=1,G$7>=INPUTS!$R$91,G$7<=INPUTS!$S$91),1,0) -> 0 | H58: =IF(AND((INPUTS!$E$91="Yes"),H$16=1,H$7>=INPUTS!$R$91,H$7<=INPUTS!$S$91),1,0) -> 0 | I58: =IF(AND((INPUTS!$E$91="Yes"),I$16=1,I$7>=INPUTS!$R$91,I$7<=INPUTS!$S$91),1,0) -> 1 | J58: =IF(AND((INPUTS!$E$91="Yes"),J$16=1,J$7>=INPUTS!$R$91,J$7<=INPUTS!$S$91),1,0) -> 1 | K58: =IF(AND((INPUTS!$E$91="Yes"),K$16=1,K$7>=INPUTS!$R$91,K$7<=INPUTS!$S$91),1,0) -> 1 | ... AQ58: =IF(AND((INPUTS!$E$91="Yes"),AQ$16=1,AQ$7>=INPUTS!$R$91,AQ$7<=INPUTS!$S$91),1,0) -> 0
B59: Construction quarter # in window | C59: =MAX(D59:AQ59) -> 12 | D59: =IF(D58=1,D$7-INPUTS!$R$91+1,0) -> 0 | E59: =IF(E58=1,E$7-INPUTS!$R$91+1,0) -> 0 | F59: =IF(F58=1,F$7-INPUTS!$R$91+1,0) -> 0 | G59: =IF(G58=1,G$7-INPUTS!$R$91+1,0) -> 0 | H59: =IF(H58=1,H$7-INPUTS!$R$91+1,0) -> 0 | I59: =IF(I58=1,I$7-INPUTS!$R$91+1,0) -> 1 | J59: =IF(J58=1,J$7-INPUTS!$R$91+1,0) -> 2 | K59: =IF(K58=1,K$7-INPUTS!$R$91+1,0) -> 3 | ... AQ59: =IF(AQ58=1,AQ$7-INPUTS!$R$91+1,0) -> 0
B60: Construction complete (1 = after end) | C60: =SUM(D60:AQ60) -> 23 | D60: =IF(AND((INPUTS!$E$91="Yes"),D$16=1,D$7>INPUTS!$S$91),1,0) -> 0 | E60: =IF(AND((INPUTS!$E$91="Yes"),E$16=1,E$7>INPUTS!$S$91),1,0) -> 0 | F60: =IF(AND((INPUTS!$E$91="Yes"),F$16=1,F$7>INPUTS!$S$91),1,0) -> 0 | G60: =IF(AND((INPUTS!$E$91="Yes"),G$16=1,G$7>INPUTS!$S$91),1,0) -> 0 | H60: =IF(AND((INPUTS!$E$91="Yes"),H$16=1,H$7>INPUTS!$S$91),1,0) -> 0 | I60: =IF(AND((INPUTS!$E$91="Yes"),I$16=1,I$7>INPUTS!$S$91),1,0) -> 0 | J60: =IF(AND((INPUTS!$E$91="Yes"),J$16=1,J$7>INPUTS!$S$91),1,0) -> 0 | K60: =IF(AND((INPUTS!$E$91="Yes"),K$16=1,K$7>INPUTS!$S$91),1,0) -> 0 | ... AQ60: =IF(AND((INPUTS!$E$91="Yes"),AQ$16=1,AQ$7>INPUTS!$S$91),1,0) -> 1
B61: Timing check | C61: =IF(INPUTS!$E$91<>"Yes","Off",IF(OR(NOT(ISNUMBER(INPUTS!$P$91)),NOT(ISNUMBER(INPUTS!$Q$91)),NOT(ISNUMBER(INPUTS!$R$91)),NOT(ISNUMBER(INPUTS!$S$91))),"ERROR",IF(AND(C56=INPUTS!$Q$91-INPUTS!$P$91+1,C58=INPUTS!$S$91-INPUTS!$R$91+1,C60=MAX(0,INPUTS!$C$24-INPUTS!$S$91)),"OK","ERROR"))) -> OK
B62: =IF(INPUTS!$E$92="Yes",INPUTS!$B$92,"Product row 5 (off)") -> Product row 5 (off)
B63: Sales window (1 = selling) | C63: =SUM(D63:AQ63) -> 0 | D63: =IF(AND((INPUTS!$E$92="Yes"),D$16=1,D$7>=INPUTS!$P$92,D$7<=INPUTS!$Q$92),1,0) -> 0 | E63: =IF(AND((INPUTS!$E$92="Yes"),E$16=1,E$7>=INPUTS!$P$92,E$7<=INPUTS!$Q$92),1,0) -> 0 | F63: =IF(AND((INPUTS!$E$92="Yes"),F$16=1,F$7>=INPUTS!$P$92,F$7<=INPUTS!$Q$92),1,0) -> 0 | G63: =IF(AND((INPUTS!$E$92="Yes"),G$16=1,G$7>=INPUTS!$P$92,G$7<=INPUTS!$Q$92),1,0) -> 0 | H63: =IF(AND((INPUTS!$E$92="Yes"),H$16=1,H$7>=INPUTS!$P$92,H$7<=INPUTS!$Q$92),1,0) -> 0 | I63: =IF(AND((INPUTS!$E$92="Yes"),I$16=1,I$7>=INPUTS!$P$92,I$7<=INPUTS!$Q$92),1,0) -> 0 | J63: =IF(AND((INPUTS!$E$92="Yes"),J$16=1,J$7>=INPUTS!$P$92,J$7<=INPUTS!$Q$92),1,0) -> 0 | K63: =IF(AND((INPUTS!$E$92="Yes"),K$16=1,K$7>=INPUTS!$P$92,K$7<=INPUTS!$Q$92),1,0) -> 0 | ... AQ63: =IF(AND((INPUTS!$E$92="Yes"),AQ$16=1,AQ$7>=INPUTS!$P$92,AQ$7<=INPUTS!$Q$92),1,0) -> 0
B64: Sales quarter # in window | C64: =MAX(D64:AQ64) -> 0 | D64: =IF(D63=1,D$7-INPUTS!$P$92+1,0) -> 0 | E64: =IF(E63=1,E$7-INPUTS!$P$92+1,0) -> 0 | F64: =IF(F63=1,F$7-INPUTS!$P$92+1,0) -> 0 | G64: =IF(G63=1,G$7-INPUTS!$P$92+1,0) -> 0 | H64: =IF(H63=1,H$7-INPUTS!$P$92+1,0) -> 0 | I64: =IF(I63=1,I$7-INPUTS!$P$92+1,0) -> 0 | J64: =IF(J63=1,J$7-INPUTS!$P$92+1,0) -> 0 | K64: =IF(K63=1,K$7-INPUTS!$P$92+1,0) -> 0 | ... AQ64: =IF(AQ63=1,AQ$7-INPUTS!$P$92+1,0) -> 0
B65: Construction window (1 = building) | C65: =SUM(D65:AQ65) -> 0 | D65: =IF(AND((INPUTS!$E$92="Yes"),D$16=1,D$7>=INPUTS!$R$92,D$7<=INPUTS!$S$92),1,0) -> 0 | E65: =IF(AND((INPUTS!$E$92="Yes"),E$16=1,E$7>=INPUTS!$R$92,E$7<=INPUTS!$S$92),1,0) -> 0 | F65: =IF(AND((INPUTS!$E$92="Yes"),F$16=1,F$7>=INPUTS!$R$92,F$7<=INPUTS!$S$92),1,0) -> 0 | G65: =IF(AND((INPUTS!$E$92="Yes"),G$16=1,G$7>=INPUTS!$R$92,G$7<=INPUTS!$S$92),1,0) -> 0 | H65: =IF(AND((INPUTS!$E$92="Yes"),H$16=1,H$7>=INPUTS!$R$92,H$7<=INPUTS!$S$92),1,0) -> 0 | I65: =IF(AND((INPUTS!$E$92="Yes"),I$16=1,I$7>=INPUTS!$R$92,I$7<=INPUTS!$S$92),1,0) -> 0 | J65: =IF(AND((INPUTS!$E$92="Yes"),J$16=1,J$7>=INPUTS!$R$92,J$7<=INPUTS!$S$92),1,0) -> 0 | K65: =IF(AND((INPUTS!$E$92="Yes"),K$16=1,K$7>=INPUTS!$R$92,K$7<=INPUTS!$S$92),1,0) -> 0 | ... AQ65: =IF(AND((INPUTS!$E$92="Yes"),AQ$16=1,AQ$7>=INPUTS!$R$92,AQ$7<=INPUTS!$S$92),1,0) -> 0
B66: Construction quarter # in window | C66: =MAX(D66:AQ66) -> 0 | D66: =IF(D65=1,D$7-INPUTS!$R$92+1,0) -> 0 | E66: =IF(E65=1,E$7-INPUTS!$R$92+1,0) -> 0 | F66: =IF(F65=1,F$7-INPUTS!$R$92+1,0) -> 0 | G66: =IF(G65=1,G$7-INPUTS!$R$92+1,0) -> 0 | H66: =IF(H65=1,H$7-INPUTS!$R$92+1,0) -> 0 | I66: =IF(I65=1,I$7-INPUTS!$R$92+1,0) -> 0 | J66: =IF(J65=1,J$7-INPUTS!$R$92+1,0) -> 0 | K66: =IF(K65=1,K$7-INPUTS!$R$92+1,0) -> 0 | ... AQ66: =IF(AQ65=1,AQ$7-INPUTS!$R$92+1,0) -> 0
B67: Construction complete (1 = after end) | C67: =SUM(D67:AQ67) -> 0 | D67: =IF(AND((INPUTS!$E$92="Yes"),D$16=1,D$7>INPUTS!$S$92),1,0) -> 0 | E67: =IF(AND((INPUTS!$E$92="Yes"),E$16=1,E$7>INPUTS!$S$92),1,0) -> 0 | F67: =IF(AND((INPUTS!$E$92="Yes"),F$16=1,F$7>INPUTS!$S$92),1,0) -> 0 | G67: =IF(AND((INPUTS!$E$92="Yes"),G$16=1,G$7>INPUTS!$S$92),1,0) -> 0 | H67: =IF(AND((INPUTS!$E$92="Yes"),H$16=1,H$7>INPUTS!$S$92),1,0) -> 0 | I67: =IF(AND((INPUTS!$E$92="Yes"),I$16=1,I$7>INPUTS!$S$92),1,0) -> 0 | J67: =IF(AND((INPUTS!$E$92="Yes"),J$16=1,J$7>INPUTS!$S$92),1,0) -> 0 | K67: =IF(AND((INPUTS!$E$92="Yes"),K$16=1,K$7>INPUTS!$S$92),1,0) -> 0 | ... AQ67: =IF(AND((INPUTS!$E$92="Yes"),AQ$16=1,AQ$7>INPUTS!$S$92),1,0) -> 0
B68: Timing check | C68: =IF(INPUTS!$E$92<>"Yes","Off",IF(OR(NOT(ISNUMBER(INPUTS!$P$92)),NOT(ISNUMBER(INPUTS!$Q$92)),NOT(ISNUMBER(INPUTS!$R$92)),NOT(ISNUMBER(INPUTS!$S$92))),"ERROR",IF(AND(C63=INPUTS!$Q$92-INPUTS!$P$92+1,C65=INPUTS!$S$92-INPUTS!$R$92+1,C67=MAX(0,INPUTS!$C$24-INPUTS!$S$92)),"OK","ERROR"))) -> Off
B69: =IF(INPUTS!$E$93="Yes",INPUTS!$B$93,"Product row 6 (off)") -> Product row 6 (off)
B70: Sales window (1 = selling) | C70: =SUM(D70:AQ70) -> 0 | D70: =IF(AND((INPUTS!$E$93="Yes"),D$16=1,D$7>=INPUTS!$P$93,D$7<=INPUTS!$Q$93),1,0) -> 0 | E70: =IF(AND((INPUTS!$E$93="Yes"),E$16=1,E$7>=INPUTS!$P$93,E$7<=INPUTS!$Q$93),1,0) -> 0 | F70: =IF(AND((INPUTS!$E$93="Yes"),F$16=1,F$7>=INPUTS!$P$93,F$7<=INPUTS!$Q$93),1,0) -> 0 | G70: =IF(AND((INPUTS!$E$93="Yes"),G$16=1,G$7>=INPUTS!$P$93,G$7<=INPUTS!$Q$93),1,0) -> 0 | H70: =IF(AND((INPUTS!$E$93="Yes"),H$16=1,H$7>=INPUTS!$P$93,H$7<=INPUTS!$Q$93),1,0) -> 0 | I70: =IF(AND((INPUTS!$E$93="Yes"),I$16=1,I$7>=INPUTS!$P$93,I$7<=INPUTS!$Q$93),1,0) -> 0 | J70: =IF(AND((INPUTS!$E$93="Yes"),J$16=1,J$7>=INPUTS!$P$93,J$7<=INPUTS!$Q$93),1,0) -> 0 | K70: =IF(AND((INPUTS!$E$93="Yes"),K$16=1,K$7>=INPUTS!$P$93,K$7<=INPUTS!$Q$93),1,0) -> 0 | ... AQ70: =IF(AND((INPUTS!$E$93="Yes"),AQ$16=1,AQ$7>=INPUTS!$P$93,AQ$7<=INPUTS!$Q$93),1,0) -> 0
B71: Sales quarter # in window | C71: =MAX(D71:AQ71) -> 0 | D71: =IF(D70=1,D$7-INPUTS!$P$93+1,0) -> 0 | E71: =IF(E70=1,E$7-INPUTS!$P$93+1,0) -> 0 | F71: =IF(F70=1,F$7-INPUTS!$P$93+1,0) -> 0 | G71: =IF(G70=1,G$7-INPUTS!$P$93+1,0) -> 0 | H71: =IF(H70=1,H$7-INPUTS!$P$93+1,0) -> 0 | I71: =IF(I70=1,I$7-INPUTS!$P$93+1,0) -> 0 | J71: =IF(J70=1,J$7-INPUTS!$P$93+1,0) -> 0 | K71: =IF(K70=1,K$7-INPUTS!$P$93+1,0) -> 0 | ... AQ71: =IF(AQ70=1,AQ$7-INPUTS!$P$93+1,0) -> 0
B72: Construction window (1 = building) | C72: =SUM(D72:AQ72) -> 0 | D72: =IF(AND((INPUTS!$E$93="Yes"),D$16=1,D$7>=INPUTS!$R$93,D$7<=INPUTS!$S$93),1,0) -> 0 | E72: =IF(AND((INPUTS!$E$93="Yes"),E$16=1,E$7>=INPUTS!$R$93,E$7<=INPUTS!$S$93),1,0) -> 0 | F72: =IF(AND((INPUTS!$E$93="Yes"),F$16=1,F$7>=INPUTS!$R$93,F$7<=INPUTS!$S$93),1,0) -> 0 | G72: =IF(AND((INPUTS!$E$93="Yes"),G$16=1,G$7>=INPUTS!$R$93,G$7<=INPUTS!$S$93),1,0) -> 0 | H72: =IF(AND((INPUTS!$E$93="Yes"),H$16=1,H$7>=INPUTS!$R$93,H$7<=INPUTS!$S$93),1,0) -> 0 | I72: =IF(AND((INPUTS!$E$93="Yes"),I$16=1,I$7>=INPUTS!$R$93,I$7<=INPUTS!$S$93),1,0) -> 0 | J72: =IF(AND((INPUTS!$E$93="Yes"),J$16=1,J$7>=INPUTS!$R$93,J$7<=INPUTS!$S$93),1,0) -> 0 | K72: =IF(AND((INPUTS!$E$93="Yes"),K$16=1,K$7>=INPUTS!$R$93,K$7<=INPUTS!$S$93),1,0) -> 0 | ... AQ72: =IF(AND((INPUTS!$E$93="Yes"),AQ$16=1,AQ$7>=INPUTS!$R$93,AQ$7<=INPUTS!$S$93),1,0) -> 0
B73: Construction quarter # in window | C73: =MAX(D73:AQ73) -> 0 | D73: =IF(D72=1,D$7-INPUTS!$R$93+1,0) -> 0 | E73: =IF(E72=1,E$7-INPUTS!$R$93+1,0) -> 0 | F73: =IF(F72=1,F$7-INPUTS!$R$93+1,0) -> 0 | G73: =IF(G72=1,G$7-INPUTS!$R$93+1,0) -> 0 | H73: =IF(H72=1,H$7-INPUTS!$R$93+1,0) -> 0 | I73: =IF(I72=1,I$7-INPUTS!$R$93+1,0) -> 0 | J73: =IF(J72=1,J$7-INPUTS!$R$93+1,0) -> 0 | K73: =IF(K72=1,K$7-INPUTS!$R$93+1,0) -> 0 | ... AQ73: =IF(AQ72=1,AQ$7-INPUTS!$R$93+1,0) -> 0
B74: Construction complete (1 = after end) | C74: =SUM(D74:AQ74) -> 0 | D74: =IF(AND((INPUTS!$E$93="Yes"),D$16=1,D$7>INPUTS!$S$93),1,0) -> 0 | E74: =IF(AND((INPUTS!$E$93="Yes"),E$16=1,E$7>INPUTS!$S$93),1,0) -> 0 | F74: =IF(AND((INPUTS!$E$93="Yes"),F$16=1,F$7>INPUTS!$S$93),1,0) -> 0 | G74: =IF(AND((INPUTS!$E$93="Yes"),G$16=1,G$7>INPUTS!$S$93),1,0) -> 0 | H74: =IF(AND((INPUTS!$E$93="Yes"),H$16=1,H$7>INPUTS!$S$93),1,0) -> 0 | I74: =IF(AND((INPUTS!$E$93="Yes"),I$16=1,I$7>INPUTS!$S$93),1,0) -> 0 | J74: =IF(AND((INPUTS!$E$93="Yes"),J$16=1,J$7>INPUTS!$S$93),1,0) -> 0 | K74: =IF(AND((INPUTS!$E$93="Yes"),K$16=1,K$7>INPUTS!$S$93),1,0) -> 0 | ... AQ74: =IF(AND((INPUTS!$E$93="Yes"),AQ$16=1,AQ$7>INPUTS!$S$93),1,0) -> 0
B75: Timing check | C75: =IF(INPUTS!$E$93<>"Yes","Off",IF(OR(NOT(ISNUMBER(INPUTS!$P$93)),NOT(ISNUMBER(INPUTS!$Q$93)),NOT(ISNUMBER(INPUTS!$R$93)),NOT(ISNUMBER(INPUTS!$S$93))),"ERROR",IF(AND(C70=INPUTS!$Q$93-INPUTS!$P$93+1,C72=INPUTS!$S$93-INPUTS!$R$93+1,C74=MAX(0,INPUTS!$C$24-INPUTS!$S$93)),"OK","ERROR"))) -> Off
B76: =IF(INPUTS!$E$94="Yes",INPUTS!$B$94,"Product row 7 (off)") -> Product row 7 (off)
B77: Sales window (1 = selling) | C77: =SUM(D77:AQ77) -> 0 | D77: =IF(AND((INPUTS!$E$94="Yes"),D$16=1,D$7>=INPUTS!$P$94,D$7<=INPUTS!$Q$94),1,0) -> 0 | E77: =IF(AND((INPUTS!$E$94="Yes"),E$16=1,E$7>=INPUTS!$P$94,E$7<=INPUTS!$Q$94),1,0) -> 0 | F77: =IF(AND((INPUTS!$E$94="Yes"),F$16=1,F$7>=INPUTS!$P$94,F$7<=INPUTS!$Q$94),1,0) -> 0 | G77: =IF(AND((INPUTS!$E$94="Yes"),G$16=1,G$7>=INPUTS!$P$94,G$7<=INPUTS!$Q$94),1,0) -> 0 | H77: =IF(AND((INPUTS!$E$94="Yes"),H$16=1,H$7>=INPUTS!$P$94,H$7<=INPUTS!$Q$94),1,0) -> 0 | I77: =IF(AND((INPUTS!$E$94="Yes"),I$16=1,I$7>=INPUTS!$P$94,I$7<=INPUTS!$Q$94),1,0) -> 0 | J77: =IF(AND((INPUTS!$E$94="Yes"),J$16=1,J$7>=INPUTS!$P$94,J$7<=INPUTS!$Q$94),1,0) -> 0 | K77: =IF(AND((INPUTS!$E$94="Yes"),K$16=1,K$7>=INPUTS!$P$94,K$7<=INPUTS!$Q$94),1,0) -> 0 | ... AQ77: =IF(AND((INPUTS!$E$94="Yes"),AQ$16=1,AQ$7>=INPUTS!$P$94,AQ$7<=INPUTS!$Q$94),1,0) -> 0
B78: Sales quarter # in window | C78: =MAX(D78:AQ78) -> 0 | D78: =IF(D77=1,D$7-INPUTS!$P$94+1,0) -> 0 | E78: =IF(E77=1,E$7-INPUTS!$P$94+1,0) -> 0 | F78: =IF(F77=1,F$7-INPUTS!$P$94+1,0) -> 0 | G78: =IF(G77=1,G$7-INPUTS!$P$94+1,0) -> 0 | H78: =IF(H77=1,H$7-INPUTS!$P$94+1,0) -> 0 | I78: =IF(I77=1,I$7-INPUTS!$P$94+1,0) -> 0 | J78: =IF(J77=1,J$7-INPUTS!$P$94+1,0) -> 0 | K78: =IF(K77=1,K$7-INPUTS!$P$94+1,0) -> 0 | ... AQ78: =IF(AQ77=1,AQ$7-INPUTS!$P$94+1,0) -> 0
B79: Construction window (1 = building) | C79: =SUM(D79:AQ79) -> 0 | D79: =IF(AND((INPUTS!$E$94="Yes"),D$16=1,D$7>=INPUTS!$R$94,D$7<=INPUTS!$S$94),1,0) -> 0 | E79: =IF(AND((INPUTS!$E$94="Yes"),E$16=1,E$7>=INPUTS!$R$94,E$7<=INPUTS!$S$94),1,0) -> 0 | F79: =IF(AND((INPUTS!$E$94="Yes"),F$16=1,F$7>=INPUTS!$R$94,F$7<=INPUTS!$S$94),1,0) -> 0 | G79: =IF(AND((INPUTS!$E$94="Yes"),G$16=1,G$7>=INPUTS!$R$94,G$7<=INPUTS!$S$94),1,0) -> 0 | H79: =IF(AND((INPUTS!$E$94="Yes"),H$16=1,H$7>=INPUTS!$R$94,H$7<=INPUTS!$S$94),1,0) -> 0 | I79: =IF(AND((INPUTS!$E$94="Yes"),I$16=1,I$7>=INPUTS!$R$94,I$7<=INPUTS!$S$94),1,0) -> 0 | J79: =IF(AND((INPUTS!$E$94="Yes"),J$16=1,J$7>=INPUTS!$R$94,J$7<=INPUTS!$S$94),1,0) -> 0 | K79: =IF(AND((INPUTS!$E$94="Yes"),K$16=1,K$7>=INPUTS!$R$94,K$7<=INPUTS!$S$94),1,0) -> 0 | ... AQ79: =IF(AND((INPUTS!$E$94="Yes"),AQ$16=1,AQ$7>=INPUTS!$R$94,AQ$7<=INPUTS!$S$94),1,0) -> 0
B80: Construction quarter # in window | C80: =MAX(D80:AQ80) -> 0 | D80: =IF(D79=1,D$7-INPUTS!$R$94+1,0) -> 0 | E80: =IF(E79=1,E$7-INPUTS!$R$94+1,0) -> 0 | F80: =IF(F79=1,F$7-INPUTS!$R$94+1,0) -> 0 | G80: =IF(G79=1,G$7-INPUTS!$R$94+1,0) -> 0 | H80: =IF(H79=1,H$7-INPUTS!$R$94+1,0) -> 0 | I80: =IF(I79=1,I$7-INPUTS!$R$94+1,0) -> 0 | J80: =IF(J79=1,J$7-INPUTS!$R$94+1,0) -> 0 | K80: =IF(K79=1,K$7-INPUTS!$R$94+1,0) -> 0 | ... AQ80: =IF(AQ79=1,AQ$7-INPUTS!$R$94+1,0) -> 0
B81: Construction complete (1 = after end) | C81: =SUM(D81:AQ81) -> 0 | D81: =IF(AND((INPUTS!$E$94="Yes"),D$16=1,D$7>INPUTS!$S$94),1,0) -> 0 | E81: =IF(AND((INPUTS!$E$94="Yes"),E$16=1,E$7>INPUTS!$S$94),1,0) -> 0 | F81: =IF(AND((INPUTS!$E$94="Yes"),F$16=1,F$7>INPUTS!$S$94),1,0) -> 0 | G81: =IF(AND((INPUTS!$E$94="Yes"),G$16=1,G$7>INPUTS!$S$94),1,0) -> 0 | H81: =IF(AND((INPUTS!$E$94="Yes"),H$16=1,H$7>INPUTS!$S$94),1,0) -> 0 | I81: =IF(AND((INPUTS!$E$94="Yes"),I$16=1,I$7>INPUTS!$S$94),1,0) -> 0 | J81: =IF(AND((INPUTS!$E$94="Yes"),J$16=1,J$7>INPUTS!$S$94),1,0) -> 0 | K81: =IF(AND((INPUTS!$E$94="Yes"),K$16=1,K$7>INPUTS!$S$94),1,0) -> 0 | ... AQ81: =IF(AND((INPUTS!$E$94="Yes"),AQ$16=1,AQ$7>INPUTS!$S$94),1,0) -> 0
B82: Timing check | C82: =IF(INPUTS!$E$94<>"Yes","Off",IF(OR(NOT(ISNUMBER(INPUTS!$P$94)),NOT(ISNUMBER(INPUTS!$Q$94)),NOT(ISNUMBER(INPUTS!$R$94)),NOT(ISNUMBER(INPUTS!$S$94))),"ERROR",IF(AND(C77=INPUTS!$Q$94-INPUTS!$P$94+1,C79=INPUTS!$S$94-INPUTS!$R$94+1,C81=MAX(0,INPUTS!$C$24-INPUTS!$S$94)),"OK","ERROR"))) -> Off
B83: =IF(INPUTS!$E$95="Yes",INPUTS!$B$95,"Product row 8 (off)") -> Product row 8 (off)
B84: Sales window (1 = selling) | C84: =SUM(D84:AQ84) -> 0 | D84: =IF(AND((INPUTS!$E$95="Yes"),D$16=1,D$7>=INPUTS!$P$95,D$7<=INPUTS!$Q$95),1,0) -> 0 | E84: =IF(AND((INPUTS!$E$95="Yes"),E$16=1,E$7>=INPUTS!$P$95,E$7<=INPUTS!$Q$95),1,0) -> 0 | F84: =IF(AND((INPUTS!$E$95="Yes"),F$16=1,F$7>=INPUTS!$P$95,F$7<=INPUTS!$Q$95),1,0) -> 0 | G84: =IF(AND((INPUTS!$E$95="Yes"),G$16=1,G$7>=INPUTS!$P$95,G$7<=INPUTS!$Q$95),1,0) -> 0 | H84: =IF(AND((INPUTS!$E$95="Yes"),H$16=1,H$7>=INPUTS!$P$95,H$7<=INPUTS!$Q$95),1,0) -> 0 | I84: =IF(AND((INPUTS!$E$95="Yes"),I$16=1,I$7>=INPUTS!$P$95,I$7<=INPUTS!$Q$95),1,0) -> 0 | J84: =IF(AND((INPUTS!$E$95="Yes"),J$16=1,J$7>=INPUTS!$P$95,J$7<=INPUTS!$Q$95),1,0) -> 0 | K84: =IF(AND((INPUTS!$E$95="Yes"),K$16=1,K$7>=INPUTS!$P$95,K$7<=INPUTS!$Q$95),1,0) -> 0 | ... AQ84: =IF(AND((INPUTS!$E$95="Yes"),AQ$16=1,AQ$7>=INPUTS!$P$95,AQ$7<=INPUTS!$Q$95),1,0) -> 0
B85: Sales quarter # in window | C85: =MAX(D85:AQ85) -> 0 | D85: =IF(D84=1,D$7-INPUTS!$P$95+1,0) -> 0 | E85: =IF(E84=1,E$7-INPUTS!$P$95+1,0) -> 0 | F85: =IF(F84=1,F$7-INPUTS!$P$95+1,0) -> 0 | G85: =IF(G84=1,G$7-INPUTS!$P$95+1,0) -> 0 | H85: =IF(H84=1,H$7-INPUTS!$P$95+1,0) -> 0 | I85: =IF(I84=1,I$7-INPUTS!$P$95+1,0) -> 0 | J85: =IF(J84=1,J$7-INPUTS!$P$95+1,0) -> 0 | K85: =IF(K84=1,K$7-INPUTS!$P$95+1,0) -> 0 | ... AQ85: =IF(AQ84=1,AQ$7-INPUTS!$P$95+1,0) -> 0
B86: Construction window (1 = building) | C86: =SUM(D86:AQ86) -> 0 | D86: =IF(AND((INPUTS!$E$95="Yes"),D$16=1,D$7>=INPUTS!$R$95,D$7<=INPUTS!$S$95),1,0) -> 0 | E86: =IF(AND((INPUTS!$E$95="Yes"),E$16=1,E$7>=INPUTS!$R$95,E$7<=INPUTS!$S$95),1,0) -> 0 | F86: =IF(AND((INPUTS!$E$95="Yes"),F$16=1,F$7>=INPUTS!$R$95,F$7<=INPUTS!$S$95),1,0) -> 0 | G86: =IF(AND((INPUTS!$E$95="Yes"),G$16=1,G$7>=INPUTS!$R$95,G$7<=INPUTS!$S$95),1,0) -> 0 | H86: =IF(AND((INPUTS!$E$95="Yes"),H$16=1,H$7>=INPUTS!$R$95,H$7<=INPUTS!$S$95),1,0) -> 0 | I86: =IF(AND((INPUTS!$E$95="Yes"),I$16=1,I$7>=INPUTS!$R$95,I$7<=INPUTS!$S$95),1,0) -> 0 | J86: =IF(AND((INPUTS!$E$95="Yes"),J$16=1,J$7>=INPUTS!$R$95,J$7<=INPUTS!$S$95),1,0) -> 0 | K86: =IF(AND((INPUTS!$E$95="Yes"),K$16=1,K$7>=INPUTS!$R$95,K$7<=INPUTS!$S$95),1,0) -> 0 | ... AQ86: =IF(AND((INPUTS!$E$95="Yes"),AQ$16=1,AQ$7>=INPUTS!$R$95,AQ$7<=INPUTS!$S$95),1,0) -> 0
B87: Construction quarter # in window | C87: =MAX(D87:AQ87) -> 0 | D87: =IF(D86=1,D$7-INPUTS!$R$95+1,0) -> 0 | E87: =IF(E86=1,E$7-INPUTS!$R$95+1,0) -> 0 | F87: =IF(F86=1,F$7-INPUTS!$R$95+1,0) -> 0 | G87: =IF(G86=1,G$7-INPUTS!$R$95+1,0) -> 0 | H87: =IF(H86=1,H$7-INPUTS!$R$95+1,0) -> 0 | I87: =IF(I86=1,I$7-INPUTS!$R$95+1,0) -> 0 | J87: =IF(J86=1,J$7-INPUTS!$R$95+1,0) -> 0 | K87: =IF(K86=1,K$7-INPUTS!$R$95+1,0) -> 0 | ... AQ87: =IF(AQ86=1,AQ$7-INPUTS!$R$95+1,0) -> 0
B88: Construction complete (1 = after end) | C88: =SUM(D88:AQ88) -> 0 | D88: =IF(AND((INPUTS!$E$95="Yes"),D$16=1,D$7>INPUTS!$S$95),1,0) -> 0 | E88: =IF(AND((INPUTS!$E$95="Yes"),E$16=1,E$7>INPUTS!$S$95),1,0) -> 0 | F88: =IF(AND((INPUTS!$E$95="Yes"),F$16=1,F$7>INPUTS!$S$95),1,0) -> 0 | G88: =IF(AND((INPUTS!$E$95="Yes"),G$16=1,G$7>INPUTS!$S$95),1,0) -> 0 | H88: =IF(AND((INPUTS!$E$95="Yes"),H$16=1,H$7>INPUTS!$S$95),1,0) -> 0 | I88: =IF(AND((INPUTS!$E$95="Yes"),I$16=1,I$7>INPUTS!$S$95),1,0) -> 0 | J88: =IF(AND((INPUTS!$E$95="Yes"),J$16=1,J$7>INPUTS!$S$95),1,0) -> 0 | K88: =IF(AND((INPUTS!$E$95="Yes"),K$16=1,K$7>INPUTS!$S$95),1,0) -> 0 | ... AQ88: =IF(AND((INPUTS!$E$95="Yes"),AQ$16=1,AQ$7>INPUTS!$S$95),1,0) -> 0
B89: Timing check | C89: =IF(INPUTS!$E$95<>"Yes","Off",IF(OR(NOT(ISNUMBER(INPUTS!$P$95)),NOT(ISNUMBER(INPUTS!$Q$95)),NOT(ISNUMBER(INPUTS!$R$95)),NOT(ISNUMBER(INPUTS!$S$95))),"ERROR",IF(AND(C84=INPUTS!$Q$95-INPUTS!$P$95+1,C86=INPUTS!$S$95-INPUTS!$R$95+1,C88=MAX(0,INPUTS!$C$24-INPUTS!$S$95)),"OK","ERROR"))) -> Off
B90: =IF(INPUTS!$E$96="Yes",INPUTS!$B$96,"Product row 9 (off)") -> Product row 9 (off)
B91: Sales window (1 = selling) | C91: =SUM(D91:AQ91) -> 0 | D91: =IF(AND((INPUTS!$E$96="Yes"),D$16=1,D$7>=INPUTS!$P$96,D$7<=INPUTS!$Q$96),1,0) -> 0 | E91: =IF(AND((INPUTS!$E$96="Yes"),E$16=1,E$7>=INPUTS!$P$96,E$7<=INPUTS!$Q$96),1,0) -> 0 | F91: =IF(AND((INPUTS!$E$96="Yes"),F$16=1,F$7>=INPUTS!$P$96,F$7<=INPUTS!$Q$96),1,0) -> 0 | G91: =IF(AND((INPUTS!$E$96="Yes"),G$16=1,G$7>=INPUTS!$P$96,G$7<=INPUTS!$Q$96),1,0) -> 0 | H91: =IF(AND((INPUTS!$E$96="Yes"),H$16=1,H$7>=INPUTS!$P$96,H$7<=INPUTS!$Q$96),1,0) -> 0 | I91: =IF(AND((INPUTS!$E$96="Yes"),I$16=1,I$7>=INPUTS!$P$96,I$7<=INPUTS!$Q$96),1,0) -> 0 | J91: =IF(AND((INPUTS!$E$96="Yes"),J$16=1,J$7>=INPUTS!$P$96,J$7<=INPUTS!$Q$96),1,0) -> 0 | K91: =IF(AND((INPUTS!$E$96="Yes"),K$16=1,K$7>=INPUTS!$P$96,K$7<=INPUTS!$Q$96),1,0) -> 0 | ... AQ91: =IF(AND((INPUTS!$E$96="Yes"),AQ$16=1,AQ$7>=INPUTS!$P$96,AQ$7<=INPUTS!$Q$96),1,0) -> 0
B92: Sales quarter # in window | C92: =MAX(D92:AQ92) -> 0 | D92: =IF(D91=1,D$7-INPUTS!$P$96+1,0) -> 0 | E92: =IF(E91=1,E$7-INPUTS!$P$96+1,0) -> 0 | F92: =IF(F91=1,F$7-INPUTS!$P$96+1,0) -> 0 | G92: =IF(G91=1,G$7-INPUTS!$P$96+1,0) -> 0 | H92: =IF(H91=1,H$7-INPUTS!$P$96+1,0) -> 0 | I92: =IF(I91=1,I$7-INPUTS!$P$96+1,0) -> 0 | J92: =IF(J91=1,J$7-INPUTS!$P$96+1,0) -> 0 | K92: =IF(K91=1,K$7-INPUTS!$P$96+1,0) -> 0 | ... AQ92: =IF(AQ91=1,AQ$7-INPUTS!$P$96+1,0) -> 0
B93: Construction window (1 = building) | C93: =SUM(D93:AQ93) -> 0 | D93: =IF(AND((INPUTS!$E$96="Yes"),D$16=1,D$7>=INPUTS!$R$96,D$7<=INPUTS!$S$96),1,0) -> 0 | E93: =IF(AND((INPUTS!$E$96="Yes"),E$16=1,E$7>=INPUTS!$R$96,E$7<=INPUTS!$S$96),1,0) -> 0 | F93: =IF(AND((INPUTS!$E$96="Yes"),F$16=1,F$7>=INPUTS!$R$96,F$7<=INPUTS!$S$96),1,0) -> 0 | G93: =IF(AND((INPUTS!$E$96="Yes"),G$16=1,G$7>=INPUTS!$R$96,G$7<=INPUTS!$S$96),1,0) -> 0 | H93: =IF(AND((INPUTS!$E$96="Yes"),H$16=1,H$7>=INPUTS!$R$96,H$7<=INPUTS!$S$96),1,0) -> 0 | I93: =IF(AND((INPUTS!$E$96="Yes"),I$16=1,I$7>=INPUTS!$R$96,I$7<=INPUTS!$S$96),1,0) -> 0 | J93: =IF(AND((INPUTS!$E$96="Yes"),J$16=1,J$7>=INPUTS!$R$96,J$7<=INPUTS!$S$96),1,0) -> 0 | K93: =IF(AND((INPUTS!$E$96="Yes"),K$16=1,K$7>=INPUTS!$R$96,K$7<=INPUTS!$S$96),1,0) -> 0 | ... AQ93: =IF(AND((INPUTS!$E$96="Yes"),AQ$16=1,AQ$7>=INPUTS!$R$96,AQ$7<=INPUTS!$S$96),1,0) -> 0
B94: Construction quarter # in window | C94: =MAX(D94:AQ94) -> 0 | D94: =IF(D93=1,D$7-INPUTS!$R$96+1,0) -> 0 | E94: =IF(E93=1,E$7-INPUTS!$R$96+1,0) -> 0 | F94: =IF(F93=1,F$7-INPUTS!$R$96+1,0) -> 0 | G94: =IF(G93=1,G$7-INPUTS!$R$96+1,0) -> 0 | H94: =IF(H93=1,H$7-INPUTS!$R$96+1,0) -> 0 | I94: =IF(I93=1,I$7-INPUTS!$R$96+1,0) -> 0 | J94: =IF(J93=1,J$7-INPUTS!$R$96+1,0) -> 0 | K94: =IF(K93=1,K$7-INPUTS!$R$96+1,0) -> 0 | ... AQ94: =IF(AQ93=1,AQ$7-INPUTS!$R$96+1,0) -> 0
B95: Construction complete (1 = after end) | C95: =SUM(D95:AQ95) -> 0 | D95: =IF(AND((INPUTS!$E$96="Yes"),D$16=1,D$7>INPUTS!$S$96),1,0) -> 0 | E95: =IF(AND((INPUTS!$E$96="Yes"),E$16=1,E$7>INPUTS!$S$96),1,0) -> 0 | F95: =IF(AND((INPUTS!$E$96="Yes"),F$16=1,F$7>INPUTS!$S$96),1,0) -> 0 | G95: =IF(AND((INPUTS!$E$96="Yes"),G$16=1,G$7>INPUTS!$S$96),1,0) -> 0 | H95: =IF(AND((INPUTS!$E$96="Yes"),H$16=1,H$7>INPUTS!$S$96),1,0) -> 0 | I95: =IF(AND((INPUTS!$E$96="Yes"),I$16=1,I$7>INPUTS!$S$96),1,0) -> 0 | J95: =IF(AND((INPUTS!$E$96="Yes"),J$16=1,J$7>INPUTS!$S$96),1,0) -> 0 | K95: =IF(AND((INPUTS!$E$96="Yes"),K$16=1,K$7>INPUTS!$S$96),1,0) -> 0 | ... AQ95: =IF(AND((INPUTS!$E$96="Yes"),AQ$16=1,AQ$7>INPUTS!$S$96),1,0) -> 0
B96: Timing check | C96: =IF(INPUTS!$E$96<>"Yes","Off",IF(OR(NOT(ISNUMBER(INPUTS!$P$96)),NOT(ISNUMBER(INPUTS!$Q$96)),NOT(ISNUMBER(INPUTS!$R$96)),NOT(ISNUMBER(INPUTS!$S$96))),"ERROR",IF(AND(C91=INPUTS!$Q$96-INPUTS!$P$96+1,C93=INPUTS!$S$96-INPUTS!$R$96+1,C95=MAX(0,INPUTS!$C$24-INPUTS!$S$96)),"OK","ERROR"))) -> Off
B97: =IF(INPUTS!$E$97="Yes",INPUTS!$B$97,"Product row 10 (off)") -> Product row 10 (off)
B98: Sales window (1 = selling) | C98: =SUM(D98:AQ98) -> 0 | D98: =IF(AND((INPUTS!$E$97="Yes"),D$16=1,D$7>=INPUTS!$P$97,D$7<=INPUTS!$Q$97),1,0) -> 0 | E98: =IF(AND((INPUTS!$E$97="Yes"),E$16=1,E$7>=INPUTS!$P$97,E$7<=INPUTS!$Q$97),1,0) -> 0 | F98: =IF(AND((INPUTS!$E$97="Yes"),F$16=1,F$7>=INPUTS!$P$97,F$7<=INPUTS!$Q$97),1,0) -> 0 | G98: =IF(AND((INPUTS!$E$97="Yes"),G$16=1,G$7>=INPUTS!$P$97,G$7<=INPUTS!$Q$97),1,0) -> 0 | H98: =IF(AND((INPUTS!$E$97="Yes"),H$16=1,H$7>=INPUTS!$P$97,H$7<=INPUTS!$Q$97),1,0) -> 0 | I98: =IF(AND((INPUTS!$E$97="Yes"),I$16=1,I$7>=INPUTS!$P$97,I$7<=INPUTS!$Q$97),1,0) -> 0 | J98: =IF(AND((INPUTS!$E$97="Yes"),J$16=1,J$7>=INPUTS!$P$97,J$7<=INPUTS!$Q$97),1,0) -> 0 | K98: =IF(AND((INPUTS!$E$97="Yes"),K$16=1,K$7>=INPUTS!$P$97,K$7<=INPUTS!$Q$97),1,0) -> 0 | ... AQ98: =IF(AND((INPUTS!$E$97="Yes"),AQ$16=1,AQ$7>=INPUTS!$P$97,AQ$7<=INPUTS!$Q$97),1,0) -> 0
B99: Sales quarter # in window | C99: =MAX(D99:AQ99) -> 0 | D99: =IF(D98=1,D$7-INPUTS!$P$97+1,0) -> 0 | E99: =IF(E98=1,E$7-INPUTS!$P$97+1,0) -> 0 | F99: =IF(F98=1,F$7-INPUTS!$P$97+1,0) -> 0 | G99: =IF(G98=1,G$7-INPUTS!$P$97+1,0) -> 0 | H99: =IF(H98=1,H$7-INPUTS!$P$97+1,0) -> 0 | I99: =IF(I98=1,I$7-INPUTS!$P$97+1,0) -> 0 | J99: =IF(J98=1,J$7-INPUTS!$P$97+1,0) -> 0 | K99: =IF(K98=1,K$7-INPUTS!$P$97+1,0) -> 0 | ... AQ99: =IF(AQ98=1,AQ$7-INPUTS!$P$97+1,0) -> 0
B100: Construction window (1 = building) | C100: =SUM(D100:AQ100) -> 0 | D100: =IF(AND((INPUTS!$E$97="Yes"),D$16=1,D$7>=INPUTS!$R$97,D$7<=INPUTS!$S$97),1,0) -> 0 | E100: =IF(AND((INPUTS!$E$97="Yes"),E$16=1,E$7>=INPUTS!$R$97,E$7<=INPUTS!$S$97),1,0) -> 0 | F100: =IF(AND((INPUTS!$E$97="Yes"),F$16=1,F$7>=INPUTS!$R$97,F$7<=INPUTS!$S$97),1,0) -> 0 | G100: =IF(AND((INPUTS!$E$97="Yes"),G$16=1,G$7>=INPUTS!$R$97,G$7<=INPUTS!$S$97),1,0) -> 0 | H100: =IF(AND((INPUTS!$E$97="Yes"),H$16=1,H$7>=INPUTS!$R$97,H$7<=INPUTS!$S$97),1,0) -> 0 | I100: =IF(AND((INPUTS!$E$97="Yes"),I$16=1,I$7>=INPUTS!$R$97,I$7<=INPUTS!$S$97),1,0) -> 0 | J100: =IF(AND((INPUTS!$E$97="Yes"),J$16=1,J$7>=INPUTS!$R$97,J$7<=INPUTS!$S$97),1,0) -> 0 | K100: =IF(AND((INPUTS!$E$97="Yes"),K$16=1,K$7>=INPUTS!$R$97,K$7<=INPUTS!$S$97),1,0) -> 0 | ... AQ100: =IF(AND((INPUTS!$E$97="Yes"),AQ$16=1,AQ$7>=INPUTS!$R$97,AQ$7<=INPUTS!$S$97),1,0) -> 0
B101: Construction quarter # in window | C101: =MAX(D101:AQ101) -> 0 | D101: =IF(D100=1,D$7-INPUTS!$R$97+1,0) -> 0 | E101: =IF(E100=1,E$7-INPUTS!$R$97+1,0) -> 0 | F101: =IF(F100=1,F$7-INPUTS!$R$97+1,0) -> 0 | G101: =IF(G100=1,G$7-INPUTS!$R$97+1,0) -> 0 | H101: =IF(H100=1,H$7-INPUTS!$R$97+1,0) -> 0 | I101: =IF(I100=1,I$7-INPUTS!$R$97+1,0) -> 0 | J101: =IF(J100=1,J$7-INPUTS!$R$97+1,0) -> 0 | K101: =IF(K100=1,K$7-INPUTS!$R$97+1,0) -> 0 | ... AQ101: =IF(AQ100=1,AQ$7-INPUTS!$R$97+1,0) -> 0
B102: Construction complete (1 = after end) | C102: =SUM(D102:AQ102) -> 0 | D102: =IF(AND((INPUTS!$E$97="Yes"),D$16=1,D$7>INPUTS!$S$97),1,0) -> 0 | E102: =IF(AND((INPUTS!$E$97="Yes"),E$16=1,E$7>INPUTS!$S$97),1,0) -> 0 | F102: =IF(AND((INPUTS!$E$97="Yes"),F$16=1,F$7>INPUTS!$S$97),1,0) -> 0 | G102: =IF(AND((INPUTS!$E$97="Yes"),G$16=1,G$7>INPUTS!$S$97),1,0) -> 0 | H102: =IF(AND((INPUTS!$E$97="Yes"),H$16=1,H$7>INPUTS!$S$97),1,0) -> 0 | I102: =IF(AND((INPUTS!$E$97="Yes"),I$16=1,I$7>INPUTS!$S$97),1,0) -> 0 | J102: =IF(AND((INPUTS!$E$97="Yes"),J$16=1,J$7>INPUTS!$S$97),1,0) -> 0 | K102: =IF(AND((INPUTS!$E$97="Yes"),K$16=1,K$7>INPUTS!$S$97),1,0) -> 0 | ... AQ102: =IF(AND((INPUTS!$E$97="Yes"),AQ$16=1,AQ$7>INPUTS!$S$97),1,0) -> 0
B103: Timing check | C103: =IF(INPUTS!$E$97<>"Yes","Off",IF(OR(NOT(ISNUMBER(INPUTS!$P$97)),NOT(ISNUMBER(INPUTS!$Q$97)),NOT(ISNUMBER(INPUTS!$R$97)),NOT(ISNUMBER(INPUTS!$S$97))),"ERROR",IF(AND(C98=INPUTS!$Q$97-INPUTS!$P$97+1,C100=INPUTS!$S$97-INPUTS!$R$97+1,C102=MAX(0,INPUTS!$C$24-INPUTS!$S$97)),"OK","ERROR"))) -> Off
B105: D. COST PHASING WINDOWS (for curve-based heads; 'Follow …' heads are driven by sales / construction / collections)
...

Sheet CURVES
B2: CURVE ENGINE — turns curve names into quarterly percentages that always add up to 100%
B3: Curve engine status | C3: =IF(COUNTIF(C186:C192,"ERROR")=0,"OK","ERROR") -> OK
B4: No inputs here. Each row = share of a total that falls in each quarter. Position (i) and window length (n) come from TIMELINE; the curve name comes from INPUTS.
B6: Quarter | C6: Total | D6: =TIMELINE!D8 -> Q1 | E6: =TIMELINE!E8 -> Q2 | F6: =TIMELINE!F8 -> Q3 | G6: =TIMELINE!G8 -> Q4 | H6: =TIMELINE!H8 -> Q5 | I6: =TIMELINE!I8 -> Q6 | J6: =TIMELINE!J8 -> Q7 | K6: =TIMELINE!K8 -> Q8 | ... AQ6: =TIMELINE!AQ8 -> Q40
B7: Quarter end | D7: =TIMELINE!D9 -> 46568 | E7: =TIMELINE!E9 -> 46660 | F7: =TIMELINE!F9 -> 46752 | G7: =TIMELINE!G9 -> 46843 | H7: =TIMELINE!H9 -> 46934 | I7: =TIMELINE!I9 -> 47026 | J7: =TIMELINE!J9 -> 47118 | K7: =TIMELINE!K9 -> 47208 | ... AQ7: =TIMELINE!AQ9 -> 50130
B9: A. CURVE GALLERY – the five shapes over a 12-quarter window (for explanation & charts)
B10: Window length used for the gallery (n) | C10: 12
B11: Position in window (i) | D11: 1 | E11: 2 | F11: 3 | G11: 4 | H11: 5 | I11: 6 | J11: 7 | K11: 8 | L11: 9 | M11: 10 | N11: 11 | O11: 12
B12: Upfront | C12: =SUM(D12:O12) -> 1 | D12: =IF(OR(D$11=0,$C$10=0),0,IF("Upfront"="Upfront",--(D$11=1),IF("Upfront"="Even",1/$C$10,IF("Upfront"="Front-loaded",($C$10-D$11+1)*2/($C$10*($C$10+1)),IF("Upfront"="Back-loaded",D$11*2/($C$10*($C$10+1)),IF("Upfront"="S-curve",SIN(PI()*(D$11-0.5)/$C$10)*SIN(PI()/(2*$C$10)),0)))))) -> 1 | E12: =IF(OR(E$11=0,$C$10=0),0,IF("Upfront"="Upfront",--(E$11=1),IF("Upfront"="Even",1/$C$10,IF("Upfront"="Front-loaded",($C$10-E$11+1)*2/($C$10*($C$10+1)),IF("Upfront"="Back-loaded",E$11*2/($C$10*($C$10+1)),IF("Upfront"="S-curve",SIN(PI()*(E$11-0.5)/$C$10)*SIN(PI()/(2*$C$10)),0)))))) -> 0 | F12: =IF(OR(F$11=0,$C$10=0),0,IF("Upfront"="Upfront",--(F$11=1),IF("Upfront"="Even",1/$C$10,IF("Upfront"="Front-loaded",($C$10-F$11+1)*2/($C$10*($C$10+1)),IF("Upfront"="Back-loaded",F$11*2/($C$10*($C$10+1)),IF("Upfront"="S-curve",SIN(PI()*(F$11-0.5)/$C$10)*SIN(PI()/(2*$C$10)),0)))))) -> 0 | G12: =IF(OR(G$11=0,$C$10=0),0,IF("Upfront"="Upfront",--(G$11=1),IF("Upfront"="Even",1/$C$10,IF("Upfront"="Front-loaded",($C$10-G$11+1)*2/($C$10*($C$10+1)),IF("Upfront"="Back-loaded",G$11*2/($C$10*($C$10+1)),IF("Upfront"="S-curve",SIN(PI()*(G$11-0.5)/$C$10)*SIN(PI()/(2*$C$10)),0)))))) -> 0 | H12: =IF(OR(H$11=0,$C$10=0),0,IF("Upfront"="Upfront",--(H$11=1),IF("Upfront"="Even",1/$C$10,IF("Upfront"="Front-loaded",($C$10-H$11+1)*2/($C$10*($C$10+1)),IF("Upfront"="Back-loaded",H$11*2/($C$10*($C$10+1)),IF("Upfront"="S-curve",SIN(PI()*(H$11-0.5)/$C$10)*SIN(PI()/(2*$C$10)),0)))))) -> 0 | I12: =IF(OR(I$11=0,$C$10=0),0,IF("Upfront"="Upfront",--(I$11=1),IF("Upfront"="Even",1/$C$10,IF("Upfront"="Front-loaded",($C$10-I$11+1)*2/($C$10*($C$10+1)),IF("Upfront"="Back-loaded",I$11*2/($C$10*($C$10+1)),IF("Upfront"="S-curve",SIN(PI()*(I$11-0.5)/$C$10)*SIN(PI()/(2*$C$10)),0)))))) -> 0 | J12: =IF(OR(J$11=0,$C$10=0),0,IF("Upfront"="Upfront",--(J$11=1),IF("Upfront"="Even",1/$C$10,IF("Upfront"="Front-loaded",($C$10-J$11+1)*2/($C$10*($C$10+1)),IF("Upfront"="Back-loaded",J$11*2/($C$10*($C$10+1)),IF("Upfront"="S-curve",SIN(PI()*(J$11-0.5)/$C$10)*SIN(PI()/(2*$C$10)),0)))))) -> 0 | K12: =IF(OR(K$11=0,$C$10=0),0,IF("Upfront"="Upfront",--(K$11=1),IF("Upfront"="Even",1/$C$10,IF("Upfront"="Front-loaded",($C$10-K$11+1)*2/($C$10*($C$10+1)),IF("Upfront"="Back-loaded",K$11*2/($C$10*($C$10+1)),IF("Upfront"="S-curve",SIN(PI()*(K$11-0.5)/$C$10)*SIN(PI()/(2*$C$10)),0)))))) -> 0 | ... O12: =IF(OR(O$11=0,$C$10=0),0,IF("Upfront"="Upfront",--(O$11=1),IF("Upfront"="Even",1/$C$10,IF("Upfront"="Front-loaded",($C$10-O$11+1)*2/($C$10*($C$10+1)),IF("Upfront"="Back-loaded",O$11*2/($C$10*($C$10+1)),IF("Upfront"="S-curve",SIN(PI()*(O$11-0.5)/$C$10)*SIN(PI()/(2*$C$10)),0)))))) -> 0
B13: Even | C13: =SUM(D13:O13) -> 1 | D13: =IF(OR(D$11=0,$C$10=0),0,IF("Even"="Upfront",--(D$11=1),IF("Even"="Even",1/$C$10,IF("Even"="Front-loaded",($C$10-D$11+1)*2/($C$10*($C$10+1)),IF("Even"="Back-loaded",D$11*2/($C$10*($C$10+1)),IF("Even"="S-curve",SIN(PI()*(D$11-0.5)/$C$10)*SIN(PI()/(2*$C$10)),0)))))) -> 0.083333333 | E13: =IF(OR(E$11=0,$C$10=0),0,IF("Even"="Upfront",--(E$11=1),IF("Even"="Even",1/$C$10,IF("Even"="Front-loaded",($C$10-E$11+1)*2/($C$10*($C$10+1)),IF("Even"="Back-loaded",E$11*2/($C$10*($C$10+1)),IF("Even"="S-curve",SIN(PI()*(E$11-0.5)/$C$10)*SIN(PI()/(2*$C$10)),0)))))) -> 0.083333333 | F13: =IF(OR(F$11=0,$C$10=0),0,IF("Even"="Upfront",--(F$11=1),IF("Even"="Even",1/$C$10,IF("Even"="Front-loaded",($C$10-F$11+1)*2/($C$10*($C$10+1)),IF("Even"="Back-loaded",F$11*2/($C$10*($C$10+1)),IF("Even"="S-curve",SIN(PI()*(F$11-0.5)/$C$10)*SIN(PI()/(2*$C$10)),0)))))) -> 0.083333333 | G13: =IF(OR(G$11=0,$C$10=0),0,IF("Even"="Upfront",--(G$11=1),IF("Even"="Even",1/$C$10,IF("Even"="Front-loaded",($C$10-G$11+1)*2/($C$10*($C$10+1)),IF("Even"="Back-loaded",G$11*2/($C$10*($C$10+1)),IF("Even"="S-curve",SIN(PI()*(G$11-0.5)/$C$10)*SIN(PI()/(2*$C$10)),0)))))) -> 0.083333333 | H13: =IF(OR(H$11=0,$C$10=0),0,IF("Even"="Upfront",--(H$11=1),IF("Even"="Even",1/$C$10,IF("Even"="Front-loaded",($C$10-H$11+1)*2/($C$10*($C$10+1)),IF("Even"="Back-loaded",H$11*2/($C$10*($C$10+1)),IF("Even"="S-curve",SIN(PI()*(H$11-0.5)/$C$10)*SIN(PI()/(2*$C$10)),0)))))) -> 0.083333333 | I13: =IF(OR(I$11=0,$C$10=0),0,IF("Even"="Upfront",--(I$11=1),IF("Even"="Even",1/$C$10,IF("Even"="Front-loaded",($C$10-I$11+1)*2/($C$10*($C$10+1)),IF("Even"="Back-loaded",I$11*2/($C$10*($C$10+1)),IF("Even"="S-curve",SIN(PI()*(I$11-0.5)/$C$10)*SIN(PI()/(2*$C$10)),0)))))) -> 0.083333333 | J13: =IF(OR(J$11=0,$C$10=0),0,IF("Even"="Upfront",--(J$11=1),IF("Even"="Even",1/$C$10,IF("Even"="Front-loaded",($C$10-J$11+1)*2/($C$10*($C$10+1)),IF("Even"="Back-loaded",J$11*2/($C$10*($C$10+1)),IF("Even"="S-curve",SIN(PI()*(J$11-0.5)/$C$10)*SIN(PI()/(2*$C$10)),0)))))) -> 0.083333333 | K13: =IF(OR(K$11=0,$C$10=0),0,IF("Even"="Upfront",--(K$11=1),IF("Even"="Even",1/$C$10,IF("Even"="Front-loaded",($C$10-K$11+1)*2/($C$10*($C$10+1)),IF("Even"="Back-loaded",K$11*2/($C$10*($C$10+1)),IF("Even"="S-curve",SIN(PI()*(K$11-0.5)/$C$10)*SIN(PI()/(2*$C$10)),0)))))) -> 0.083333333 | ... O13: =IF(OR(O$11=0,$C$10=0),0,IF("Even"="Upfront",--(O$11=1),IF("Even"="Even",1/$C$10,IF("Even"="Front-loaded",($C$10-O$11+1)*2/($C$10*($C$10+1)),IF("Even"="Back-loaded",O$11*2/($C$10*($C$10+1)),IF("Even"="S-curve",SIN(PI()*(O$11-0.5)/$C$10)*SIN(PI()/(2*$C$10)),0)))))) -> 0.083333333
B14: Front-loaded | C14: =SUM(D14:O14) -> 1 | D14: =IF(OR(D$11=0,$C$10=0),0,IF("Front-loaded"="Upfront",--(D$11=1),IF("Front-loaded"="Even",1/$C$10,IF("Front-loaded"="Front-loaded",($C$10-D$11+1)*2/($C$10*($C$10+1)),IF("Front-loaded"="Back-loaded",D$11*2/($C$10*($C$10+1)),IF("Front-loaded"="S-curve",SIN(PI()*(D$11-0.5)/$C$10)*SIN(PI()/(2*$C$10)),0)))))) -> 0.15384615 | E14: =IF(OR(E$11=0,$C$10=0),0,IF("Front-loaded"="Upfront",--(E$11=1),IF("Front-loaded"="Even",1/$C$10,IF("Front-loaded"="Front-loaded",($C$10-E$11+1)*2/($C$10*($C$10+1)),IF("Front-loaded"="Back-loaded",E$11*2/($C$10*($C$10+1)),IF("Front-loaded"="S-curve",SIN(PI()*(E$11-0.5)/$C$10)*SIN(PI()/(2*$C$10)),0)))))) -> 0.14102564 | F14: =IF(OR(F$11=0,$C$10=0),0,IF("Front-loaded"="Upfront",--(F$11=1),IF("Front-loaded"="Even",1/$C$10,IF("Front-loaded"="Front-loaded",($C$10-F$11+1)*2/($C$10*($C$10+1)),IF("Front-loaded"="Back-loaded",F$11*2/($C$10*($C$10+1)),IF("Front-loaded"="S-curve",SIN(PI()*(F$11-0.5)/$C$10)*SIN(PI()/(2*$C$10)),0)))))) -> 0.12820513 | G14: =IF(OR(G$11=0,$C$10=0),0,IF("Front-loaded"="Upfront",--(G$11=1),IF("Front-loaded"="Even",1/$C$10,IF("Front-loaded"="Front-loaded",($C$10-G$11+1)*2/($C$10*($C$10+1)),IF("Front-loaded"="Back-loaded",G$11*2/($C$10*($C$10+1)),IF("Front-loaded"="S-curve",SIN(PI()*(G$11-0.5)/$C$10)*SIN(PI()/(2*$C$10)),0)))))) -> 0.11538462 | H14: =IF(OR(H$11=0,$C$10=0),0,IF("Front-loaded"="Upfront",--(H$11=1),IF("Front-loaded"="Even",1/$C$10,IF("Front-loaded"="Front-loaded",($C$10-H$11+1)*2/($C$10*($C$10+1)),IF("Front-loaded"="Back-loaded",H$11*2/($C$10*($C$10+1)),IF("Front-loaded"="S-curve",SIN(PI()*(H$11-0.5)/$C$10)*SIN(PI()/(2*$C$10)),0)))))) -> 0.1025641 | I14: =IF(OR(I$11=0,$C$10=0),0,IF("Front-loaded"="Upfront",--(I$11=1),IF("Front-loaded"="Even",1/$C$10,IF("Front-loaded"="Front-loaded",($C$10-I$11+1)*2/($C$10*($C$10+1)),IF("Front-loaded"="Back-loaded",I$11*2/($C$10*($C$10+1)),IF("Front-loaded"="S-curve",SIN(PI()*(I$11-0.5)/$C$10)*SIN(PI()/(2*$C$10)),0)))))) -> 0.08974359 | J14: =IF(OR(J$11=0,$C$10=0),0,IF("Front-loaded"="Upfront",--(J$11=1),IF("Front-loaded"="Even",1/$C$10,IF("Front-loaded"="Front-loaded",($C$10-J$11+1)*2/($C$10*($C$10+1)),IF("Front-loaded"="Back-loaded",J$11*2/($C$10*($C$10+1)),IF("Front-loaded"="S-curve",SIN(PI()*(J$11-0.5)/$C$10)*SIN(PI()/(2*$C$10)),0)))))) -> 0.076923077 | K14: =IF(OR(K$11=0,$C$10=0),0,IF("Front-loaded"="Upfront",--(K$11=1),IF("Front-loaded"="Even",1/$C$10,IF("Front-loaded"="Front-loaded",($C$10-K$11+1)*2/($C$10*($C$10+1)),IF("Front-loaded"="Back-loaded",K$11*2/($C$10*($C$10+1)),IF("Front-loaded"="S-curve",SIN(PI()*(K$11-0.5)/$C$10)*SIN(PI()/(2*$C$10)),0)))))) -> 0.064102564 | ... O14: =IF(OR(O$11=0,$C$10=0),0,IF("Front-loaded"="Upfront",--(O$11=1),IF("Front-loaded"="Even",1/$C$10,IF("Front-loaded"="Front-loaded",($C$10-O$11+1)*2/($C$10*($C$10+1)),IF("Front-loaded"="Back-loaded",O$11*2/($C$10*($C$10+1)),IF("Front-loaded"="S-curve",SIN(PI()*(O$11-0.5)/$C$10)*SIN(PI()/(2*$C$10)),0)))))) -> 0.012820513
B15: Back-loaded | C15: =SUM(D15:O15) -> 1 | D15: =IF(OR(D$11=0,$C$10=0),0,IF("Back-loaded"="Upfront",--(D$11=1),IF("Back-loaded"="Even",1/$C$10,IF("Back-loaded"="Front-loaded",($C$10-D$11+1)*2/($C$10*($C$10+1)),IF("Back-loaded"="Back-loaded",D$11*2/($C$10*($C$10+1)),IF("Back-loaded"="S-curve",SIN(PI()*(D$11-0.5)/$C$10)*SIN(PI()/(2*$C$10)),0)))))) -> 0.012820513 | E15: =IF(OR(E$11=0,$C$10=0),0,IF("Back-loaded"="Upfront",--(E$11=1),IF("Back-loaded"="Even",1/$C$10,IF("Back-loaded"="Front-loaded",($C$10-E$11+1)*2/($C$10*($C$10+1)),IF("Back-loaded"="Back-loaded",E$11*2/($C$10*($C$10+1)),IF("Back-loaded"="S-curve",SIN(PI()*(E$11-0.5)/$C$10)*SIN(PI()/(2*$C$10)),0)))))) -> 0.025641026 | F15: =IF(OR(F$11=0,$C$10=0),0,IF("Back-loaded"="Upfront",--(F$11=1),IF("Back-loaded"="Even",1/$C$10,IF("Back-loaded"="Front-loaded",($C$10-F$11+1)*2/($C$10*($C$10+1)),IF("Back-loaded"="Back-loaded",F$11*2/($C$10*($C$10+1)),IF("Back-loaded"="S-curve",SIN(PI()*(F$11-0.5)/$C$10)*SIN(PI()/(2*$C$10)),0)))))) -> 0.038461538 | G15: =IF(OR(G$11=0,$C$10=0),0,IF("Back-loaded"="Upfront",--(G$11=1),IF("Back-loaded"="Even",1/$C$10,IF("Back-loaded"="Front-loaded",($C$10-G$11+1)*2/($C$10*($C$10+1)),IF("Back-loaded"="Back-loaded",G$11*2/($C$10*($C$10+1)),IF("Back-loaded"="S-curve",SIN(PI()*(G$11-0.5)/$C$10)*SIN(PI()/(2*$C$10)),0)))))) -> 0.051282051 | H15: =IF(OR(H$11=0,$C$10=0),0,IF("Back-loaded"="Upfront",--(H$11=1),IF("Back-loaded"="Even",1/$C$10,IF("Back-loaded"="Front-loaded",($C$10-H$11+1)*2/($C$10*($C$10+1)),IF("Back-loaded"="Back-loaded",H$11*2/($C$10*($C$10+1)),IF("Back-loaded"="S-curve",SIN(PI()*(H$11-0.5)/$C$10)*SIN(PI()/(2*$C$10)),0)))))) -> 0.064102564 | I15: =IF(OR(I$11=0,$C$10=0),0,IF("Back-loaded"="Upfront",--(I$11=1),IF("Back-loaded"="Even",1/$C$10,IF("Back-loaded"="Front-loaded",($C$10-I$11+1)*2/($C$10*($C$10+1)),IF("Back-loaded"="Back-loaded",I$11*2/($C$10*($C$10+1)),IF("Back-loaded"="S-curve",SIN(PI()*(I$11-0.5)/$C$10)*SIN(PI()/(2*$C$10)),0)))))) -> 0.076923077 | J15: =IF(OR(J$11=0,$C$10=0),0,IF("Back-loaded"="Upfront",--(J$11=1),IF("Back-loaded"="Even",1/$C$10,IF("Back-loaded"="Front-loaded",($C$10-J$11+1)*2/($C$10*($C$10+1)),IF("Back-loaded"="Back-loaded",J$11*2/($C$10*($C$10+1)),IF("Back-loaded"="S-curve",SIN(PI()*(J$11-0.5)/$C$10)*SIN(PI()/(2*$C$10)),0)))))) -> 0.08974359 | K15: =IF(OR(K$11=0,$C$10=0),0,IF("Back-loaded"="Upfront",--(K$11=1),IF("Back-loaded"="Even",1/$C$10,IF("Back-loaded"="Front-loaded",($C$10-K$11+1)*2/($C$10*($C$10+1)),IF("Back-loaded"="Back-loaded",K$11*2/($C$10*($C$10+1)),IF("Back-loaded"="S-curve",SIN(PI()*(K$11-0.5)/$C$10)*SIN(PI()/(2*$C$10)),0)))))) -> 0.1025641 | ... O15: =IF(OR(O$11=0,$C$10=0),0,IF("Back-loaded"="Upfront",--(O$11=1),IF("Back-loaded"="Even",1/$C$10,IF("Back-loaded"="Front-loaded",($C$10-O$11+1)*2/($C$10*($C$10+1)),IF("Back-loaded"="Back-loaded",O$11*2/($C$10*($C$10+1)),IF("Back-loaded"="S-curve",SIN(PI()*(O$11-0.5)/$C$10)*SIN(PI()/(2*$C$10)),0)))))) -> 0.15384615
B16: S-curve | C16: =SUM(D16:O16) -> 1 | D16: =IF(OR(D$11=0,$C$10=0),0,IF("S-curve"="Upfront",--(D$11=1),IF("S-curve"="Even",1/$C$10,IF("S-curve"="Front-loaded",($C$10-D$11+1)*2/($C$10*($C$10+1)),IF("S-curve"="Back-loaded",D$11*2/($C$10*($C$10+1)),IF("S-curve"="S-curve",SIN(PI()*(D$11-0.5)/$C$10)*SIN(PI()/(2*$C$10)),0)))))) -> 0.017037087 | E16: =IF(OR(E$11=0,$C$10=0),0,IF("S-curve"="Upfront",--(E$11=1),IF("S-curve"="Even",1/$C$10,IF("S-curve"="Front-loaded",($C$10-E$11+1)*2/($C$10*($C$10+1)),IF("S-curve"="Back-loaded",E$11*2/($C$10*($C$10+1)),IF("S-curve"="S-curve",SIN(PI()*(E$11-0.5)/$C$10)*SIN(PI()/(2*$C$10)),0)))))) -> 0.049950211 | F16: =IF(OR(F$11=0,$C$10=0),0,IF("S-curve"="Upfront",--(F$11=1),IF("S-curve"="Even",1/$C$10,IF("S-curve"="Front-loaded",($C$10-F$11+1)*2/($C$10*($C$10+1)),IF("S-curve"="Back-loaded",F$11*2/($C$10*($C$10+1)),IF("S-curve"="S-curve",SIN(PI()*(F$11-0.5)/$C$10)*SIN(PI()/(2*$C$10)),0)))))) -> 0.079459311 | G16: =IF(OR(G$11=0,$C$10=0),0,IF("S-curve"="Upfront",--(G$11=1),IF("S-curve"="Even",1/$C$10,IF("S-curve"="Front-loaded",($C$10-G$11+1)*2/($C$10*($C$10+1)),IF("S-curve"="Back-loaded",G$11*2/($C$10*($C$10+1)),IF("S-curve"="S-curve",SIN(PI()*(G$11-0.5)/$C$10)*SIN(PI()/(2*$C$10)),0)))))) -> 0.10355339 | H16: =IF(OR(H$11=0,$C$10=0),0,IF("S-curve"="Upfront",--(H$11=1),IF("S-curve"="Even",1/$C$10,IF("S-curve"="Front-loaded",($C$10-H$11+1)*2/($C$10*($C$10+1)),IF("S-curve"="Back-loaded",H$11*2/($C$10*($C$10+1)),IF("S-curve"="S-curve",SIN(PI()*(H$11-0.5)/$C$10)*SIN(PI()/(2*$C$10)),0)))))) -> 0.12059048 | I16: =IF(OR(I$11=0,$C$10=0),0,IF("S-curve"="Upfront",--(I$11=1),IF("S-curve"="Even",1/$C$10,IF("S-curve"="Front-loaded",($C$10-I$11+1)*2/($C$10*($C$10+1)),IF("S-curve"="Back-loaded",I$11*2/($C$10*($C$10+1)),IF("S-curve"="S-curve",SIN(PI()*(I$11-0.5)/$C$10)*SIN(PI()/(2*$C$10)),0)))))) -> 0.12940952 | J16: =IF(OR(J$11=0,$C$10=0),0,IF("S-curve"="Upfront",--(J$11=1),IF("S-curve"="Even",1/$C$10,IF("S-curve"="Front-loaded",($C$10-J$11+1)*2/($C$10*($C$10+1)),IF("S-curve"="Back-loaded",J$11*2/($C$10*($C$10+1)),IF("S-curve"="S-curve",SIN(PI()*(J$11-0.5)/$C$10)*SIN(PI()/(2*$C$10)),0)))))) -> 0.12940952 | K16: =IF(OR(K$11=0,$C$10=0),0,IF("S-curve"="Upfront",--(K$11=1),IF("S-curve"="Even",1/$C$10,IF("S-curve"="Front-loaded",($C$10-K$11+1)*2/($C$10*($C$10+1)),IF("S-curve"="Back-loaded",K$11*2/($C$10*($C$10+1)),IF("S-curve"="S-curve",SIN(PI()*(K$11-0.5)/$C$10)*SIN(PI()/(2*$C$10)),0)))))) -> 0.12059048 | ... O16: =IF(OR(O$11=0,$C$10=0),0,IF("S-curve"="Upfront",--(O$11=1),IF("S-curve"="Even",1/$C$10,IF("S-curve"="Front-loaded",($C$10-O$11+1)*2/($C$10*($C$10+1)),IF("S-curve"="Back-loaded",O$11*2/($C$10*($C$10+1)),IF("S-curve"="S-curve",SIN(PI()*(O$11-0.5)/$C$10)*SIN(PI()/(2*$C$10)),0)))))) -> 0.017037087
B17: S-curve – cumulative (the 'S' shape) | D17: =SUM($D16:D16) -> 0.017037087 | E17: =SUM($D16:E16) -> 0.066987298 | F17: =SUM($D16:F16) -> 0.14644661 | G17: =SUM($D16:G16) -> 0.25 | H17: =SUM($D16:H16) -> 0.37059048 | I17: =SUM($D16:I16) -> 0.5 | J17: =SUM($D16:J16) -> 0.62940952 | K17: =SUM($D16:K16) -> 0.75 | ... O17: =SUM($D16:O16) -> 1
B18: Formulas: Even = 1/n | Front-loaded = 2(n−i+1)/[n(n+1)] | Back-loaded = 2i/[n(n+1)] | S-curve = sin(π(i−0.5)/n) × sin(π/2n) – this exact scaling makes the S-curve total 100%.
B36: B. PRODUCT PHASING – share of each product's sales and construction in each quarter
B37: =IF(INPUTS!$E$88="Yes",INPUTS!$B$88,"Product row 1 (off)") -> Villas
B38: Sales % (curve: as per INPUTS) | C38: =SUM(D38:AQ38) -> 1 | D38: =IF(INPUTS!$E$88="Yes",IF(OR(TIMELINE!D36=0,TIMELINE!$C$35=0),0,IF(INPUTS!$K$88="Upfront",--(TIMELINE!D36=1),IF(INPUTS!$K$88="Even",1/TIMELINE!$C$35,IF(INPUTS!$K$88="Front-loaded",(TIMELINE!$C$35-TIMELINE!D36+1)*2/(TIMELINE!$C$35*(TIMELINE!$C$35+1)),IF(INPUTS!$K$88="Back-loaded",TIMELINE!D36*2/(TIMELINE!$C$35*(TIMELINE!$C$35+1)),IF(INPUTS!$K$88="S-curve",SIN(PI()*(TIMELINE!D36-0.5)/TIMELINE!$C$35)*SIN(PI()/(2*TIMELINE!$C$35)),0)))))),0) -> 0 | E38: =IF(INPUTS!$E$88="Yes",IF(OR(TIMELINE!E36=0,TIMELINE!$C$35=0),0,IF(INPUTS!$K$88="Upfront",--(TIMELINE!E36=1),IF(INPUTS!$K$88="Even",1/TIMELINE!$C$35,IF(INPUTS!$K$88="Front-loaded",(TIMELINE!$C$35-TIMELINE!E36+1)*2/(TIMELINE!$C$35*(TIMELINE!$C$35+1)),IF(INPUTS!$K$88="Back-loaded",TIMELINE!E36*2/(TIMELINE!$C$35*(TIMELINE!$C$35+1)),IF(INPUTS!$K$88="S-curve",SIN(PI()*(TIMELINE!E36-0.5)/TIMELINE!$C$35)*SIN(PI()/(2*TIMELINE!$C$35)),0)))))),0) -> 0 | F38: =IF(INPUTS!$E$88="Yes",IF(OR(TIMELINE!F36=0,TIMELINE!$C$35=0),0,IF(INPUTS!$K$88="Upfront",--(TIMELINE!F36=1),IF(INPUTS!$K$88="Even",1/TIMELINE!$C$35,IF(INPUTS!$K$88="Front-loaded",(TIMELINE!$C$35-TIMELINE!F36+1)*2/(TIMELINE!$C$35*(TIMELINE!$C$35+1)),IF(INPUTS!$K$88="Back-loaded",TIMELINE!F36*2/(TIMELINE!$C$35*(TIMELINE!$C$35+1)),IF(INPUTS!$K$88="S-curve",SIN(PI()*(TIMELINE!F36-0.5)/TIMELINE!$C$35)*SIN(PI()/(2*TIMELINE!$C$35)),0)))))),0) -> 0.22222222 | G38: =IF(INPUTS!$E$88="Yes",IF(OR(TIMELINE!G36=0,TIMELINE!$C$35=0),0,IF(INPUTS!$K$88="Upfront",--(TIMELINE!G36=1),IF(INPUTS!$K$88="Even",1/TIMELINE!$C$35,IF(INPUTS!$K$88="Front-loaded",(TIMELINE!$C$35-TIMELINE!G36+1)*2/(TIMELINE!$C$35*(TIMELINE!$C$35+1)),IF(INPUTS!$K$88="Back-loaded",TIMELINE!G36*2/(TIMELINE!$C$35*(TIMELINE!$C$35+1)),IF(INPUTS!$K$88="S-curve",SIN(PI()*(TIMELINE!G36-0.5)/TIMELINE!$C$35)*SIN(PI()/(2*TIMELINE!$C$35)),0)))))),0) -> 0.19444444 | H38: =IF(INPUTS!$E$88="Yes",IF(OR(TIMELINE!H36=0,TIMELINE!$C$35=0),0,IF(INPUTS!$K$88="Upfront",--(TIMELINE!H36=1),IF(INPUTS!$K$88="Even",1/TIMELINE!$C$35,IF(INPUTS!$K$88="Front-loaded",(TIMELINE!$C$35-TIMELINE!H36+1)*2/(TIMELINE!$C$35*(TIMELINE!$C$35+1)),IF(INPUTS!$K$88="Back-loaded",TIMELINE!H36*2/(TIMELINE!$C$35*(TIMELINE!$C$35+1)),IF(INPUTS!$K$88="S-curve",SIN(PI()*(TIMELINE!H36-0.5)/TIMELINE!$C$35)*SIN(PI()/(2*TIMELINE!$C$35)),0)))))),0) -> 0.16666667 | I38: =IF(INPUTS!$E$88="Yes",IF(OR(TIMELINE!I36=0,TIMELINE!$C$35=0),0,IF(INPUTS!$K$88="Upfront",--(TIMELINE!I36=1),IF(INPUTS!$K$88="Even",1/TIMELINE!$C$35,IF(INPUTS!$K$88="Front-loaded",(TIMELINE!$C$35-TIMELINE!I36+1)*2/(TIMELINE!$C$35*(TIMELINE!$C$35+1)),IF(INPUTS!$K$88="Back-loaded",TIMELINE!I36*2/(TIMELINE!$C$35*(TIMELINE!$C$35+1)),IF(INPUTS!$K$88="S-curve",SIN(PI()*(TIMELINE!I36-0.5)/TIMELINE!$C$35)*SIN(PI()/(2*TIMELINE!$C$35)),0)))))),0) -> 0.13888889 | J38: =IF(INPUTS!$E$88="Yes",IF(OR(TIMELINE!J36=0,TIMELINE!$C$35=0),0,IF(INPUTS!$K$88="Upfront",--(TIMELINE!J36=1),IF(INPUTS!$K$88="Even",1/TIMELINE!$C$35,IF(INPUTS!$K$88="Front-loaded",(TIMELINE!$C$35-TIMELINE!J36+1)*2/(TIMELINE!$C$35*(TIMELINE!$C$35+1)),IF(INPUTS!$K$88="Back-loaded",TIMELINE!J36*2/(TIMELINE!$C$35*(TIMELINE!$C$35+1)),IF(INPUTS!$K$88="S-curve",SIN(PI()*(TIMELINE!J36-0.5)/TIMELINE!$C$35)*SIN(PI()/(2*TIMELINE!$C$35)),0)))))),0) -> 0.11111111 | K38: =IF(INPUTS!$E$88="Yes",IF(OR(TIMELINE!K36=0,TIMELINE!$C$35=0),0,IF(INPUTS!$K$88="Upfront",--(TIMELINE!K36=1),IF(INPUTS!$K$88="Even",1/TIMELINE!$C$35,IF(INPUTS!$K$88="Front-loaded",(TIMELINE!$C$35-TIMELINE!K36+1)*2/(TIMELINE!$C$35*(TIMELINE!$C$35+1)),IF(INPUTS!$K$88="Back-loaded",TIMELINE!K36*2/(TIMELINE!$C$35*(TIMELINE!$C$35+1)),IF(INPUTS!$K$88="S-curve",SIN(PI()*(TIMELINE!K36-0.5)/TIMELINE!$C$35)*SIN(PI()/(2*TIMELINE!$C$35)),0)))))),0) -> 0.083333333 | ... AQ38: =IF(INPUTS!$E$88="Yes",IF(OR(TIMELINE!AQ36=0,TIMELINE!$C$35=0),0,IF(INPUTS!$K$88="Upfront",--(TIMELINE!AQ36=1),IF(INPUTS!$K$88="Even",1/TIMELINE!$C$35,IF(INPUTS!$K$88="Front-loaded",(TIMELINE!$C$35-TIMELINE!AQ36+1)*2/(TIMELINE!$C$35*(TIMELINE!$C$35+1)),IF(INPUTS!$K$88="Back-loaded",TIMELINE!AQ36*2/(TIMELINE!$C$35*(TIMELINE!$C$35+1)),IF(INPUTS!$K$88="S-curve",SIN(PI()*(TIMELINE!AQ36-0.5)/TIMELINE!$C$35)*SIN(PI()/(2*TIMELINE!$C$35)),0)))))),0) -> 0
B39: Sales % – cumulative | D39: =SUM($D38:D38) -> 0 | E39: =SUM($D38:E38) -> 0 | F39: =SUM($D38:F38) -> 0.22222222 | G39: =SUM($D38:G38) -> 0.41666667 | H39: =SUM($D38:H38) -> 0.58333333 | I39: =SUM($D38:I38) -> 0.72222222 | J39: =SUM($D38:J38) -> 0.83333333 | K39: =SUM($D38:K38) -> 0.91666667 | ... AQ39: =SUM($D38:AQ38) -> 1
B40: Construction % (curve: as per INPUTS) | C40: =SUM(D40:AQ40) -> 1 | D40: =IF(INPUTS!$E$88="Yes",IF(OR(TIMELINE!D38=0,TIMELINE!$C$37=0),0,IF(INPUTS!$O$88="Upfront",--(TIMELINE!D38=1),IF(INPUTS!$O$88="Even",1/TIMELINE!$C$37,IF(INPUTS!$O$88="Front-loaded",(TIMELINE!$C$37-TIMELINE!D38+1)*2/(TIMELINE!$C$37*(TIMELINE!$C$37+1)),IF(INPUTS!$O$88="Back-loaded",TIMELINE!D38*2/(TIMELINE!$C$37*(TIMELINE!$C$37+1)),IF(INPUTS!$O$88="S-curve",SIN(PI()*(TIMELINE!D38-0.5)/TIMELINE!$C$37)*SIN(PI()/(2*TIMELINE!$C$37)),0)))))),0) -> 0 | E40: =IF(INPUTS!$E$88="Yes",IF(OR(TIMELINE!E38=0,TIMELINE!$C$37=0),0,IF(INPUTS!$O$88="Upfront",--(TIMELINE!E38=1),IF(INPUTS!$O$88="Even",1/TIMELINE!$C$37,IF(INPUTS!$O$88="Front-loaded",(TIMELINE!$C$37-TIMELINE!E38+1)*2/(TIMELINE!$C$37*(TIMELINE!$C$37+1)),IF(INPUTS!$O$88="Back-loaded",TIMELINE!E38*2/(TIMELINE!$C$37*(TIMELINE!$C$37+1)),IF(INPUTS!$O$88="S-curve",SIN(PI()*(TIMELINE!E38-0.5)/TIMELINE!$C$37)*SIN(PI()/(2*TIMELINE!$C$37)),0)))))),0) -> 0 | F40: =IF(INPUTS!$E$88="Yes",IF(OR(TIMELINE!F38=0,TIMELINE!$C$37=0),0,IF(INPUTS!$O$88="Upfront",--(TIMELINE!F38=1),IF(INPUTS!$O$88="Even",1/TIMELINE!$C$37,IF(INPUTS!$O$88="Front-loaded",(TIMELINE!$C$37-TIMELINE!F38+1)*2/(TIMELINE!$C$37*(TIMELINE!$C$37+1)),IF(INPUTS!$O$88="Back-loaded",TIMELINE!F38*2/(TIMELINE!$C$37*(TIMELINE!$C$37+1)),IF(INPUTS!$O$88="S-curve",SIN(PI()*(TIMELINE!F38-0.5)/TIMELINE!$C$37)*SIN(PI()/(2*TIMELINE!$C$37)),0)))))),0) -> 0 | G40: =IF(INPUTS!$E$88="Yes",IF(OR(TIMELINE!G38=0,TIMELINE!$C$37=0),0,IF(INPUTS!$O$88="Upfront",--(TIMELINE!G38=1),IF(INPUTS!$O$88="Even",1/TIMELINE!$C$37,IF(INPUTS!$O$88="Front-loaded",(TIMELINE!$C$37-TIMELINE!G38+1)*2/(TIMELINE!$C$37*(TIMELINE!$C$37+1)),IF(INPUTS!$O$88="Back-loaded",TIMELINE!G38*2/(TIMELINE!$C$37*(TIMELINE!$C$37+1)),IF(INPUTS!$O$88="S-curve",SIN(PI()*(TIMELINE!G38-0.5)/TIMELINE!$C$37)*SIN(PI()/(2*TIMELINE!$C$37)),0)))))),0) -> 0.017037087 | H40: =IF(INPUTS!$E$88="Yes",IF(OR(TIMELINE!H38=0,TIMELINE!$C$37=0),0,IF(INPUTS!$O$88="Upfront",--(TIMELINE!H38=1),IF(INPUTS!$O$88="Even",1/TIMELINE!$C$37,IF(INPUTS!$O$88="Front-loaded",(TIMELINE!$C$37-TIMELINE!H38+1)*2/(TIMELINE!$C$37*(TIMELINE!$C$37+1)),IF(INPUTS!$O$88="Back-loaded",TIMELINE!H38*2/(TIMELINE!$C$37*(TIMELINE!$C$37+1)),IF(INPUTS!$O$88="S-curve",SIN(PI()*(TIMELINE!H38-0.5)/TIMELINE!$C$37)*SIN(PI()/(2*TIMELINE!$C$37)),0)))))),0) -> 0.049950211 | I40: =IF(INPUTS!$E$88="Yes",IF(OR(TIMELINE!I38=0,TIMELINE!$C$37=0),0,IF(INPUTS!$O$88="Upfront",--(TIMELINE!I38=1),IF(INPUTS!$O$88="Even",1/TIMELINE!$C$37,IF(INPUTS!$O$88="Front-loaded",(TIMELINE!$C$37-TIMELINE!I38+1)*2/(TIMELINE!$C$37*(TIMELINE!$C$37+1)),IF(INPUTS!$O$88="Back-loaded",TIMELINE!I38*2/(TIMELINE!$C$37*(TIMELINE!$C$37+1)),IF(INPUTS!$O$88="S-curve",SIN(PI()*(TIMELINE!I38-0.5)/TIMELINE!$C$37)*SIN(PI()/(2*TIMELINE!$C$37)),0)))))),0) -> 0.079459311 | J40: =IF(INPUTS!$E$88="Yes",IF(OR(TIMELINE!J38=0,TIMELINE!$C$37=0),0,IF(INPUTS!$O$88="Upfront",--(TIMELINE!J38=1),IF(INPUTS!$O$88="Even",1/TIMELINE!$C$37,IF(INPUTS!$O$88="Front-loaded",(TIMELINE!$C$37-TIMELINE!J38+1)*2/(TIMELINE!$C$37*(TIMELINE!$C$37+1)),IF(INPUTS!$O$88="Back-loaded",TIMELINE!J38*2/(TIMELINE!$C$37*(TIMELINE!$C$37+1)),IF(INPUTS!$O$88="S-curve",SIN(PI()*(TIMELINE!J38-0.5)/TIMELINE!$C$37)*SIN(PI()/(2*TIMELINE!$C$37)),0)))))),0) -> 0.10355339 | K40: =IF(INPUTS!$E$88="Yes",IF(OR(TIMELINE!K38=0,TIMELINE!$C$37=0),0,IF(INPUTS!$O$88="Upfront",--(TIMELINE!K38=1),IF(INPUTS!$O$88="Even",1/TIMELINE!$C$37,IF(INPUTS!$O$88="Front-loaded",(TIMELINE!$C$37-TIMELINE!K38+1)*2/(TIMELINE!$C$37*(TIMELINE!$C$37+1)),IF(INPUTS!$O$88="Back-loaded",TIMELINE!K38*2/(TIMELINE!$C$37*(TIMELINE!$C$37+1)),IF(INPUTS!$O$88="S-curve",SIN(PI()*(TIMELINE!K38-0.5)/TIMELINE!$C$37)*SIN(PI()/(2*TIMELINE!$C$37)),0)))))),0) -> 0.12059048 | ... AQ40: =IF(INPUTS!$E$88="Yes",IF(OR(TIMELINE!AQ38=0,TIMELINE!$C$37=0),0,IF(INPUTS!$O$88="Upfront",--(TIMELINE!AQ38=1),IF(INPUTS!$O$88="Even",1/TIMELINE!$C$37,IF(INPUTS!$O$88="Front-loaded",(TIMELINE!$C$37-TIMELINE!AQ38+1)*2/(TIMELINE!$C$37*(TIMELINE!$C$37+1)),IF(INPUTS!$O$88="Back-loaded",TIMELINE!AQ38*2/(TIMELINE!$C$37*(TIMELINE!$C$37+1)),IF(INPUTS!$O$88="S-curve",SIN(PI()*(TIMELINE!AQ38-0.5)/TIMELINE!$C$37)*SIN(PI()/(2*TIMELINE!$C$37)),0)))))),0) -> 0
B41: Construction % – cumulative (drives CLP in Step 4) | D41: =SUM($D40:D40) -> 0 | E41: =SUM($D40:E40) -> 0 | F41: =SUM($D40:F40) -> 0 | G41: =SUM($D40:G40) -> 0.017037087 | H41: =SUM($D40:H40) -> 0.066987298 | I41: =SUM($D40:I40) -> 0.14644661 | J41: =SUM($D40:J40) -> 0.25 | K41: =SUM($D40:K40) -> 0.37059048 | ... AQ41: =SUM($D40:AQ40) -> 1
B42: Check (each must total 100%) | C42: =IF(NOT(INPUTS!$E$88="Yes"),"Off",IF(AND(ABS(C38-1)<0.000000001,ABS(C40-1)<0.000000001,ABS(AQ41-1)<0.000000001),"OK","ERROR")) -> OK
B43: =IF(INPUTS!$E$89="Yes",INPUTS!$B$89,"Product row 2 (off)") -> Apartments – Towers A & B
B44: Sales % (curve: as per INPUTS) | C44: =SUM(D44:AQ44) -> 1 | D44: =IF(INPUTS!$E$89="Yes",IF(OR(TIMELINE!D43=0,TIMELINE!$C$42=0),0,IF(INPUTS!$K$89="Upfront",--(TIMELINE!D43=1),IF(INPUTS!$K$89="Even",1/TIMELINE!$C$42,IF(INPUTS!$K$89="Front-loaded",(TIMELINE!$C$42-TIMELINE!D43+1)*2/(TIMELINE!$C$42*(TIMELINE!$C$42+1)),IF(INPUTS!$K$89="Back-loaded",TIMELINE!D43*2/(TIMELINE!$C$42*(TIMELINE!$C$42+1)),IF(INPUTS!$K$89="S-curve",SIN(PI()*(TIMELINE!D43-0.5)/TIMELINE!$C$42)*SIN(PI()/(2*TIMELINE!$C$42)),0)))))),0) -> 0 | E44: =IF(INPUTS!$E$89="Yes",IF(OR(TIMELINE!E43=0,TIMELINE!$C$42=0),0,IF(INPUTS!$K$89="Upfront",--(TIMELINE!E43=1),IF(INPUTS!$K$89="Even",1/TIMELINE!$C$42,IF(INPUTS!$K$89="Front-loaded",(TIMELINE!$C$42-TIMELINE!E43+1)*2/(TIMELINE!$C$42*(TIMELINE!$C$42+1)),IF(INPUTS!$K$89="Back-loaded",TIMELINE!E43*2/(TIMELINE!$C$42*(TIMELINE!$C$42+1)),IF(INPUTS!$K$89="S-curve",SIN(PI()*(TIMELINE!E43-0.5)/TIMELINE!$C$42)*SIN(PI()/(2*TIMELINE!$C$42)),0)))))),0) -> 0 | F44: =IF(INPUTS!$E$89="Yes",IF(OR(TIMELINE!F43=0,TIMELINE!$C$42=0),0,IF(INPUTS!$K$89="Upfront",--(TIMELINE!F43=1),IF(INPUTS!$K$89="Even",1/TIMELINE!$C$42,IF(INPUTS!$K$89="Front-loaded",(TIMELINE!$C$42-TIMELINE!F43+1)*2/(TIMELINE!$C$42*(TIMELINE!$C$42+1)),IF(INPUTS!$K$89="Back-loaded",TIMELINE!F43*2/(TIMELINE!$C$42*(TIMELINE!$C$42+1)),IF(INPUTS!$K$89="S-curve",SIN(PI()*(TIMELINE!F43-0.5)/TIMELINE!$C$42)*SIN(PI()/(2*TIMELINE!$C$42)),0)))))),0) -> 0 | G44: =IF(INPUTS!$E$89="Yes",IF(OR(TIMELINE!G43=0,TIMELINE!$C$42=0),0,IF(INPUTS!$K$89="Upfront",--(TIMELINE!G43=1),IF(INPUTS!$K$89="Even",1/TIMELINE!$C$42,IF(INPUTS!$K$89="Front-loaded",(TIMELINE!$C$42-TIMELINE!G43+1)*2/(TIMELINE!$C$42*(TIMELINE!$C$42+1)),IF(INPUTS!$K$89="Back-loaded",TIMELINE!G43*2/(TIMELINE!$C$42*(TIMELINE!$C$42+1)),IF(INPUTS!$K$89="S-curve",SIN(PI()*(TIMELINE!G43-0.5)/TIMELINE!$C$42)*SIN(PI()/(2*TIMELINE!$C$42)),0)))))),0) -> 0.083333333 | H44: =IF(INPUTS!$E$89="Yes",IF(OR(TIMELINE!H43=0,TIMELINE!$C$42=0),0,IF(INPUTS!$K$89="Upfront",--(TIMELINE!H43=1),IF(INPUTS!$K$89="Even",1/TIMELINE!$C$42,IF(INPUTS!$K$89="Front-loaded",(TIMELINE!$C$42-TIMELINE!H43+1)*2/(TIMELINE!$C$42*(TIMELINE!$C$42+1)),IF(INPUTS!$K$89="Back-loaded",TIMELINE!H43*2/(TIMELINE!$C$42*(TIMELINE!$C$42+1)),IF(INPUTS!$K$89="S-curve",SIN(PI()*(TIMELINE!H43-0.5)/TIMELINE!$C$42)*SIN(PI()/(2*TIMELINE!$C$42)),0)))))),0) -> 0.083333333 | I44: =IF(INPUTS!$E$89="Yes",IF(OR(TIMELINE!I43=0,TIMELINE!$C$42=0),0,IF(INPUTS!$K$89="Upfront",--(TIMELINE!I43=1),IF(INPUTS!$K$89="Even",1/TIMELINE!$C$42,IF(INPUTS!$K$89="Front-loaded",(TIMELINE!$C$42-TIMELINE!I43+1)*2/(TIMELINE!$C$42*(TIMELINE!$C$42+1)),IF(INPUTS!$K$89="Back-loaded",TIMELINE!I43*2/(TIMELINE!$C$42*(TIMELINE!$C$42+1)),IF(INPUTS!$K$89="S-curve",SIN(PI()*(TIMELINE!I43-0.5)/TIMELINE!$C$42)*SIN(PI()/(2*TIMELINE!$C$42)),0)))))),0) -> 0.083333333 | J44: =IF(INPUTS!$E$89="Yes",IF(OR(TIMELINE!J43=0,TIMELINE!$C$42=0),0,IF(INPUTS!$K$89="Upfront",--(TIMELINE!J43=1),IF(INPUTS!$K$89="Even",1/TIMELINE!$C$42,IF(INPUTS!$K$89="Front-loaded",(TIMELINE!$C$42-TIMELINE!J43+1)*2/(TIMELINE!$C$42*(TIMELINE!$C$42+1)),IF(INPUTS!$K$89="Back-loaded",TIMELINE!J43*2/(TIMELINE!$C$42*(TIMELINE!$C$42+1)),IF(INPUTS!$K$89="S-curve",SIN(PI()*(TIMELINE!J43-0.5)/TIMELINE!$C$42)*SIN(PI()/(2*TIMELINE!$C$42)),0)))))),0) -> 0.083333333 | K44: =IF(INPUTS!$E$89="Yes",IF(OR(TIMELINE!K43=0,TIMELINE!$C$42=0),0,IF(INPUTS!$K$89="Upfront",--(TIMELINE!K43=1),IF(INPUTS!$K$89="Even",1/TIMELINE!$C$42,IF(INPUTS!$K$89="Front-loaded",(TIMELINE!$C$42-TIMELINE!K43+1)*2/(TIMELINE!$C$42*(TIMELINE!$C$42+1)),IF(INPUTS!$K$89="Back-loaded",TIMELINE!K43*2/(TIMELINE!$C$42*(TIMELINE!$C$42+1)),IF(INPUTS!$K$89="S-curve",SIN(PI()*(TIMELINE!K43-0.5)/TIMELINE!$C$42)*SIN(PI()/(2*TIMELINE!$C$42)),0)))))),0) -> 0.083333333 | ... AQ44: =IF(INPUTS!$E$89="Yes",IF(OR(TIMELINE!AQ43=0,TIMELINE!$C$42=0),0,IF(INPUTS!$K$89="Upfront",--(TIMELINE!AQ43=1),IF(INPUTS!$K$89="Even",1/TIMELINE!$C$42,IF(INPUTS!$K$89="Front-loaded",(TIMELINE!$C$42-TIMELINE!AQ43+1)*2/(TIMELINE!$C$42*(TIMELINE!$C$42+1)),IF(INPUTS!$K$89="Back-loaded",TIMELINE!AQ43*2/(TIMELINE!$C$42*(TIMELINE!$C$42+1)),IF(INPUTS!$K$89="S-curve",SIN(PI()*(TIMELINE!AQ43-0.5)/TIMELINE!$C$42)*SIN(PI()/(2*TIMELINE!$C$42)),0)))))),0) -> 0
B45: Sales % – cumulative | D45: =SUM($D44:D44) -> 0 | E45: =SUM($D44:E44) -> 0 | F45: =SUM($D44:F44) -> 0 | G45: =SUM($D44:G44) -> 0.083333333 | H45: =SUM($D44:H44) -> 0.16666667 | I45: =SUM($D44:I44) -> 0.25 | J45: =SUM($D44:J44) -> 0.33333333 | K45: =SUM($D44:K44) -> 0.41666667 | ... AQ45: =SUM($D44:AQ44) -> 1
B46: Construction % (curve: as per INPUTS) | C46: =SUM(D46:AQ46) -> 1 | D46: =IF(INPUTS!$E$89="Yes",IF(OR(TIMELINE!D45=0,TIMELINE!$C$44=0),0,IF(INPUTS!$O$89="Upfront",--(TIMELINE!D45=1),IF(INPUTS!$O$89="Even",1/TIMELINE!$C$44,IF(INPUTS!$O$89="Front-loaded",(TIMELINE!$C$44-TIMELINE!D45+1)*2/(TIMELINE!$C$44*(TIMELINE!$C$44+1)),IF(INPUTS!$O$89="Back-loaded",TIMELINE!D45*2/(TIMELINE!$C$44*(TIMELINE!$C$44+1)),IF(INPUTS!$O$89="S-curve",SIN(PI()*(TIMELINE!D45-0.5)/TIMELINE!$C$44)*SIN(PI()/(2*TIMELINE!$C$44)),0)))))),0) -> 0 | E46: =IF(INPUTS!$E$89="Yes",IF(OR(TIMELINE!E45=0,TIMELINE!$C$44=0),0,IF(INPUTS!$O$89="Upfront",--(TIMELINE!E45=1),IF(INPUTS!$O$89="Even",1/TIMELINE!$C$44,IF(INPUTS!$O$89="Front-loaded",(TIMELINE!$C$44-TIMELINE!E45+1)*2/(TIMELINE!$C$44*(TIMELINE!$C$44+1)),IF(INPUTS!$O$89="Back-loaded",TIMELINE!E45*2/(TIMELINE!$C$44*(TIMELINE!$C$44+1)),IF(INPUTS!$O$89="S-curve",SIN(PI()*(TIMELINE!E45-0.5)/TIMELINE!$C$44)*SIN(PI()/(2*TIMELINE!$C$44)),0)))))),0) -> 0 | F46: =IF(INPUTS!$E$89="Yes",IF(OR(TIMELINE!F45=0,TIMELINE!$C$44=0),0,IF(INPUTS!$O$89="Upfront",--(TIMELINE!F45=1),IF(INPUTS!$O$89="Even",1/TIMELINE!$C$44,IF(INPUTS!$O$89="Front-loaded",(TIMELINE!$C$44-TIMELINE!F45+1)*2/(TIMELINE!$C$44*(TIMELINE!$C$44+1)),IF(INPUTS!$O$89="Back-loaded",TIMELINE!F45*2/(TIMELINE!$C$44*(TIMELINE!$C$44+1)),IF(INPUTS!$O$89="S-curve",SIN(PI()*(TIMELINE!F45-0.5)/TIMELINE!$C$44)*SIN(PI()/(2*TIMELINE!$C$44)),0)))))),0) -> 0 | G46: =IF(INPUTS!$E$89="Yes",IF(OR(TIMELINE!G45=0,TIMELINE!$C$44=0),0,IF(INPUTS!$O$89="Upfront",--(TIMELINE!G45=1),IF(INPUTS!$O$89="Even",1/TIMELINE!$C$44,IF(INPUTS!$O$89="Front-loaded",(TIMELINE!$C$44-TIMELINE!G45+1)*2/(TIMELINE!$C$44*(TIMELINE!$C$44+1)),IF(INPUTS!$O$89="Back-loaded",TIMELINE!G45*2/(TIMELINE!$C$44*(TIMELINE!$C$44+1)),IF(INPUTS!$O$89="S-curve",SIN(PI()*(TIMELINE!G45-0.5)/TIMELINE!$C$44)*SIN(PI()/(2*TIMELINE!$C$44)),0)))))),0) -> 0 | H46: =IF(INPUTS!$E$89="Yes",IF(OR(TIMELINE!H45=0,TIMELINE!$C$44=0),0,IF(INPUTS!$O$89="Upfront",--(TIMELINE!H45=1),IF(INPUTS!$O$89="Even",1/TIMELINE!$C$44,IF(INPUTS!$O$89="Front-loaded",(TIMELINE!$C$44-TIMELINE!H45+1)*2/(TIMELINE!$C$44*(TIMELINE!$C$44+1)),IF(INPUTS!$O$89="Back-loaded",TIMELINE!H45*2/(TIMELINE!$C$44*(TIMELINE!$C$44+1)),IF(INPUTS!$O$89="S-curve",SIN(PI()*(TIMELINE!H45-0.5)/TIMELINE!$C$44)*SIN(PI()/(2*TIMELINE!$C$44)),0)))))),0) -> 0.0096073598 | I46: =IF(INPUTS!$E$89="Yes",IF(OR(TIMELINE!I45=0,TIMELINE!$C$44=0),0,IF(INPUTS!$O$89="Upfront",--(TIMELINE!I45=1),IF(INPUTS!$O$89="Even",1/TIMELINE!$C$44,IF(INPUTS!$O$89="Front-loaded",(TIMELINE!$C$44-TIMELINE!I45+1)*2/(TIMELINE!$C$44*(TIMELINE!$C$44+1)),IF(INPUTS!$O$89="Back-loaded",TIMELINE!I45*2/(TIMELINE!$C$44*(TIMELINE!$C$44+1)),IF(INPUTS!$O$89="S-curve",SIN(PI()*(TIMELINE!I45-0.5)/TIMELINE!$C$44)*SIN(PI()/(2*TIMELINE!$C$44)),0)))))),0) -> 0.028452874 | J46: =IF(INPUTS!$E$89="Yes",IF(OR(TIMELINE!J45=0,TIMELINE!$C$44=0),0,IF(INPUTS!$O$89="Upfront",--(TIMELINE!J45=1),IF(INPUTS!$O$89="Even",1/TIMELINE!$C$44,IF(INPUTS!$O$89="Front-loaded",(TIMELINE!$C$44-TIMELINE!J45+1)*2/(TIMELINE!$C$44*(TIMELINE!$C$44+1)),IF(INPUTS!$O$89="Back-loaded",TIMELINE!J45*2/(TIMELINE!$C$44*(TIMELINE!$C$44+1)),IF(INPUTS!$O$89="S-curve",SIN(PI()*(TIMELINE!J45-0.5)/TIMELINE!$C$44)*SIN(PI()/(2*TIMELINE!$C$44)),0)))))),0) -> 0.04620496 | K46: =IF(INPUTS!$E$89="Yes",IF(OR(TIMELINE!K45=0,TIMELINE!$C$44=0),0,IF(INPUTS!$O$89="Upfront",--(TIMELINE!K45=1),IF(INPUTS!$O$89="Even",1/TIMELINE!$C$44,IF(INPUTS!$O$89="Front-loaded",(TIMELINE!$C$44-TIMELINE!K45+1)*2/(TIMELINE!$C$44*(TIMELINE!$C$44+1)),IF(INPUTS!$O$89="Back-loaded",TIMELINE!K45*2/(TIMELINE!$C$44*(TIMELINE!$C$44+1)),IF(INPUTS!$O$89="S-curve",SIN(PI()*(TIMELINE!K45-0.5)/TIMELINE!$C$44)*SIN(PI()/(2*TIMELINE!$C$44)),0)))))),0) -> 0.062181416 | ... AQ46: =IF(INPUTS!$E$89="Yes",IF(OR(TIMELINE!AQ45=0,TIMELINE!$C$44=0),0,IF(INPUTS!$O$89="Upfront",--(TIMELINE!AQ45=1),IF(INPUTS!$O$89="Even",1/TIMELINE!$C$44,IF(INPUTS!$O$89="Front-loaded",(TIMELINE!$C$44-TIMELINE!AQ45+1)*2/(TIMELINE!$C$44*(TIMELINE!$C$44+1)),IF(INPUTS!$O$89="Back-loaded",TIMELINE!AQ45*2/(TIMELINE!$C$44*(TIMELINE!$C$44+1)),IF(INPUTS!$O$89="S-curve",SIN(PI()*(TIMELINE!AQ45-0.5)/TIMELINE!$C$44)*SIN(PI()/(2*TIMELINE!$C$44)),0)))))),0) -> 0
B47: Construction % – cumulative (drives CLP in Step 4) | D47: =SUM($D46:D46) -> 0 | E47: =SUM($D46:E46) -> 0 | F47: =SUM($D46:F46) -> 0 | G47: =SUM($D46:G46) -> 0 | H47: =SUM($D46:H46) -> 0.0096073598 | I47: =SUM($D46:I46) -> 0.038060234 | J47: =SUM($D46:J46) -> 0.084265194 | K47: =SUM($D46:K46) -> 0.14644661 | ... AQ47: =SUM($D46:AQ46) -> 1
B48: Check (each must total 100%) | C48: =IF(NOT(INPUTS!$E$89="Yes"),"Off",IF(AND(ABS(C44-1)<0.000000001,ABS(C46-1)<0.000000001,ABS(AQ47-1)<0.000000001),"OK","ERROR")) -> OK
B49: =IF(INPUTS!$E$90="Yes",INPUTS!$B$90,"Product row 3 (off)") -> Studios
B50: Sales % (curve: as per INPUTS) | C50: =SUM(D50:AQ50) -> 1 | D50: =IF(INPUTS!$E$90="Yes",IF(OR(TIMELINE!D50=0,TIMELINE!$C$49=0),0,IF(INPUTS!$K$90="Upfront",--(TIMELINE!D50=1),IF(INPUTS!$K$90="Even",1/TIMELINE!$C$49,IF(INPUTS!$K$90="Front-loaded",(TIMELINE!$C$49-TIMELINE!D50+1)*2/(TIMELINE!$C$49*(TIMELINE!$C$49+1)),IF(INPUTS!$K$90="Back-loaded",TIMELINE!D50*2/(TIMELINE!$C$49*(TIMELINE!$C$49+1)),IF(INPUTS!$K$90="S-curve",SIN(PI()*(TIMELINE!D50-0.5)/TIMELINE!$C$49)*SIN(PI()/(2*TIMELINE!$C$49)),0)))))),0) -> 0 | E50: =IF(INPUTS!$E$90="Yes",IF(OR(TIMELINE!E50=0,TIMELINE!$C$49=0),0,IF(INPUTS!$K$90="Upfront",--(TIMELINE!E50=1),IF(INPUTS!$K$90="Even",1/TIMELINE!$C$49,IF(INPUTS!$K$90="Front-loaded",(TIMELINE!$C$49-TIMELINE!E50+1)*2/(TIMELINE!$C$49*(TIMELINE!$C$49+1)),IF(INPUTS!$K$90="Back-loaded",TIMELINE!E50*2/(TIMELINE!$C$49*(TIMELINE!$C$49+1)),IF(INPUTS!$K$90="S-curve",SIN(PI()*(TIMELINE!E50-0.5)/TIMELINE!$C$49)*SIN(PI()/(2*TIMELINE!$C$49)),0)))))),0) -> 0 | F50: =IF(INPUTS!$E$90="Yes",IF(OR(TIMELINE!F50=0,TIMELINE!$C$49=0),0,IF(INPUTS!$K$90="Upfront",--(TIMELINE!F50=1),IF(INPUTS!$K$90="Even",1/TIMELINE!$C$49,IF(INPUTS!$K$90="Front-loaded",(TIMELINE!$C$49-TIMELINE!F50+1)*2/(TIMELINE!$C$49*(TIMELINE!$C$49+1)),IF(INPUTS!$K$90="Back-loaded",TIMELINE!F50*2/(TIMELINE!$C$49*(TIMELINE!$C$49+1)),IF(INPUTS!$K$90="S-curve",SIN(PI()*(TIMELINE!F50-0.5)/TIMELINE!$C$49)*SIN(PI()/(2*TIMELINE!$C$49)),0)))))),0) -> 0 | G50: =IF(INPUTS!$E$90="Yes",IF(OR(TIMELINE!G50=0,TIMELINE!$C$49=0),0,IF(INPUTS!$K$90="Upfront",--(TIMELINE!G50=1),IF(INPUTS!$K$90="Even",1/TIMELINE!$C$49,IF(INPUTS!$K$90="Front-loaded",(TIMELINE!$C$49-TIMELINE!G50+1)*2/(TIMELINE!$C$49*(TIMELINE!$C$49+1)),IF(INPUTS!$K$90="Back-loaded",TIMELINE!G50*2/(TIMELINE!$C$49*(TIMELINE!$C$49+1)),IF(INPUTS!$K$90="S-curve",SIN(PI()*(TIMELINE!G50-0.5)/TIMELINE!$C$49)*SIN(PI()/(2*TIMELINE!$C$49)),0)))))),0) -> 0 | H50: =IF(INPUTS!$E$90="Yes",IF(OR(TIMELINE!H50=0,TIMELINE!$C$49=0),0,IF(INPUTS!$K$90="Upfront",--(TIMELINE!H50=1),IF(INPUTS!$K$90="Even",1/TIMELINE!$C$49,IF(INPUTS!$K$90="Front-loaded",(TIMELINE!$C$49-TIMELINE!H50+1)*2/(TIMELINE!$C$49*(TIMELINE!$C$49+1)),IF(INPUTS!$K$90="Back-loaded",TIMELINE!H50*2/(TIMELINE!$C$49*(TIMELINE!$C$49+1)),IF(INPUTS!$K$90="S-curve",SIN(PI()*(TIMELINE!H50-0.5)/TIMELINE!$C$49)*SIN(PI()/(2*TIMELINE!$C$49)),0)))))),0) -> 0 | I50: =IF(INPUTS!$E$90="Yes",IF(OR(TIMELINE!I50=0,TIMELINE!$C$49=0),0,IF(INPUTS!$K$90="Upfront",--(TIMELINE!I50=1),IF(INPUTS!$K$90="Even",1/TIMELINE!$C$49,IF(INPUTS!$K$90="Front-loaded",(TIMELINE!$C$49-TIMELINE!I50+1)*2/(TIMELINE!$C$49*(TIMELINE!$C$49+1)),IF(INPUTS!$K$90="Back-loaded",TIMELINE!I50*2/(TIMELINE!$C$49*(TIMELINE!$C$49+1)),IF(INPUTS!$K$90="S-curve",SIN(PI()*(TIMELINE!I50-0.5)/TIMELINE!$C$49)*SIN(PI()/(2*TIMELINE!$C$49)),0)))))),0) -> 0.125 | J50: =IF(INPUTS!$E$90="Yes",IF(OR(TIMELINE!J50=0,TIMELINE!$C$49=0),0,IF(INPUTS!$K$90="Upfront",--(TIMELINE!J50=1),IF(INPUTS!$K$90="Even",1/TIMELINE!$C$49,IF(INPUTS!$K$90="Front-loaded",(TIMELINE!$C$49-TIMELINE!J50+1)*2/(TIMELINE!$C$49*(TIMELINE!$C$49+1)),IF(INPUTS!$K$90="Back-loaded",TIMELINE!J50*2/(TIMELINE!$C$49*(TIMELINE!$C$49+1)),IF(INPUTS!$K$90="S-curve",SIN(PI()*(TIMELINE!J50-0.5)/TIMELINE!$C$49)*SIN(PI()/(2*TIMELINE!$C$49)),0)))))),0) -> 0.125 | K50: =IF(INPUTS!$E$90="Yes",IF(OR(TIMELINE!K50=0,TIMELINE!$C$49=0),0,IF(INPUTS!$K$90="Upfront",--(TIMELINE!K50=1),IF(INPUTS!$K$90="Even",1/TIMELINE!$C$49,IF(INPUTS!$K$90="Front-loaded",(TIMELINE!$C$49-TIMELINE!K50+1)*2/(TIMELINE!$C$49*(TIMELINE!$C$49+1)),IF(INPUTS!$K$90="Back-loaded",TIMELINE!K50*2/(TIMELINE!$C$49*(TIMELINE!$C$49+1)),IF(INPUTS!$K$90="S-curve",SIN(PI()*(TIMELINE!K50-0.5)/TIMELINE!$C$49)*SIN(PI()/(2*TIMELINE!$C$49)),0)))))),0) -> 0.125 | ... AQ50: =IF(INPUTS!$E$90="Yes",IF(OR(TIMELINE!AQ50=0,TIMELINE!$C$49=0),0,IF(INPUTS!$K$90="Upfront",--(TIMELINE!AQ50=1),IF(INPUTS!$K$90="Even",1/TIMELINE!$C$49,IF(INPUTS!$K$90="Front-loaded",(TIMELINE!$C$49-TIMELINE!AQ50+1)*2/(TIMELINE!$C$49*(TIMELINE!$C$49+1)),IF(INPUTS!$K$90="Back-loaded",TIMELINE!AQ50*2/(TIMELINE!$C$49*(TIMELINE!$C$49+1)),IF(INPUTS!$K$90="S-curve",SIN(PI()*(TIMELINE!AQ50-0.5)/TIMELINE!$C$49)*SIN(PI()/(2*TIMELINE!$C$49)),0)))))),0) -> 0
B51: Sales % – cumulative | D51: =SUM($D50:D50) -> 0 | E51: =SUM($D50:E50) -> 0 | F51: =SUM($D50:F50) -> 0 | G51: =SUM($D50:G50) -> 0 | H51: =SUM($D50:H50) -> 0 | I51: =SUM($D50:I50) -> 0.125 | J51: =SUM($D50:J50) -> 0.25 | K51: =SUM($D50:K50) -> 0.375 | ... AQ51: =SUM($D50:AQ50) -> 1
B52: Construction % (curve: as per INPUTS) | C52: =SUM(D52:AQ52) -> 1 | D52: =IF(INPUTS!$E$90="Yes",IF(OR(TIMELINE!D52=0,TIMELINE!$C$51=0),0,IF(INPUTS!$O$90="Upfront",--(TIMELINE!D52=1),IF(INPUTS!$O$90="Even",1/TIMELINE!$C$51,IF(INPUTS!$O$90="Front-loaded",(TIMELINE!$C$51-TIMELINE!D52+1)*2/(TIMELINE!$C$51*(TIMELINE!$C$51+1)),IF(INPUTS!$O$90="Back-loaded",TIMELINE!D52*2/(TIMELINE!$C$51*(TIMELINE!$C$51+1)),IF(INPUTS!$O$90="S-curve",SIN(PI()*(TIMELINE!D52-0.5)/TIMELINE!$C$51)*SIN(PI()/(2*TIMELINE!$C$51)),0)))))),0) -> 0 | E52: =IF(INPUTS!$E$90="Yes",IF(OR(TIMELINE!E52=0,TIMELINE!$C$51=0),0,IF(INPUTS!$O$90="Upfront",--(TIMELINE!E52=1),IF(INPUTS!$O$90="Even",1/TIMELINE!$C$51,IF(INPUTS!$O$90="Front-loaded",(TIMELINE!$C$51-TIMELINE!E52+1)*2/(TIMELINE!$C$51*(TIMELINE!$C$51+1)),IF(INPUTS!$O$90="Back-loaded",TIMELINE!E52*2/(TIMELINE!$C$51*(TIMELINE!$C$51+1)),IF(INPUTS!$O$90="S-curve",SIN(PI()*(TIMELINE!E52-0.5)/TIMELINE!$C$51)*SIN(PI()/(2*TIMELINE!$C$51)),0)))))),0) -> 0 | F52: =IF(INPUTS!$E$90="Yes",IF(OR(TIMELINE!F52=0,TIMELINE!$C$51=0),0,IF(INPUTS!$O$90="Upfront",--(TIMELINE!F52=1),IF(INPUTS!$O$90="Even",1/TIMELINE!$C$51,IF(INPUTS!$O$90="Front-loaded",(TIMELINE!$C$51-TIMELINE!F52+1)*2/(TIMELINE!$C$51*(TIMELINE!$C$51+1)),IF(INPUTS!$O$90="Back-loaded",TIMELINE!F52*2/(TIMELINE!$C$51*(TIMELINE!$C$51+1)),IF(INPUTS!$O$90="S-curve",SIN(PI()*(TIMELINE!F52-0.5)/TIMELINE!$C$51)*SIN(PI()/(2*TIMELINE!$C$51)),0)))))),0) -> 0 | G52: =IF(INPUTS!$E$90="Yes",IF(OR(TIMELINE!G52=0,TIMELINE!$C$51=0),0,IF(INPUTS!$O$90="Upfront",--(TIMELINE!G52=1),IF(INPUTS!$O$90="Even",1/TIMELINE!$C$51,IF(INPUTS!$O$90="Front-loaded",(TIMELINE!$C$51-TIMELINE!G52+1)*2/(TIMELINE!$C$51*(TIMELINE!$C$51+1)),IF(INPUTS!$O$90="Back-loaded",TIMELINE!G52*2/(TIMELINE!$C$51*(TIMELINE!$C$51+1)),IF(INPUTS!$O$90="S-curve",SIN(PI()*(TIMELINE!G52-0.5)/TIMELINE!$C$51)*SIN(PI()/(2*TIMELINE!$C$51)),0)))))),0) -> 0 | H52: =IF(INPUTS!$E$90="Yes",IF(OR(TIMELINE!H52=0,TIMELINE!$C$51=0),0,IF(INPUTS!$O$90="Upfront",--(TIMELINE!H52=1),IF(INPUTS!$O$90="Even",1/TIMELINE!$C$51,IF(INPUTS!$O$90="Front-loaded",(TIMELINE!$C$51-TIMELINE!H52+1)*2/(TIMELINE!$C$51*(TIMELINE!$C$51+1)),IF(INPUTS!$O$90="Back-loaded",TIMELINE!H52*2/(TIMELINE!$C$51*(TIMELINE!$C$51+1)),IF(INPUTS!$O$90="S-curve",SIN(PI()*(TIMELINE!H52-0.5)/TIMELINE!$C$51)*SIN(PI()/(2*TIMELINE!$C$51)),0)))))),0) -> 0 | I52: =IF(INPUTS!$E$90="Yes",IF(OR(TIMELINE!I52=0,TIMELINE!$C$51=0),0,IF(INPUTS!$O$90="Upfront",--(TIMELINE!I52=1),IF(INPUTS!$O$90="Even",1/TIMELINE!$C$51,IF(INPUTS!$O$90="Front-loaded",(TIMELINE!$C$51-TIMELINE!I52+1)*2/(TIMELINE!$C$51*(TIMELINE!$C$51+1)),IF(INPUTS!$O$90="Back-loaded",TIMELINE!I52*2/(TIMELINE!$C$51*(TIMELINE!$C$51+1)),IF(INPUTS!$O$90="S-curve",SIN(PI()*(TIMELINE!I52-0.5)/TIMELINE!$C$51)*SIN(PI()/(2*TIMELINE!$C$51)),0)))))),0) -> 0.017037087 | J52: =IF(INPUTS!$E$90="Yes",IF(OR(TIMELINE!J52=0,TIMELINE!$C$51=0),0,IF(INPUTS!$O$90="Upfront",--(TIMELINE!J52=1),IF(INPUTS!$O$90="Even",1/TIMELINE!$C$51,IF(INPUTS!$O$90="Front-loaded",(TIMELINE!$C$51-TIMELINE!J52+1)*2/(TIMELINE!$C$51*(TIMELINE!$C$51+1)),IF(INPUTS!$O$90="Back-loaded",TIMELINE!J52*2/(TIMELINE!$C$51*(TIMELINE!$C$51+1)),IF(INPUTS!$O$90="S-curve",SIN(PI()*(TIMELINE!J52-0.5)/TIMELINE!$C$51)*SIN(PI()/(2*TIMELINE!$C$51)),0)))))),0) -> 0.049950211 | K52: =IF(INPUTS!$E$90="Yes",IF(OR(TIMELINE!K52=0,TIMELINE!$C$51=0),0,IF(INPUTS!$O$90="Upfront",--(TIMELINE!K52=1),IF(INPUTS!$O$90="Even",1/TIMELINE!$C$51,IF(INPUTS!$O$90="Front-loaded",(TIMELINE!$C$51-TIMELINE!K52+1)*2/(TIMELINE!$C$51*(TIMELINE!$C$51+1)),IF(INPUTS!$O$90="Back-loaded",TIMELINE!K52*2/(TIMELINE!$C$51*(TIMELINE!$C$51+1)),IF(INPUTS!$O$90="S-curve",SIN(PI()*(TIMELINE!K52-0.5)/TIMELINE!$C$51)*SIN(PI()/(2*TIMELINE!$C$51)),0)))))),0) -> 0.079459311 | ... AQ52: =IF(INPUTS!$E$90="Yes",IF(OR(TIMELINE!AQ52=0,TIMELINE!$C$51=0),0,IF(INPUTS!$O$90="Upfront",--(TIMELINE!AQ52=1),IF(INPUTS!$O$90="Even",1/TIMELINE!$C$51,IF(INPUTS!$O$90="Front-loaded",(TIMELINE!$C$51-TIMELINE!AQ52+1)*2/(TIMELINE!$C$51*(TIMELINE!$C$51+1)),IF(INPUTS!$O$90="Back-loaded",TIMELINE!AQ52*2/(TIMELINE!$C$51*(TIMELINE!$C$51+1)),IF(INPUTS!$O$90="S-curve",SIN(PI()*(TIMELINE!AQ52-0.5)/TIMELINE!$C$51)*SIN(PI()/(2*TIMELINE!$C$51)),0)))))),0) -> 0
B53: Construction % – cumulative (drives CLP in Step 4) | D53: =SUM($D52:D52) -> 0 | E53: =SUM($D52:E52) -> 0 | F53: =SUM($D52:F52) -> 0 | G53: =SUM($D52:G52) -> 0 | H53: =SUM($D52:H52) -> 0 | I53: =SUM($D52:I52) -> 0.017037087 | J53: =SUM($D52:J52) -> 0.066987298 | K53: =SUM($D52:K52) -> 0.14644661 | ... AQ53: =SUM($D52:AQ52) -> 1
B54: Check (each must total 100%) | C54: =IF(NOT(INPUTS!$E$90="Yes"),"Off",IF(AND(ABS(C50-1)<0.000000001,ABS(C52-1)<0.000000001,ABS(AQ53-1)<0.000000001),"OK","ERROR")) -> OK
B55: =IF(INPUTS!$E$91="Yes",INPUTS!$B$91,"Product row 4 (off)") -> High-street retail
